Workbook

Sheet All_India_Index_Upto_April23 (1
A1: Sector | B1: Year | C1: Month | D1: Cereals and products | E1: Meat and fish | F1: Egg | G1: Milk and products | H1: Oils and fats | I1: Fruits | J1: Vegetables | K1: Pulses and products | L1: Sugar and Confectionery | M1: Spices | N1: Non-alcoholic beverages | O1: Prepared meals, snacks, sweets etc. | P1: Food and beverages | Q1: Pan, tobacco and intoxicants | R1: Clothing | S1: Footwear | T1: Clothing and footwear | U1: Housing | V1: Fuel and light | W1: Household goods and services | X1: Health | Y1: Transport and communication | Z1: Recreation and amusement | AA1: Education | AB1: Personal care and effects | AC1: Miscellaneous | AD1: General index
A2: Rural | B2: 2013 | C2: January | D2: 107.5 | E2: 106.3 | F2: 108.1 | G2: 104.9 | H2: 106.1 | I2: 103.9 | J2: 101.9 | K2: 106.1 | L2: 106.8 | M2: 103.1 | N2: 104.8 | O2: 106.7 | P2: 105.5 | Q2: 105.1 | R2: 106.5 | S2: 105.8 | T2: 106.4 | U2: NA | V2: 105.5 | W2: 104.8 | X2: 104 | Y2: 103.3 | Z2: 103.4 | AA2: 103.8 | AB2: 104.7 | AC2: 104 | AD2: 105.1
A3: Urban | B3: 2013 | C3: January | D3: 110.5 | E3: 109.1 | F3: 113 | G3: 103.6 | H3: 103.4 | I3: 102.3 | J3: 102.9 | K3: 105.8 | L3: 105.1 | M3: 101.8 | N3: 105.1 | O3: 107.9 | P3: 105.9 | Q3: 105.2 | R3: 105.9 | S3: 105 | T3: 105.8 | U3: 100.3 | V3: 105.4 | W3: 104.8 | X3: 104.1 | Y3: 103.2 | Z3: 102.9 | AA3: 103.5 | AB3: 104.3 | AC3: 103.7 | AD3: 104
A4: Rural+Urban | B4: 2013 | C4: January | D4: 108.4 | E4: 107.3 | F4: 110 | G4: 104.4 | H4: 105.1 | I4: 103.2 | J4: 102.2 | K4: 106 | L4: 106.2 | M4: 102.7 | N4: 104.9 | O4: 107.3 | P4: 105.6 | Q4: 105.1 | R4: 106.3 | S4: 105.5 | T4: 106.2 | U4: 100.3 | V4: 105.5 | W4: 104.8 | X4: 104 | Y4: 103.2 | Z4: 103.1 | AA4: 103.6 | AB4: 104.5 | AC4: 103.9 | AD4: 104.6
A5: Rural | B5: 2013 | C5: February | D5: 109.2 | E5: 108.7 | F5: 110.2 | G5: 105.4 | H5: 106.7 | I5: 104 | J5: 102.4 | K5: 105.9 | L5: 105.7 | M5: 103.1 | N5: 105.1 | O5: 107.7 | P5: 106.3 | Q5: 105.6 | R5: 107.1 | S5: 106.3 | T5: 107 | U5: NA | V5: 106.2 | W5: 105.2 | X5: 104.4 | Y5: 103.9 | Z5: 104 | AA5: 104.1 | AB5: 104.6 | AC5: 104.4 | AD5: 105.8
A6: Urban | B6: 2013 | C6: February | D6: 112.9 | E6: 112.9 | F6: 116.9 | G6: 104 | H6: 103.5 | I6: 103.1 | J6: 104.9 | K6: 104.1 | L6: 103.8 | M6: 102.3 | N6: 106 | O6: 109 | P6: 107.2 | Q6: 106 | R6: 106.6 | S6: 105.5 | T6: 106.4 | U6: 100.4 | V6: 105.7 | W6: 105.2 | X6: 104.7 | Y6: 104.4 | Z6: 103.3 | AA6: 103.7 | AB6: 104.3 | AC6: 104.3 | AD6: 104.7
A7: Rural+Urban | B7: 2013 | C7: February | D7: 110.4 | E7: 110.2 | F7: 112.8 | G7: 104.9 | H7: 105.5 | I7: 103.6 | J7: 103.2 | K7: 105.3 | L7: 105.1 | M7: 102.8 | N7: 105.5 | O7: 108.3 | P7: 106.6 | Q7: 105.7 | R7: 106.9 | S7: 106 | T7: 106.8 | U7: 100.4 | V7: 106 | W7: 105.2 | X7: 104.5 | Y7: 104.2 | Z7: 103.6 | AA7: 103.9 | AB7: 104.5 | AC7: 104.4 | AD7: 105.3
A8: Rural | B8: 2013 | C8: March | D8: 110.2 | E8: 108.8 | F8: 109.9 | G8: 105.6 | H8: 106.2 | I8: 105.7 | J8: 101.4 | K8: 105.7 | L8: 105 | M8: 103.3 | N8: 105.6 | O8: 108.2 | P8: 106.6 | Q8: 106.5 | R8: 107.6 | S8: 106.8 | T8: 107.5 | U8: NA | V8: 106.1 | W8: 105.6 | X8: 104.7 | Y8: 104.6 | Z8: 104 | AA8: 104.3 | AB8: 104.3 | AC8: 104.6 | AD8: 106
A9: Urban | B9: 2013 | C9: March | D9: 113.9 | E9: 111.4 | F9: 113.2 | G9: 104.3 | H9: 102.7 | I9: 104.9 | J9: 103.8 | K9: 103.5 | L9: 102.6 | M9: 102.4 | N9: 107 | O9: 109.8 | P9: 107.3 | Q9: 106.8 | R9: 107.2 | S9: 106 | T9: 107 | U9: 100.4 | V9: 106 | W9: 105.7 | X9: 105.2 | Y9: 105.5 | Z9: 103.5 | AA9: 103.8 | AB9: 104.2 | AC9: 104.9 | AD9: 105
A10: Rural+Urban | B10: 2013 | C10: March | D10: 111.4 | E10: 109.7 | F10: 111.2 | G10: 105.1 | H10: 104.9 | I10: 105.3 | J10: 102.2 | K10: 105 | L10: 104.2 | M10: 103 | N10: 106.2 | O10: 108.9 | P10: 106.9 | Q10: 106.6 | R10: 107.4 | S10: 106.5 | T10: 107.3 | U10: 100.4 | V10: 106.1 | W10: 105.6 | X10: 104.9 | Y10: 105.1 | Z10: 103.7 | AA10: 104 | AB10: 104.3 | AC10: 104.7 | AD10: 105.5
A11: Rural | B11: 2013 | C11: April | D11: 110.2 | E11: 109.5 | F11: 106.9 | G11: 106.3 | H11: 105.7 | I11: 108.3 | J11: 103.4 | K11: 105.7 | L11: 104.2 | M11: 103.2 | N11: 106.5 | O11: 108.8 | P11: 107.1 | Q11: 107.1 | R11: 108.1 | S11: 107.4 | T11: 108 | U11: NA | V11: 106.5 | W11: 106.1 | X11: 105.1 | Y11: 104.4 | Z11: 104.5 | AA11: 104.8 | AB11: 102.7 | AC11: 104.6 | AD11: 106.4
A12: Urban | B12: 2013 | C12: April | D12: 114.6 | E12: 113.4 | F12: 106 | G12: 104.7 | H12: 102.1 | I12: 109.5 | J12: 109.7 | K12: 104.6 | L12: 102 | M12: 103.5 | N12: 108.2 | O12: 110.6 | P12: 108.8 | Q12: 108.5 | R12: 107.9 | S12: 106.4 | T12: 107.7 | U12: 100.5 | V12: 106.4 | W12: 106.5 | X12: 105.7 | Y12: 105 | Z12: 104 | AA12: 105.2 | AB12: 103.2 | AC12: 105.1 | AD12: 105.7
A13: Rural+Urban | B13: 2013 | C13: April | D13: 111.6 | E13: 110.9 | F13: 106.6 | G13: 105.7 | H13: 104.4 | I13: 108.9 | J13: 105.5 | K13: 105.3 | L13: 103.5 | M13: 103.3 | N13: 107.2 | O13: 109.6 | P13: 107.7 | Q13: 107.5 | R13: 108 | S13: 107 | T13: 107.9 | U13: 100.5 | V13: 106.5 | W13: 106.3 | X13: 105.3 | Y13: 104.7 | Z13: 104.2 | AA13: 105 | AB13: 102.9 | AC13: 104.8 | AD13: 106.1
A14: Rural | B14: 2013 | C14: May | D14: 110.9 | E14: 109.8 | F14: 105.9 | G14: 107.5 | H14: 105.3 | I14: 108.1 | J14: 107.3 | K14: 106.1 | L14: 103.7 | M14: 104 | N14: 107.4 | O14: 109.9 | P14: 108.1 | Q14: 108.1 | R14: 108.8 | S14: 107.9 | T14: 108.6 | U14: NA | V14: 107.5 | W14: 106.8 | X14: 105.7 | Y14: 104.1 | Z14: 105 | AA14: 105.5 | AB14: 102.1 | AC14: 104.8 | AD14: 107.2
A15: Urban | B15: 2013 | C15: May | D15: 115.4 | E15: 114.2 | F15: 102.7 | G15: 105.5 | H15: 101.5 | I15: 110.6 | J15: 123.7 | K15: 105.2 | L15: 101.9 | M15: 105 | N15: 109.1 | O15: 111.3 | P15: 111.1 | Q15: 109.8 | R15: 108.5 | S15: 106.7 | T15: 108.3 | U15: 100.5 | V15: 107.2 | W15: 107.1 | X15: 106.2 | Y15: 103.9 | Z15: 104.6 | AA15: 105.7 | AB15: 102.6 | AC15: 104.9 | AD15: 106.6
A16: Rural+Urban | B16: 2013 | C16: May | D16: 112.3 | E16: 111.3 | F16: 104.7 | G16: 106.8 | H16: 103.9 | I16: 109.3 | J16: 112.9 | K16: 105.8 | L16: 103.1 | M16: 104.3 | N16: 108.1 | O16: 110.5 | P16: 109.2 | Q16: 108.6 | R16: 108.7 | S16: 107.4 | T16: 108.5 | U16: 100.5 | V16: 107.4 | W16: 106.9 | X16: 105.9 | Y16: 104 | Z16: 104.8 | AA16: 105.6 | AB16: 102.3 | AC16: 104.8 | AD16: 106.9
A17: Rural | B17: 2013 | C17: June | D17: 112.3 | E17: 112.1 | F17: 108.1 | G17: 108.3 | H17: 105.9 | I17: 109.2 | J17: 118 | K17: 106.8 | L17: 104.1 | M17: 105.4 | N17: 108.2 | O17: 111 | P17: 110.6 | Q17: 109 | R17: 109.7 | S17: 108.8 | T17: 109.5 | U17: NA | V17: 108.5 | W17: 107.5 | X17: 106.3 | Y17: 105 | Z17: 105.6 | AA17: 106.5 | AB17: 102.5 | AC17: 105.5 | AD17: 108.9
A18: Urban | B18: 2013 | C18: June | D18: 117 | E18: 120.1 | F18: 112.5 | G18: 107.3 | H18: 101.3 | I18: 112.4 | J18: 143.6 | K18: 105.4 | L18: 101.4 | M18: 106.4 | N18: 110 | O18: 112.2 | P18: 115 | Q18: 110.9 | R18: 109.2 | S18: 107.2 | T18: 108.9 | U18: 106.6 | V18: 108 | W18: 107.7 | X18: 106.5 | Y18: 105.2 | Z18: 105.2 | AA18: 108.1 | AB18: 103.3 | AC18: 106.1 | AD18: 109.7
A19: Rural+Urban | B19: 2013 | C19: June | D19: 113.8 | E19: 114.9 | F19: 109.8 | G19: 107.9 | H19: 104.2 | I19: 110.7 | J19: 126.7 | K19: 106.3 | L19: 103.2 | M19: 105.7 | N19: 109 | O19: 111.6 | P19: 112.2 | Q19: 109.5 | R19: 109.5 | S19: 108.1 | T19: 109.3 | U19: 106.6 | V19: 108.3 | W19: 107.6 | X19: 106.4 | Y19: 105.1 | Z19: 105.4 | AA19: 107.4 | AB19: 102.8 | AC19: 105.8 | AD19: 109.3
A20: Rural | B20: 2013 | C20: July | D20: 113.4 | E20: 114.9 | F20: 110.5 | G20: 109.3 | H20: 106.2 | I20: 110.3 | J20: 129.2 | K20: 107.1 | L20: 104.3 | M20: 106.4 | N20: 109.1 | O20: 112.1 | P20: 113.1 | Q20: 109.8 | R20: 110.5 | S20: 109.5 | T20: 110.3 | U20: NA | V20: 109.5 | W20: 108.3 | X20: 106.9 | Y20: 106.8 | Z20: 106.4 | AA20: 107.8 | AB20: 102.5 | AC20: 106.5 | AD20: 110.7
A21: Urban | B21: 2013 | C21: July | D21: 117.8 | E21: 119.2 | F21: 114 | G21: 108.3 | H21: 101.1 | I21: 113.2 | J21: 160.9 | K21: 105.1 | L21: 101.3 | M21: 107.5 | N21: 110.4 | O21: 113.1 | P21: 117.5 | Q21: 111.7 | R21: 109.8 | S21: 107.8 | T21: 109.5 | U21: 107.7 | V21: 108.6 | W21: 108.1 | X21: 107.1 | Y21: 107.3 | Z21: 105.9 | AA21: 110.1 | AB21: 103.2 | AC21: 107.3 | AD21: 111.4
A22: Rural+Urban | B22: 2013 | C22: July | D22: 114.8 | E22: 116.4 | F22: 111.9 | G22: 108.9 | H22: 104.3 | I22: 111.7 | J22: 140 | K22: 106.4 | L22: 103.3 | M22: 106.8 | N22: 109.6 | O22: 112.6 | P22: 114.7 | Q22: 110.3 | R22: 110.2 | S22: 108.8 | T22: 110 | U22: 107.7 | V22: 109.2 | W22: 108.2 | X22: 107 | Y22: 107.1 | Z22: 106.1 | AA22: 109.1 | AB22: 102.8 | AC22: 106.9 | AD22: 111
A23: Rural | B23: 2013 | C23: August | D23: 114.3 | E23: 115.4 | F23: 111.1 | G23: 110 | H23: 106.4 | I23: 110.8 | J23: 138.9 | K23: 107.4 | L23: 104.1 | M23: 106.9 | N23: 109.7 | O23: 112.6 | P23: 114.9 | Q23: 110.7 | R23: 111.3 | S23: 110.2 | T23: 111.1 | U23: NA | V23: 109.9 | W23: 108.7 | X23: 107.5 | Y23: 107.8 | Z23: 106.8 | AA23: 108.7 | AB23: 105 | AC23: 107.5 | AD23: 112.1
A24: Urban | B24: 2013 | C24: August | D24: 118.3 | E24: 120.4 | F24: 112.7 | G24: 108.9 | H24: 101.1 | I24: 108.7 | J24: 177 | K24: 104.7 | L24: 101 | M24: 108.5 | N24: 110.9 | O24: 114.3 | P24: 119.6 | Q24: 112.4 | R24: 110.6 | S24: 108.3 | T24: 110.2 | U24: 108.9 | V24: 109.3 | W24: 108.7 | X24: 107.6 | Y24: 108.1 | Z24: 106.5 | AA24: 110.8 | AB24: 106 | AC24: 108.3 | AD24: 112.7
A25: Rural+Urban | B25: 2013 | C25: August | D25: 115.6 | E25: 117.2 | F25: 111.7 | G25: 109.6 | H25: 104.5 | I25: 109.8 | J25: 151.8 | K25: 106.5 | L25: 103.1 | M25: 107.4 | N25: 110.2 | O25: 113.4 | P25: 116.6 | Q25: 111.2 | R25: 111 | S25: 109.4 | T25: 110.7 | U25: 108.9 | V25: 109.7 | W25: 108.7 | X25: 107.5 | Y25: 108 | Z25: 106.6 | AA25: 109.9 | AB25: 105.4 | AC25: 107.9 | AD25: 112.4
A26: Rural | B26: 2013 | C26: September | D26: 115.4 | E26: 115.7 | F26: 111.7 | G26: 111 | H26: 107.4 | I26: 110.9 | J26: 154 | K26: 108.1 | L26: 104.2 | M26: 107.9 | N26: 110.4 | O26: 114 | P26: 117.8 | Q26: 111.7 | R26: 112.7 | S26: 111.4 | T26: 112.5 | U26: NA | V26: 111.1 | W26: 109.6 | X26: 108.3 | Y26: 109.3 | Z26: 107.7 | AA26: 109.8 | AB26: 106.7 | AC26: 108.7 | AD26: 114.2
A27: Urban | B27: 2013 | C27: September | D27: 118.6 | E27: 119.1 | F27: 113.2 | G27: 109.6 | H27: 101.7 | I27: 103.2 | J27: 174.3 | K27: 105.1 | L27: 100.8 | M27: 109.1 | N27: 111.1 | O27: 115.4 | P27: 119.2 | Q27: 112.9 | R27: 111.4 | S27: 109 | T27: 111.1 | U27: 109.7 | V27: 109.5 | W27: 109.6 | X27: 107.9 | Y27: 110.4 | Z27: 107.4 | AA27: 111.2 | AB27: 106.9 | AC27: 109.4 | AD27: 113.2
A28: Rural+Urban | B28: 2013 | C28: September | D28: 116.4 | E28: 116.9 | F28: 112.3 | G28: 110.5 | H28: 105.3 | I28: 107.3 | J28: 160.9 | K28: 107.1 | L28: 103.1 | M28: 108.3 | N28: 110.7 | O28: 114.6 | P28: 118.3 | Q28: 112 | R28: 112.2 | S28: 110.4 | T28: 111.9 | U28: 109.7 | V28: 110.5 | W28: 109.6 | X28: 108.1 | Y28: 109.9 | Z28: 107.5 | AA28: 110.6 | AB28: 106.8 | AC28: 109 | AD28: 113.7
A29: Rural | B29: 2013 | C29: October | D29: 116.3 | E29: 115.4 | F29: 112.6 | G29: 111.7 | H29: 107.7 | I29: 113.2 | J29: 164.9 | K29: 108.3 | L29: 103.9 | M29: 108.2 | N29: 111.1 | O29: 114.9 | P29: 119.8 | Q29: 112.2 | R29: 113.6 | S29: 112.3 | T29: 113.4 | U29: NA | V29: 111.6 | W29: 110.4 | X29: 108.9 | Y29: 109.3 | Z29: 108.3 | AA29: 110.2 | AB29: 107.5 | AC29: 109.1 | AD29: 115.5
A30: Urban | B30: 2013 | C30: October | D30: 118.9 | E30: 118.1 | F30: 114.5 | G30: 110.4 | H30: 102.3 | I30: 106.2 | J30: 183.5 | K30: 105.3 | L30: 100.2 | M30: 109.6 | N30: 111.4 | O30: 116 | P30: 120.8 | Q30: 113.5 | R30: 112.5 | S30: 109.7 | T30: 112 | U30: 110.5 | V30: 109.7 | W30: 110.2 | X30: 108.2 | Y30: 109.7 | Z30: 108 | AA30: 111.3 | AB30: 107.3 | AC30: 109.4 | AD30: 114
A31: Rural+Urban | B31: 2013 | C31: October | D31: 117.1 | E31: 116.3 | F31: 113.3 | G31: 111.2 | H31: 105.7 | I31: 109.9 | J31: 171.2 | K31: 107.3 | L31: 102.7 | M31: 108.7 | N31: 111.2 | O31: 115.4 | P31: 120.2 | Q31: 112.5 | R31: 113.2 | S31: 111.2 | T31: 112.8 | U31: 110.5 | V31: 110.9 | W31: 110.3 | X31: 108.6 | Y31: 109.5 | Z31: 108.1 | AA31: 110.8 | AB31: 107.4 | AC31: 109.2 | AD31: 114.8
A32: Rural | B32: 2013 | C32: November | D32: 117.3 | E32: 114.9 | F32: 116.2 | G32: 112.8 | H32: 108.9 | I32: 116.6 | J32: 178.1 | K32: 109.1 | L32: 103.6 | M32: 109 | N32: 111.8 | O32: 116 | P32: 122.5 | Q32: 112.8 | R32: 114.6 | S32: 113.1 | T32: 114.4 | U32: NA | V32: 112.6 | W32: 111.3 | X32: 109.7 | Y32: 109.6 | Z32: 108.7 | AA32: 111 | AB32: 108.2 | AC32: 109.8 | AD32: 117.4
A33: Urban | B33: 2013 | C33: November | D33: 119.8 | E33: 116.3 | F33: 122.6 | G33: 112 | H33: 103.2 | I33: 110 | J33: 192.8 | K33: 106.3 | L33: 99.5 | M33: 110.3 | N33: 111.8 | O33: 117.1 | P33: 122.9 | Q33: 114.1 | R33: 113.5 | S33: 110.3 | T33: 113 | U33: 111.1 | V33: 110 | W33: 110.9 | X33: 108.6 | Y33: 109.5 | Z33: 108.5 | AA33: 111.3 | AB33: 107.9 | AC33: 109.6 | AD33: 115
A34: Rural+Urban | B34: 2013 | C34: November | D34: 118.1 | E34: 115.4 | F34: 118.7 | G34: 112.5 | H34: 106.8 | I34: 113.5 | J34: 183.1 | K34: 108.2 | L34: 102.2 | M34: 109.4 | N34: 111.8 | O34: 116.5 | P34: 122.6 | Q34: 113.1 | R34: 114.2 | S34: 111.9 | T34: 113.8 | U34: 111.1 | V34: 111.6 | W34: 111.1 | X34: 109.3 | Y34: 109.5 | Z34: 108.6 | AA34: 111.2 | AB34: 108.1 | AC34: 109.7 | AD34: 116.3
A35: Rural | B35: 2013 | C35: December | D35: 118.4 | E35: 115.9 | F35: 120.4 | G35: 113.8 | H35: 109.5 | I35: 115.5 | J35: 145.7 | K35: 109.5 | L35: 102.9 | M35: 109.8 | N35: 112.1 | O35: 116.8 | P35: 118.7 | Q35: 113.6 | R35: 115.8 | S35: 114 | T35: 115.5 | U35: NA | V35: 112.8 | W35: 112.1 | X35: 110.1 | Y35: 109.9 | Z35: 109.2 | AA35: 111.6 | AB35: 108.1 | AC35: 110.1 | AD35: 115.5
A36: Urban | B36: 2013 | C36: December | D36: 120.5 | E36: 118.1 | F36: 128.5 | G36: 112.8 | H36: 103.4 | I36: 110.7 | J36: 144.8 | K36: 107.1 | L36: 98.6 | M36: 111.9 | N36: 112.1 | O36: 118.1 | P36: 117.8 | Q36: 115 | R36: 114.2 | S36: 110.9 | T36: 113.7 | U36: 110.7 | V36: 110.4 | W36: 111.3 | X36: 109 | Y36: 109.7 | Z36: 108.9 | AA36: 111.4 | AB36: 107.7 | AC36: 109.8 | AD36: 113.3
A37: Rural+Urban | B37: 2013 | C37: December | D37: 119.1 | E37: 116.7 | F37: 123.5 | G37: 113.4 | H37: 107.3 | I37: 113.3 | J37: 145.4 | K37: 108.7 | L37: 101.5 | M37: 110.5 | N37: 112.1 | O37: 117.4 | P37: 118.4 | Q37: 114 | R37: 115.2 | S37: 112.7 | T37: 114.8 | U37: 110.7 | V37: 111.9 | W37: 111.7 | X37: 109.7 | Y37: 109.8 | Z37: 109 | AA37: 111.5 | AB37: 107.9 | AC37: 110 | AD37: 114.5
A38: Rural | B38: 2014 | C38: January | D38: 118.9 | E38: 117.1 | F38: 120.5 | G38: 114.4 | H38: 109 | I38: 115.5 | J38: 123.9 | K38: 109.6 | L38: 101.8 | M38: 110.2 | N38: 112.4 | O38: 117.3 | P38: 116 | Q38: 114 | R38: 116.5 | S38: 114.5 | T38: 116.2 | U38: NA | V38: 113 | W38: 112.6 | X38: 110.6 | Y38: 110.5 | Z38: 109.6 | AA38: 111.8 | AB38: 108.3 | AC38: 110.6 | AD38: 114.2
A39: Urban | B39: 2014 | C39: January | D39: 121.2 | E39: 122 | F39: 129.9 | G39: 113.6 | H39: 102.9 | I39: 112.1 | J39: 118.9 | K39: 107.5 | L39: 96.9 | M39: 112.7 | N39: 112.1 | O39: 119 | P39: 115.5 | Q39: 115.7 | R39: 114.8 | S39: 111.3 | T39: 114.3 | U39: 111.6 | V39: 111 | W39: 111.9 | X39: 109.7 | Y39: 110.8 | Z39: 109.8 | AA39: 111.5 | AB39: 108 | AC39: 110.5 | AD39: 112.9
A40: Rural+Urban | B40: 2014 | C40: January | D40: 119.6 | E40: 118.8 | F40: 124.1 | G40: 114.1 | H40: 106.8 | I40: 113.9 | J40: 122.2 | K40: 108.9 | L40: 100.2 | M40: 111 | N40: 112.3 | O40: 118.1 | P40: 115.8 | Q40: 114.5 | R40: 115.8 | S40: 113.2 | T40: 115.4 | U40: 111.6 | V40: 112.2 | W40: 112.3 | X40: 110.3 | Y40: 110.7 | Z40: 109.7 | AA40: 111.6 | AB40: 108.2 | AC40: 110.6 | AD40: 113.6
A41: Rural | B41: 2014 | C41: February | D41: 119.4 | E41: 117.7 | F41: 121.2 | G41: 115 | H41: 109 | I41: 116.6 | J41: 116 | K41: 109.8 | L41: 101.1 | M41: 110.4 | N41: 112.9 | O41: 117.8 | P41: 115.3 | Q41: 114.2 | R41: 117.1 | S41: 114.5 | T41: 116.7 | U41: NA | V41: 113.2 | W41: 112.9 | X41: 110.9 | Y41: 110.8 | Z41: 109.9 | AA41: 112 | AB41: 108.7 | AC41: 110.9 | AD41: 114
A42: Urban | B42: 2014 | C42: February | D42: 121.9 | E42: 122 | F42: 124.5 | G42: 115.2 | H42: 102.5 | I42: 114.1 | J42: 111.5 | K42: 108.2 | L42: 95.4 | M42: 113.5 | N42: 112.1 | O42: 119.9 | P42: 115.2 | Q42: 116.2 | R42: 115.3 | S42: 111.7 | T42: 114.7 | U42: 112.5 | V42: 111.1 | W42: 112.6 | X42: 110.4 | Y42: 111.3 | Z42: 110.3 | AA42: 111.6 | AB42: 108.7 | AC42: 111 | AD42: 113.1
A43: Rural+Urban | B43: 2014 | C43: February | D43: 120.2 | E43: 119.2 | F43: 122.5 | G43: 115.1 | H43: 106.6 | I43: 115.4 | J43: 114.5 | K43: 109.3 | L43: 99.2 | M43: 111.4 | N43: 112.6 | O43: 118.8 | P43: 115.3 | Q43: 114.7 | R43: 116.4 | S43: 113.3 | T43: 115.9 | U43: 112.5 | V43: 112.4 | W43: 112.8 | X43: 110.7 | Y43: 111.1 | Z43: 110.1 | AA43: 111.8 | AB43: 108.7 | AC43: 110.9 | AD43: 113.6
A44: Rural | B44: 2014 | C44: March | D44: 120.1 | E44: 118.1 | F44: 120.7 | G44: 116.1 | H44: 109.3 | I44: 119.6 | J44: 117.9 | K44: 110.2 | L44: 101.2 | M44: 110.7 | N44: 113 | O44: 118.3 | P44: 116.2 | Q44: 114.6 | R44: 117.5 | S44: 114.9 | T44: 117.2 | U44: NA | V44: 113.4 | W44: 113.4 | X44: 111.4 | Y44: 111.2 | Z44: 110.2 | AA44: 112.4 | AB44: 108.9 | AC44: 111.3 | AD44: 114.6
A45: Urban | B45: 2014 | C45: March | D45: 122.1 | E45: 121.4 | F45: 121.5 | G45: 116.2 | H45: 102.8 | I45: 117.7 | J45: 113.3 | K45: 108.9 | L45: 96.3 | M45: 114.1 | N45: 112.2 | O45: 120.5 | P45: 116 | Q45: 116.7 | R45: 115.8 | S45: 112.1 | T45: 115.2 | U45: 113.2 | V45: 110.9 | W45: 113 | X45: 110.8 | Y45: 111.6 | Z45: 110.9 | AA45: 111.8 | AB45: 109.2 | AC45: 111.4 | AD45: 113.7
A46: Rural+Urban | B46: 2014 | C46: Marcrh | D46: 120.7 | E46: 119.3 | F46: 121 | G46: 116.1 | H46: 106.9 | I46: 118.7 | J46: 116.3 | K46: 109.8 | L46: 99.6 | M46: 111.8 | N46: 112.7 | O46: 119.3 | P46: 116.1 | Q46: 115.2 | R46: 116.8 | S46: 113.7 | T46: 116.4 | U46: 113.2 | V46: 112.5 | W46: 113.2 | X46: 111.2 | Y46: 111.4 | Z46: 110.6 | AA46: 112 | AB46: 109 | AC46: 111.3 | AD46: 114.2
A47: Rural | B47: 2014 | C47: April | D47: 120.2 | E47: 118.9 | F47: 118.1 | G47: 117 | H47: 109.7 | I47: 125.5 | J47: 120.5 | K47: 111 | L47: 102.6 | M47: 111.2 | N47: 113.5 | O47: 118.7 | P47: 117.2 | Q47: 115.4 | R47: 118.1 | S47: 116.1 | T47: 117.8 | U47: NA | V47: 113.4 | W47: 113.7 | X47: 111.8 | Y47: 111.2 | Z47: 110.5 | AA47: 113 | AB47: 108.9 | AC47: 111.5 | AD47: 115.4
A48: Urban | B48: 2014 | C48: April | D48: 122.5 | E48: 121.7 | F48: 113.3 | G48: 117 | H48: 103.1 | I48: 126.7 | J48: 121.2 | K48: 111 | L48: 100.3 | M48: 115.3 | N48: 112.7 | O48: 121 | P48: 118.2 | Q48: 117.6 | R48: 116.3 | S48: 112.5 | T48: 115.7 | U48: 113.9 | V48: 110.9 | W48: 113.4 | X48: 111 | Y48: 111.2 | Z48: 111.2 | AA48: 112.5 | AB48: 109.1 | AC48: 111.4 | AD48: 114.7
A49: Rural+Urban | B49: 2014 | C49: April | D49: 120.9 | E49: 119.9 | F49: 116.2 | G49: 117 | H49: 107.3 | I49: 126.1 | J49: 120.7 | K49: 111 | L49: 101.8 | M49: 112.6 | N49: 113.2 | O49: 119.8 | P49: 117.6 | Q49: 116 | R49: 117.4 | S49: 114.6 | T49: 117 | U49: 113.9 | V49: 112.5 | W49: 113.6 | X49: 111.5 | Y49: 111.2 | Z49: 110.9 | AA49: 112.7 | AB49: 109 | AC49: 111.5 | AD49: 115.1
A50: Rural | B50: 2014 | C50: May | D50: 120.3 | E50: 120.2 | F50: 116.9 | G50: 118 | H50: 110.1 | I50: 126.3 | J50: 123.9 | K50: 111.5 | L50: 103.5 | M50: 111.6 | N50: 114.2 | O50: 119.2 | P50: 118.2 | Q50: 116.3 | R50: 118.7 | S50: 116.8 | T50: 118.5 | U50: NA | V50: 113.4 | W50: 114.1 | X50: 112.1 | Y50: 111.4 | Z50: 110.9 | AA50: 113.1 | AB50: 108.9 | AC50: 111.8 | AD50: 116
A51: Urban | B51: 2014 | C51: May | D51: 122.7 | E51: 124.1 | F51: 114.2 | G51: 119.1 | H51: 103.5 | I51: 129.2 | J51: 127 | K51: 112.6 | L51: 101.3 | M51: 117 | N51: 112.9 | O51: 121.7 | P51: 120 | Q51: 118.3 | R51: 116.8 | S51: 112.9 | T51: 116.2 | U51: 114.3 | V51: 111.1 | W51: 114.1 | X51: 111.2 | Y51: 111.3 | Z51: 111.5 | AA51: 112.9 | AB51: 109.3 | AC51: 111.7 | AD51: 115.6
A52: Rural+Urban | B52: 2014 | C52: May | D52: 121.1 | E52: 121.6 | F52: 115.9 | G52: 118.4 | H52: 107.7 | I52: 127.7 | J52: 125 | K52: 111.9 | L52: 102.8 | M52: 113.4 | N52: 113.7 | O52: 120.4 | P52: 118.9 | Q52: 116.8 | R52: 118 | S52: 115.2 | T52: 117.6 | U52: 114.3 | V52: 112.5 | W52: 114.1 | X52: 111.8 | Y52: 111.3 | Z52: 111.2 | AA52: 113 | AB52: 109.1 | AC52: 111.8 | AD52: 115.8
A53: Rural | B53: 2014 | C53: June | D53: 120.7 | E53: 121.6 | F53: 116.1 | G53: 119.3 | H53: 110.3 | I53: 125.8 | J53: 129.3 | K53: 112.2 | L53: 103.6 | M53: 112.3 | N53: 114.9 | O53: 120.1 | P53: 119.5 | Q53: 117.3 | R53: 119.7 | S53: 117.3 | T53: 119.3 | U53: NA | V53: 114.4 | W53: 114.9 | X53: 112.8 | Y53: 112.2 | Z53: 111.4 | AA53: 114.3 | AB53: 108 | AC53: 112.3 | AD53: 117
A54: Urban | B54: 2014 | C54: June | D54: 123.1 | E54: 125.9 | F54: 115.4 | G54: 120.4 | H54: 103.4 | I54: 131.2 | J54: 137.5 | K54: 112.8 | L54: 101.4 | M54: 118.3 | N54: 113.2 | O54: 122.4 | P54: 122 | Q54: 119 | R54: 117.4 | S54: 113.2 | T54: 116.7 | U54: 113.9 | V54: 111.2 | W54: 114.3 | X54: 111.4 | Y54: 111.5 | Z54: 111.8 | AA54: 115.1 | AB54: 108.7 | AC54: 112.2 | AD54: 116.4
A55: Rural+Urban | B55: 2014 | C55: June | D55: 121.5 | E55: 123.1 | F55: 115.8 | G55: 119.7 | H55: 107.8 | I55: 128.3 | J55: 132.1 | K55: 112.4 | L55: 102.9 | M55: 114.3 | N55: 114.2 | O55: 121.2 | P55: 120.4 | Q55: 117.8 | R55: 118.8 | S55: 115.6 | T55: 118.3 | U55: 113.9 | V55: 113.2 | W55: 114.6 | X55: 112.3 | Y55: 111.8 | Z55: 111.6 | AA55: 114.8 | AB55: 108.3 | AC55: 112.3 | AD55: 116.7
A56: Rural | B56: 2014 | C56: July | D56: 121.7 | E56: 122.5 | F56: 117.7 | G56: 120.6 | H56: 110.4 | I56: 129.1 | J56: 150.1 | K56: 113.2 | L56: 104.8 | M56: 113.3 | N56: 115.6 | O56: 120.9 | P56: 123.3 | Q56: 118 | R56: 120.7 | S56: 118.3 | T56: 120.3 | U56: NA | V56: 115.3 | W56: 115.4 | X56: 113.4 | Y56: 113.2 | Z56: 111.8 | AA56: 115.5 | AB56: 108.8 | AC56: 113.1 | AD56: 119.5
A57: Urban | B57: 2014 | C57: July | D57: 123.8 | E57: 126.4 | F57: 118 | G57: 121.6 | H57: 103.5 | I57: 133.7 | J57: 172.4 | K57: 113.1 | L57: 102.7 | M57: 120 | N57: 113.8 | O57: 123.4 | P57: 127.1 | Q57: 121 | R57: 118 | S57: 113.6 | T57: 117.4 | U57: 114.8 | V57: 111.6 | W57: 114.9 | X57: 111.5 | Y57: 113 | Z57: 112.4 | AA57: 117.8 | AB57: 109.7 | AC57: 113.5 | AD57: 118.9
A58: Rural+Urban | B58: 2014 | C58: July | D58: 122.4 | E58: 123.9 | F58: 117.8 | G58: 121 | H58: 107.9 | I58: 131.2 | J58: 157.7 | K58: 113.2 | L58: 104.1 | M58: 115.5 | N58: 114.8 | O58: 122.1 | P58: 124.7 | Q58: 118.8 | R58: 119.6 | S58: 116.3 | T58: 119.1 | U58: 114.8 | V58: 113.9 | W58: 115.2 | X58: 112.7 | Y58: 113.1 | Z58: 112.1 | AA58: 116.8 | AB58: 109.2 | AC58: 113.3 | AD58: 119.2
A59: Rural | B59: 2014 | C59: August | D59: 121.8 | E59: 122.8 | F59: 117.8 | G59: 121.9 | H59: 110.6 | I59: 129.7 | J59: 161.1 | K59: 114.1 | L59: 105.1 | M59: 114.6 | N59: 115.8 | O59: 121.7 | P59: 125.3 | Q59: 118.8 | R59: 120.9 | S59: 118.8 | T59: 120.7 | U59: NA | V59: 115.4 | W59: 115.9 | X59: 114 | Y59: 113.2 | Z59: 112.2 | AA59: 116.2 | AB59: 109.4 | AC59: 113.5 | AD59: 120.7
A60: Urban | B60: 2014 | C60: August | D60: 124.8 | E60: 127.3 | F60: 116.5 | G60: 122.2 | H60: 103.6 | I60: 132.7 | J60: 181.9 | K60: 115.2 | L60: 102.7 | M60: 122.1 | N60: 114.4 | O60: 124.7 | P60: 128.9 | Q60: 123 | R60: 118.6 | S60: 114.1 | T60: 117.9 | U60: 115.5 | V60: 111.8 | W60: 115.3 | X60: 112.2 | Y60: 112.5 | Z60: 112.9 | AA60: 119.2 | AB60: 110.5 | AC60: 113.9 | AD60: 119.9
A61: Rural+Urban | B61: 2014 | C61: August | D61: 122.7 | E61: 124.4 | F61: 117.3 | G61: 122 | H61: 108 | I61: 131.1 | J61: 168.2 | K61: 114.5 | L61: 104.3 | M61: 117.1 | N61: 115.2 | O61: 123.1 | P61: 126.6 | Q61: 119.9 | R61: 120 | S61: 116.8 | T61: 119.6 | U61: 115.5 | V61: 114 | W61: 115.6 | X61: 113.3 | Y61: 112.8 | Z61: 112.6 | AA61: 118 | AB61: 109.9 | AC61: 113.7 | AD61: 120.3
A62: Rural | B62: 2014 | C62: September | D62: 122.3 | E62: 122.4 | F62: 117.8 | G62: 122.7 | H62: 110.4 | I62: 129.8 | J62: 158.8 | K62: 115 | L62: 104.7 | M62: 114.9 | N62: 116.5 | O62: 122.6 | P62: 125.3 | Q62: 119.5 | R62: 121.7 | S62: 119.2 | T62: 121.3 | U62: NA | V62: 115.8 | W62: 116.7 | X62: 114.5 | Y62: 112.8 | Z62: 112.6 | AA62: 116.6 | AB62: 109.1 | AC62: 113.7 | AD62: 120.9
A63: Urban | B63: 2014 | C63: September | D63: 124.2 | E63: 125.4 | F63: 116.4 | G63: 122.7 | H63: 103.5 | I63: 124.5 | J63: 168.6 | K63: 116.9 | L63: 101.9 | M63: 122.9 | N63: 114.8 | O63: 125.2 | P63: 126.7 | Q63: 124.3 | R63: 119.2 | S63: 114.5 | T63: 118.4 | U63: 116.1 | V63: 111.8 | W63: 115.5 | X63: 112.3 | Y63: 111.2 | Z63: 113.4 | AA63: 120 | AB63: 110 | AC63: 113.6 | AD63: 119.2
A64: Rural+Urban | B64: 2014 | C64: September | D64: 122.9 | E64: 123.5 | F64: 117.3 | G64: 122.7 | H64: 107.9 | I64: 127.3 | J64: 162.1 | K64: 115.6 | L64: 103.8 | M64: 117.6 | N64: 115.8 | O64: 123.8 | P64: 125.8 | Q64: 120.8 | R64: 120.7 | S64: 117.2 | T64: 120.1 | U64: 116.1 | V64: 114.3 | W64: 116.1 | X64: 113.7 | Y64: 112 | Z64: 113.1 | AA64: 118.6 | AB64: 109.5 | AC64: 113.7 | AD64: 120.1
A65: Rural | B65: 2014 | C65: October | D65: 122.6 | E65: 122.5 | F65: 118.3 | G65: 123.2 | H65: 110.5 | I65: 128.9 | J65: 155.3 | K65: 115.5 | L65: 104 | M65: 115.3 | N65: 116.8 | O65: 123.2 | P65: 125.1 | Q65: 120 | R65: 122.7 | S65: 120.3 | T65: 122.3 | U65: NA | V65: 116.4 | W65: 117.5 | X65: 115.3 | Y65: 112.6 | Z65: 113 | AA65: 116.9 | AB65: 109.3 | AC65: 114 | AD65: 121
A66: Urban | B66: 2014 | C66: October | D66: 124.6 | E66: 126.1 | F66: 117.8 | G66: 123.1 | H66: 103.5 | I66: 123.5 | J66: 159.6 | K66: 117.4 | L66: 101.2 | M66: 123.8 | N66: 115.2 | O66: 125.9 | P66: 125.8 | Q66: 124.3 | R66: 119.6 | S66: 114.9 | T66: 118.9 | U66: 116.7 | V66: 112 | W66: 115.8 | X66: 112.6 | Y66: 111 | Z66: 113.6 | AA66: 120.2 | AB66: 110.1 | AC66: 113.7 | AD66: 119.1
A67: Rural+Urban | B67: 2014 | C67: October | D67: 123.2 | E67: 123.8 | F67: 118.1 | G67: 123.2 | H67: 107.9 | I67: 126.4 | J67: 156.8 | K67: 116.1 | L67: 103.1 | M67: 118.1 | N67: 116.1 | O67: 124.5 | P67: 125.4 | Q67: 121.1 | R67: 121.5 | S67: 118.1 | T67: 121 | U67: 116.7 | V67: 114.7 | W67: 116.7 | X67: 114.3 | Y67: 111.8 | Z67: 113.3 | AA67: 118.8 | AB67: 109.6 | AC67: 113.9 | AD67: 120.1
A68: Rural | B68: 2014 | C68: November | D68: 122.7 | E68: 122.6 | F68: 119.9 | G68: 124 | H68: 110.5 | I68: 128.8 | J68: 152 | K68: 116.2 | L68: 103.3 | M68: 115.8 | N68: 116.8 | O68: 124.5 | P68: 124.9 | Q68: 120.8 | R68: 123.3 | S68: 120.5 | T68: 122.9 | U68: NA | V68: 117.3 | W68: 118.1 | X68: 115.9 | Y68: 112 | Z68: 113.3 | AA68: 117.2 | AB68: 108.8 | AC68: 114.1 | AD68: 121.1
A69: Urban | B69: 2014 | C69: November | D69: 124.5 | E69: 125.6 | F69: 122.7 | G69: 124.6 | H69: 103.2 | I69: 122.2 | J69: 153.2 | K69: 119.3 | L69: 99.8 | M69: 124.6 | N69: 115.8 | O69: 126.9 | P69: 125.4 | Q69: 125.8 | R69: 120.3 | S69: 115.4 | T69: 119.5 | U69: 117.1 | V69: 112.6 | W69: 116.4 | X69: 113 | Y69: 109.7 | Z69: 114 | AA69: 120.3 | AB69: 109.6 | AC69: 113.4 | AD69: 119
A70: Rural+Urban | B70: 2014 | C70: November | D70: 123.3 | E70: 123.7 | F70: 121 | G70: 124.2 | H70: 107.8 | I70: 125.7 | J70: 152.4 | K70: 117.2 | L70: 102.1 | M70: 118.7 | N70: 116.4 | O70: 125.6 | P70: 125.1 | Q70: 122.1 | R70: 122.1 | S70: 118.4 | T70: 121.6 | U70: 117.1 | V70: 115.5 | W70: 117.3 | X70: 114.8 | Y70: 110.8 | Z70: 113.7 | AA70: 119 | AB70: 109.1 | AC70: 113.8 | AD70: 120.1
A71: Rural | B71: 2014 | C71: December | D71: 122.4 | E71: 122.4 | F71: 121.8 | G71: 124.2 | H71: 110.2 | I71: 128.6 | J71: 140.3 | K71: 116.3 | L71: 102 | M71: 116 | N71: 117.3 | O71: 124.8 | P71: 123.3 | Q71: 121.7 | R71: 123.8 | S71: 120.6 | T71: 123.3 | U71: NA | V71: 117.4 | W71: 118.2 | X71: 116.2 | Y71: 111.5 | Z71: 113.3 | AA71: 117.7 | AB71: 109.4 | AC71: 114.2 | AD71: 120.3
A72: Urban | B72: 2014 | C72: December | D72: 124 | E72: 124.7 | F72: 126.3 | G72: 124.9 | H72: 103 | I72: 122.3 | J72: 141 | K72: 120.1 | L72: 97.8 | M72: 125.4 | N72: 116.1 | O72: 127.6 | P72: 124 | Q72: 126.4 | R72: 120.7 | S72: 115.8 | T72: 120 | U72: 116.5 | V72: 113 | W72: 116.8 | X72: 113.2 | Y72: 108.8 | Z72: 114.3 | AA72: 120.7 | AB72: 110.4 | AC72: 113.4 | AD72: 118.4
A73: Rural+Urban | B73: 2014 | C73: December | D73: 122.9 | E73: 123.2 | F73: 123.5 | G73: 124.5 | H73: 107.6 | I73: 125.7 | J73: 140.5 | K73: 117.6 | L73: 100.6 | M73: 119.1 | N73: 116.8 | O73: 126.1 | P73: 123.6 | Q73: 123 | R73: 122.6 | S73: 118.6 | T73: 122 | U73: 116.5 | V73: 115.7 | W73: 117.5 | X73: 115.1 | Y73: 110.1 | Z73: 113.9 | AA73: 119.5 | AB73: 109.8 | AC73: 113.8 | AD73: 119.4
A74: Rural | B74: 2015 | C74: January | D74: 123.1 | E74: 123.1 | F74: 122.1 | G74: 124.9 | H74: 111 | I74: 130.4 | J74: 132.3 | K74: 117.2 | L74: 100.5 | M74: 117.2 | N74: 117.9 | O74: 125.6 | P74: 122.8 | Q74: 122.7 | R74: 124.4 | S74: 121.6 | T74: 124 | U74: NA | V74: 118.4 | W74: 118.9 | X74: 116.6 | Y74: 111 | Z74: 114 | AA74: 118.2 | AB74: 110.2 | AC74: 114.5 | AD74: 120.3
A75: Urban | B75: 2015 | C75: January | D75: 124 | E75: 125.5 | F75: 126.6 | G75: 125.2 | H75: 104.3 | I75: 121.3 | J75: 134.4 | K75: 122.9 | L75: 96.1 | M75: 126.6 | N75: 116.5 | O75: 128 | P75: 123.5 | Q75: 127.4 | R75: 121 | S75: 116.1 | T75: 120.2 | U75: 117.3 | V75: 113.4 | W75: 117.2 | X75: 113.7 | Y75: 107.9 | Z75: 114.6 | AA75: 120.8 | AB75: 111.4 | AC75: 113.4 | AD75: 118.5
A76: Rural+Urban | B76: 2015 | C76: January | D76: 123.4 | E76: 123.9 | F76: 123.8 | G76: 125 | H76: 108.5 | I76: 126.2 | J76: 133 | K76: 119.1 | L76: 99 | M76: 120.3 | N76: 117.3 | O76: 126.7 | P76: 123.1 | Q76: 124 | R76: 123.1 | S76: 119.3 | T76: 122.5 | U76: 117.3 | V76: 116.5 | W76: 118.1 | X76: 115.5 | Y76: 109.4 | Z76: 114.3 | AA76: 119.7 | AB76: 110.7 | AC76: 114 | AD76: 119.5
A77: Rural | B77: 2015 | C77: February | D77: 123.4 | E77: 124.4 | F77: 122.1 | G77: 125.8 | H77: 111.5 | I77: 129.4 | J77: 128.2 | K77: 118.8 | L77: 100 | M77: 118.6 | N77: 118.8 | O77: 126.8 | P77: 122.8 | Q77: 124.2 | R77: 125.4 | S77: 122.7 | T77: 125 | U77: NA | V77: 120 | W77: 119.6 | X77: 117.7 | Y77: 110.9 | Z77: 114.8 | AA77: 118.7 | AB77: 110.8 | AC77: 115 | AD77: 120.6
A78: Urban | B78: 2015 | C78: February | D78: 124.3 | E78: 126.5 | F78: 119.5 | G78: 125.6 | H78: 104.9 | I78: 121.6 | J78: 131.8 | K78: 125.1 | L78: 95 | M78: 127.7 | N78: 116.8 | O78: 128.6 | P78: 123.7 | Q78: 128.1 | R78: 121.3 | S78: 116.5 | T78: 120.6 | U78: 118.1 | V78: 114 | W78: 117.7 | X78: 114.1 | Y78: 106.8 | Z78: 114.9 | AA78: 120.4 | AB78: 111.7 | AC78: 113.2 | AD78: 118.7
A79: Rural+Urban | B79: 2015 | C79: February | D79: 123.7 | E79: 125.1 | F79: 121.1 | G79: 125.7 | H79: 109.1 | I79: 125.8 | J79: 129.4 | K79: 120.9 | L79: 98.3 | M79: 121.6 | N79: 118 | O79: 127.6 | P79: 123.1 | Q79: 125.2 | R79: 123.8 | S79: 120.1 | T79: 123.3 | U79: 118.1 | V79: 117.7 | W79: 118.7 | X79: 116.3 | Y79: 108.7 | Z79: 114.9 | AA79: 119.7 | AB79: 111.2 | AC79: 114.1 | AD79: 119.7
A80: Rural | B80: 2015 | C80: March | D80: 123.3 | E80: 124.7 | F80: 118.9 | G80: 126 | H80: 111.8 | I80: 130.9 | J80: 128 | K80: 119.9 | L80: 98.9 | M80: 119.4 | N80: 118.9 | O80: 127.7 | P80: 123.1 | Q80: 124.7 | R80: 126 | S80: 122.9 | T80: 125.5 | U80: NA | V80: 120.6 | W80: 120.2 | X80: 118.2 | Y80: 111.6 | Z80: 115.5 | AA80: 119.4 | AB80: 110.8 | AC80: 115.5 | AD80: 121.1
A81: Urban | B81: 2015 | C81: March | D81: 124 | E81: 126.7 | F81: 113.5 | G81: 125.9 | H81: 104.8 | I81: 123.8 | J81: 131.4 | K81: 127.2 | L81: 93.2 | M81: 127.4 | N81: 117 | O81: 129.2 | P81: 123.9 | Q81: 128.8 | R81: 121.7 | S81: 116.9 | T81: 120.9 | U81: 118.6 | V81: 114.4 | W81: 118 | X81: 114.3 | Y81: 108.4 | Z81: 115.4 | AA81: 120.6 | AB81: 111.3 | AC81: 113.8 | AD81: 119.1
A82: Rural+Urban | B82: 2015 | C82: March | D82: 123.5 | E82: 125.4 | F82: 116.8 | G82: 126 | H82: 109.2 | I82: 127.6 | J82: 129.2 | K82: 122.4 | L82: 97 | M82: 122.1 | N82: 118.1 | O82: 128.4 | P82: 123.4 | Q82: 125.8 | R82: 124.3 | S82: 120.4 | T82: 123.7 | U82: 118.6 | V82: 118.3 | W82: 119.2 | X82: 116.7 | Y82: 109.9 | Z82: 115.4 | AA82: 120.1 | AB82: 111 | AC82: 114.7 | AD82: 120.2
A83: Rural | B83: 2015 | C83: April | D83: 123.3 | E83: 125.5 | F83: 117.2 | G83: 126.8 | H83: 111.9 | I83: 134.2 | J83: 127.5 | K83: 121.5 | L83: 97.8 | M83: 119.8 | N83: 119.4 | O83: 128.7 | P83: 123.6 | Q83: 125.7 | R83: 126.4 | S83: 123.3 | T83: 126 | U83: NA | V83: 121.2 | W83: 120.9 | X83: 118.6 | Y83: 111.9 | Z83: 116.2 | AA83: 119.9 | AB83: 111.6 | AC83: 116 | AD83: 121.5
A84: Urban | B84: 2015 | C84: April | D84: 123.8 | E84: 128.2 | F84: 110 | G84: 126.3 | H84: 104.5 | I84: 130.6 | J84: 130.8 | K84: 131.3 | L84: 91.6 | M84: 127.7 | N84: 117.2 | O84: 129.5 | P84: 124.6 | Q84: 130.1 | R84: 122.1 | S84: 117.2 | T84: 121.3 | U84: 119.2 | V84: 114.7 | W84: 118.4 | X84: 114.6 | Y84: 108.4 | Z84: 115.6 | AA84: 121.7 | AB84: 111.8 | AC84: 114.2 | AD84: 119.7
A85: Rural+Urban | B85: 2015 | C85: April | D85: 123.5 | E85: 126.4 | F85: 114.4 | G85: 126.6 | H85: 109.2 | I85: 132.5 | J85: 128.6 | K85: 124.8 | L85: 95.7 | M85: 122.4 | N85: 118.5 | O85: 129.1 | P85: 124 | Q85: 126.9 | R85: 124.7 | S85: 120.8 | T85: 124.1 | U85: 119.2 | V85: 118.7 | W85: 119.7 | X85: 117.1 | Y85: 110.1 | Z85: 115.9 | AA85: 121 | AB85: 111.7 | AC85: 115.1 | AD85: 120.7
A86: Rural | B86: 2015 | C86: May | D86: 123.5 | E86: 127.1 | F86: 117.3 | G86: 127.7 | H86: 112.5 | I86: 134.1 | J86: 128.5 | K86: 124.3 | L86: 97.6 | M86: 120.7 | N86: 120.2 | O86: 129.8 | P86: 124.4 | Q86: 126.7 | R86: 127.3 | S86: 124.1 | T86: 126.8 | U86: NA | V86: 121.9 | W86: 121.5 | X86: 119.4 | Y86: 113.3 | Z86: 116.7 | AA86: 120.5 | AB86: 112.3 | AC86: 116.9 | AD86: 122.4
A87: Urban | B87: 2015 | C87: May | D87: 123.8 | E87: 129.7 | F87: 111.3 | G87: 126.6 | H87: 105.2 | I87: 130.8 | J87: 135.6 | K87: 142.6 | L87: 90.8 | M87: 128.8 | N87: 117.7 | O87: 129.9 | P87: 126.1 | Q87: 131.3 | R87: 122.4 | S87: 117.4 | T87: 121.6 | U87: 119.6 | V87: 114.9 | W87: 118.7 | X87: 114.9 | Y87: 110.8 | Z87: 116 | AA87: 122 | AB87: 112.4 | AC87: 115.2 | AD87: 120.7
A88: Rural+Urban | B88: 2015 | C88: May | D88: 123.6 | E88: 128 | F88: 115 | G88: 127.3 | H88: 109.8 | I88: 132.6 | J88: 130.9 | K88: 130.5 | L88: 95.3 | M88: 123.4 | N88: 119.2 | O88: 129.8 | P88: 125 | Q88: 127.9 | R88: 125.4 | S88: 121.3 | T88: 124.7 | U88: 119.6 | V88: 119.2 | W88: 120.2 | X88: 117.7 | Y88: 112 | Z88: 116.3 | AA88: 121.4 | AB88: 112.3 | AC88: 116.1 | AD88: 121.6
A89: Rural | B89: 2015 | C89: June | D89: 124.1 | E89: 130.4 | F89: 122.1 | G89: 128.7 | H89: 114.1 | I89: 133.2 | J89: 135.2 | K89: 131.9 | L89: 96.3 | M89: 123 | N89: 121.1 | O89: 131.2 | P89: 126.6 | Q89: 128.2 | R89: 128.4 | S89: 125.1 | T89: 128 | U89: NA | V89: 122.6 | W89: 122.8 | X89: 120.4 | Y89: 114.2 | Z89: 117.9 | AA89: 122 | AB89: 113 | AC89: 117.9 | AD89: 124.1
A90: Urban | B90: 2015 | C90: June | D90: 123.6 | E90: 134.4 | F90: 120.9 | G90: 127.3 | H90: 106 | I90: 132.3 | J90: 146.7 | K90: 148.1 | L90: 89.8 | M90: 130.5 | N90: 118 | O90: 130.5 | P90: 128.5 | Q90: 132.1 | R90: 123.2 | S90: 117.6 | T90: 122.3 | U90: 119 | V90: 115.1 | W90: 119.2 | X90: 115.4 | Y90: 111.7 | Z90: 116.2 | AA90: 123.8 | AB90: 112.5 | AC90: 116 | AD90: 121.7
A91: Rural+Urban | B91: 2015 | C91: June | D91: 123.9 | E91: 131.8 | F91: 121.6 | G91: 128.2 | H91: 111.1 | I91: 132.8 | J91: 139.1 | K91: 137.4 | L91: 94.1 | M91: 125.5 | N91: 119.8 | O91: 130.9 | P91: 127.3 | Q91: 129.2 | R91: 126.4 | S91: 122 | T91: 125.7 | U91: 119 | V91: 119.8 | W91: 121.1 | X91: 118.5 | Y91: 112.9 | Z91: 116.9 | AA91: 123.1 | AB91: 112.8 | AC91: 117 | AD91: 123
A92: Rural | B92: 2015 | C92: July | D92: 124 | E92: 131.5 | F92: 122 | G92: 128.7 | H92: 113.5 | I92: 133.3 | J92: 140.8 | K92: 133.8 | L92: 94.1 | M92: 123.4 | N92: 121 | O92: 131.7 | P92: 127.5 | Q92: 129.4 | R92: 128.8 | S92: 125.5 | T92: 128.3 | U92: NA | V92: 123 | W92: 123 | X92: 120.8 | Y92: 114.1 | Z92: 118 | AA92: 122.9 | AB92: 112.7 | AC92: 118.1 | AD92: 124.7
A93: Urban | B93: 2015 | C93: July | D93: 123.2 | E93: 134.3 | F93: 119.5 | G93: 127.7 | H93: 106.3 | I93: 132.8 | J93: 153.5 | K93: 149.5 | L93: 85.7 | M93: 131.5 | N93: 118.3 | O93: 131.1 | P93: 129.5 | Q93: 133.1 | R93: 123.5 | S93: 117.9 | T93: 122.7 | U93: 119.9 | V93: 115.3 | W93: 119.5 | X93: 116 | Y93: 111.5 | Z93: 116.6 | AA93: 125.4 | AB93: 111.7 | AC93: 116.3 | AD93: 122.4
A94: Rural+Urban | B94: 2015 | C94: July | D94: 123.7 | E94: 132.5 | F94: 121 | G94: 128.3 | H94: 110.9 | I94: 133.1 | J94: 145.1 | K94: 139.1 | L94: 91.3 | M94: 126.1 | N94: 119.9 | O94: 131.4 | P94: 128.2 | Q94: 130.4 | R94: 126.7 | S94: 122.3 | T94: 126.1 | U94: 119.9 | V94: 120.1 | W94: 121.3 | X94: 119 | Y94: 112.7 | Z94: 117.2 | AA94: 124.4 | AB94: 112.3 | AC94: 117.2 | AD94: 123.6
A95: Rural | B95: 2015 | C95: August | D95: 124.7 | E95: 131.3 | F95: 121.3 | G95: 128.8 | H95: 114 | I95: 134.2 | J95: 153.6 | K95: 137.9 | L95: 93.1 | M95: 123.9 | N95: 121.5 | O95: 132.5 | P95: 129.8 | Q95: 130.1 | R95: 129.5 | S95: 126.3 | T95: 129 | U95: NA | V95: 123.8 | W95: 123.7 | X95: 121.1 | Y95: 113.6 | Z95: 118.5 | AA95: 123.6 | AB95: 112.5 | AC95: 118.2 | AD95: 126.1
A96: Urban | B96: 2015 | C96: August | D96: 123.1 | E96: 131.7 | F96: 118.1 | G96: 128 | H96: 106.8 | I96: 130.1 | J96: 165.5 | K96: 156 | L96: 85.3 | M96: 132.7 | N96: 118.8 | O96: 131.7 | P96: 131.1 | Q96: 134.2 | R96: 123.7 | S96: 118.2 | T96: 122.9 | U96: 120.9 | V96: 115.3 | W96: 120 | X96: 116.6 | Y96: 109.9 | Z96: 117.2 | AA96: 126.2 | AB96: 112 | AC96: 116.2 | AD96: 123.2
A97: Rural+Urban | B97: 2015 | C97: August | D97: 124.2 | E97: 131.4 | F97: 120.1 | G97: 128.5 | H97: 111.4 | I97: 132.3 | J97: 157.6 | K97: 144 | L97: 90.5 | M97: 126.8 | N97: 120.4 | O97: 132.1 | P97: 130.3 | Q97: 131.2 | R97: 127.2 | S97: 122.9 | T97: 126.6 | U97: 120.9 | V97: 120.6 | W97: 122 | X97: 119.4 | Y97: 111.7 | Z97: 117.8 | AA97: 125.1 | AB97: 112.3 | AC97: 117.2 | AD97: 124.8
A98: Rural | B98: 2015 | C98: September | D98: 125.1 | E98: 131.1 | F98: 120.7 | G98: 129.2 | H98: 114.7 | I98: 132.3 | J98: 158.9 | K98: 142.1 | L98: 92.5 | M98: 125.4 | N98: 121.9 | O98: 132.7 | P98: 131 | Q98: 131 | R98: 130.4 | S98: 126.8 | T98: 129.9 | U98: NA | V98: 123.7 | W98: 124.5 | X98: 121.4 | Y98: 113.8 | Z98: 119.6 | AA98: 124.5 | AB98: 113.7 | AC98: 118.8 | AD98: 127
A99: Urban | B99: 2015 | C99: September | D99: 123.4 | E99: 129 | F99: 115.6 | G99: 128.3 | H99: 107 | I99: 124 | J99: 168.5 | K99: 165.4 | L99: 86.3 | M99: 134.4 | N99: 119.1 | O99: 132.3 | P99: 131.5 | Q99: 134.7 | R99: 124 | S99: 118.6 | T99: 123.2 | U99: 121.6 | V99: 115.1 | W99: 120.4 | X99: 117.1 | Y99: 109.1 | Z99: 117.3 | AA99: 126.5 | AB99: 112.9 | AC99: 116.2 | AD99: 123.5
A100: Rural+Urban | B100: 2015 | C100: September | D100: 124.6 | E100: 130.4 | F100: 118.7 | G100: 128.9 | H100: 111.9 | I100: 128.4 | J100: 162.2 | K100: 150 | L100: 90.4 | M100: 128.4 | N100: 120.7 | O100: 132.5 | P100: 131.2 | Q100: 132 | R100: 127.9 | S100: 123.4 | T100: 127.2 | U100: 121.6 | V100: 120.4 | W100: 122.6 | X100: 119.8 | Y100: 111.3 | Z100: 118.3 | AA100: 125.7 | AB100: 113.4 | AC100: 117.5 | AD100: 125.4
...

Sheet Working_Data
A1: Sector | B1: Year | C1: Month | D1: Cereals and products | E1: Meat and fish | F1: Egg | G1: Milk and products | H1: Oils and fats | I1: Fruits | J1: Vegetables | K1: Pulses and products | L1: Sugar and Confectionery | M1: Spices | N1: Non-alcoholic beverages | O1: Prepared meals, snacks, sweets etc. | P1: Food and beverages | Q1: Pan, tobacco and intoxicants | R1: Clothing | S1: Footwear | T1: Clothing and footwear | U1: Housing | V1: Fuel and light | W1: Household goods and services | X1: Health | Y1: Transport and communication | Z1: Recreation and amusement | AA1: Education | AB1: Personal care and effects | AC1: Miscellaneous | AD1: General index
A2: Rural | B2: 2013 | C2: January | D2: 107.5 | E2: 106.3 | F2: 108.1 | G2: 104.9 | H2: 106.1 | I2: 103.9 | J2: 101.9 | K2: 106.1 | L2: 106.8 | M2: 103.1 | N2: 104.8 | O2: 106.7 | P2: 105.5 | Q2: 105.1 | R2: 106.5 | S2: 105.8 | T2: 106.4 | U2: NA | V2: 105.5 | W2: 104.8 | X2: 104 | Y2: 103.3 | Z2: 103.4 | AA2: 103.8 | AB2: 104.7 | AC2: 104 | AD2: 105.1
A3: Urban | B3: 2013 | C3: January | D3: 110.5 | E3: 109.1 | F3: 113 | G3: 103.6 | H3: 103.4 | I3: 102.3 | J3: 102.9 | K3: 105.8 | L3: 105.1 | M3: 101.8 | N3: 105.1 | O3: 107.9 | P3: 105.9 | Q3: 105.2 | R3: 105.9 | S3: 105 | T3: 105.8 | U3: 100.3 | V3: 105.4 | W3: 104.8 | X3: 104.1 | Y3: 103.2 | Z3: 102.9 | AA3: 103.5 | AB3: 104.3 | AC3: 103.7 | AD3: 104
A4: Rural+Urban | B4: 2013 | C4: January | D4: 108.4 | E4: 107.3 | F4: 110 | G4: 104.4 | H4: 105.1 | I4: 103.2 | J4: 102.2 | K4: 106 | L4: 106.2 | M4: 102.7 | N4: 104.9 | O4: 107.3 | P4: 105.6 | Q4: 105.1 | R4: 106.3 | S4: 105.5 | T4: 106.2 | U4: 100.3 | V4: 105.5 | W4: 104.8 | X4: 104 | Y4: 103.2 | Z4: 103.1 | AA4: 103.6 | AB4: 104.5 | AC4: 103.9 | AD4: 104.6
A5: Rural | B5: 2013 | C5: February | D5: 109.2 | E5: 108.7 | F5: 110.2 | G5: 105.4 | H5: 106.7 | I5: 104 | J5: 102.4 | K5: 105.9 | L5: 105.7 | M5: 103.1 | N5: 105.1 | O5: 107.7 | P5: 106.3 | Q5: 105.6 | R5: 107.1 | S5: 106.3 | T5: 107 | U5: NA | V5: 106.2 | W5: 105.2 | X5: 104.4 | Y5: 103.9 | Z5: 104 | AA5: 104.1 | AB5: 104.6 | AC5: 104.4 | AD5: 105.8
A6: Urban | B6: 2013 | C6: February | D6: 112.9 | E6: 112.9 | F6: 116.9 | G6: 104 | H6: 103.5 | I6: 103.1 | J6: 104.9 | K6: 104.1 | L6: 103.8 | M6: 102.3 | N6: 106 | O6: 109 | P6: 107.2 | Q6: 106 | R6: 106.6 | S6: 105.5 | T6: 106.4 | U6: 100.4 | V6: 105.7 | W6: 105.2 | X6: 104.7 | Y6: 104.4 | Z6: 103.3 | AA6: 103.7 | AB6: 104.3 | AC6: 104.3 | AD6: 104.7
A7: Rural+Urban | B7: 2013 | C7: February | D7: 110.4 | E7: 110.2 | F7: 112.8 | G7: 104.9 | H7: 105.5 | I7: 103.6 | J7: 103.2 | K7: 105.3 | L7: 105.1 | M7: 102.8 | N7: 105.5 | O7: 108.3 | P7: 106.6 | Q7: 105.7 | R7: 106.9 | S7: 106 | T7: 106.8 | U7: 100.4 | V7: 106 | W7: 105.2 | X7: 104.5 | Y7: 104.2 | Z7: 103.6 | AA7: 103.9 | AB7: 104.5 | AC7: 104.4 | AD7: 105.3
A8: Rural | B8: 2013 | C8: March | D8: 110.2 | E8: 108.8 | F8: 109.9 | G8: 105.6 | H8: 106.2 | I8: 105.7 | J8: 101.4 | K8: 105.7 | L8: 105 | M8: 103.3 | N8: 105.6 | O8: 108.2 | P8: 106.6 | Q8: 106.5 | R8: 107.6 | S8: 106.8 | T8: 107.5 | U8: NA | V8: 106.1 | W8: 105.6 | X8: 104.7 | Y8: 104.6 | Z8: 104 | AA8: 104.3 | AB8: 104.3 | AC8: 104.6 | AD8: 106
A9: Urban | B9: 2013 | C9: March | D9: 113.9 | E9: 111.4 | F9: 113.2 | G9: 104.3 | H9: 102.7 | I9: 104.9 | J9: 103.8 | K9: 103.5 | L9: 102.6 | M9: 102.4 | N9: 107 | O9: 109.8 | P9: 107.3 | Q9: 106.8 | R9: 107.2 | S9: 106 | T9: 107 | U9: 100.4 | V9: 106 | W9: 105.7 | X9: 105.2 | Y9: 105.5 | Z9: 103.5 | AA9: 103.8 | AB9: 104.2 | AC9: 104.9 | AD9: 105
A10: Rural+Urban | B10: 2013 | C10: March | D10: 111.4 | E10: 109.7 | F10: 111.2 | G10: 105.1 | H10: 104.9 | I10: 105.3 | J10: 102.2 | K10: 105 | L10: 104.2 | M10: 103 | N10: 106.2 | O10: 108.9 | P10: 106.9 | Q10: 106.6 | R10: 107.4 | S10: 106.5 | T10: 107.3 | U10: 100.4 | V10: 106.1 | W10: 105.6 | X10: 104.9 | Y10: 105.1 | Z10: 103.7 | AA10: 104 | AB10: 104.3 | AC10: 104.7 | AD10: 105.5
A11: Rural | B11: 2013 | C11: April | D11: 110.2 | E11: 109.5 | F11: 106.9 | G11: 106.3 | H11: 105.7 | I11: 108.3 | J11: 103.4 | K11: 105.7 | L11: 104.2 | M11: 103.2 | N11: 106.5 | O11: 108.8 | P11: 107.1 | Q11: 107.1 | R11: 108.1 | S11: 107.4 | T11: 108 | U11: NA | V11: 106.5 | W11: 106.1 | X11: 105.1 | Y11: 104.4 | Z11: 104.5 | AA11: 104.8 | AB11: 102.7 | AC11: 104.6 | AD11: 106.4
A12: Urban | B12: 2013 | C12: April | D12: 114.6 | E12: 113.4 | F12: 106 | G12: 104.7 | H12: 102.1 | I12: 109.5 | J12: 109.7 | K12: 104.6 | L12: 102 | M12: 103.5 | N12: 108.2 | O12: 110.6 | P12: 108.8 | Q12: 108.5 | R12: 107.9 | S12: 106.4 | T12: 107.7 | U12: 100.5 | V12: 106.4 | W12: 106.5 | X12: 105.7 | Y12: 105 | Z12: 104 | AA12: 105.2 | AB12: 103.2 | AC12: 105.1 | AD12: 105.7
A13: Rural+Urban | B13: 2013 | C13: April | D13: 111.6 | E13: 110.9 | F13: 106.6 | G13: 105.7 | H13: 104.4 | I13: 108.9 | J13: 105.5 | K13: 105.3 | L13: 103.5 | M13: 103.3 | N13: 107.2 | O13: 109.6 | P13: 107.7 | Q13: 107.5 | R13: 108 | S13: 107 | T13: 107.9 | U13: 100.5 | V13: 106.5 | W13: 106.3 | X13: 105.3 | Y13: 104.7 | Z13: 104.2 | AA13: 105 | AB13: 102.9 | AC13: 104.8 | AD13: 106.1
A14: Rural | B14: 2013 | C14: May | D14: 110.9 | E14: 109.8 | F14: 105.9 | G14: 107.5 | H14: 105.3 | I14: 108.1 | J14: 107.3 | K14: 106.1 | L14: 103.7 | M14: 104 | N14: 107.4 | O14: 109.9 | P14: 108.1 | Q14: 108.1 | R14: 108.8 | S14: 107.9 | T14: 108.6 | U14: NA | V14: 107.5 | W14: 106.8 | X14: 105.7 | Y14: 104.1 | Z14: 105 | AA14: 105.5 | AB14: 102.1 | AC14: 104.8 | AD14: 107.2
A15: Urban | B15: 2013 | C15: May | D15: 115.4 | E15: 114.2 | F15: 102.7 | G15: 105.5 | H15: 101.5 | I15: 110.6 | J15: 123.7 | K15: 105.2 | L15: 101.9 | M15: 105 | N15: 109.1 | O15: 111.3 | P15: 111.1 | Q15: 109.8 | R15: 108.5 | S15: 106.7 | T15: 108.3 | U15: 100.5 | V15: 107.2 | W15: 107.1 | X15: 106.2 | Y15: 103.9 | Z15: 104.6 | AA15: 105.7 | AB15: 102.6 | AC15: 104.9 | AD15: 106.6
A16: Rural+Urban | B16: 2013 | C16: May | D16: 112.3 | E16: 111.3 | F16: 104.7 | G16: 106.8 | H16: 103.9 | I16: 109.3 | J16: 112.9 | K16: 105.8 | L16: 103.1 | M16: 104.3 | N16: 108.1 | O16: 110.5 | P16: 109.2 | Q16: 108.6 | R16: 108.7 | S16: 107.4 | T16: 108.5 | U16: 100.5 | V16: 107.4 | W16: 106.9 | X16: 105.9 | Y16: 104 | Z16: 104.8 | AA16: 105.6 | AB16: 102.3 | AC16: 104.8 | AD16: 106.9
A17: Rural | B17: 2013 | C17: June | D17: 112.3 | E17: 112.1 | F17: 108.1 | G17: 108.3 | H17: 105.9 | I17: 109.2 | J17: 118 | K17: 106.8 | L17: 104.1 | M17: 105.4 | N17: 108.2 | O17: 111 | P17: 110.6 | Q17: 109 | R17: 109.7 | S17: 108.8 | T17: 109.5 | U17: NA | V17: 108.5 | W17: 107.5 | X17: 106.3 | Y17: 105 | Z17: 105.6 | AA17: 106.5 | AB17: 102.5 | AC17: 105.5 | AD17: 108.9
A18: Urban | B18: 2013 | C18: June | D18: 117 | E18: 120.1 | F18: 112.5 | G18: 107.3 | H18: 101.3 | I18: 112.4 | J18: 143.6 | K18: 105.4 | L18: 101.4 | M18: 106.4 | N18: 110 | O18: 112.2 | P18: 115 | Q18: 110.9 | R18: 109.2 | S18: 107.2 | T18: 108.9 | U18: 106.6 | V18: 108 | W18: 107.7 | X18: 106.5 | Y18: 105.2 | Z18: 105.2 | AA18: 108.1 | AB18: 103.3 | AC18: 106.1 | AD18: 109.7
A19: Rural+Urban | B19: 2013 | C19: June | D19: 113.8 | E19: 114.9 | F19: 109.8 | G19: 107.9 | H19: 104.2 | I19: 110.7 | J19: 126.7 | K19: 106.3 | L19: 103.2 | M19: 105.7 | N19: 109 | O19: 111.6 | P19: 112.2 | Q19: 109.5 | R19: 109.5 | S19: 108.1 | T19: 109.3 | U19: 106.6 | V19: 108.3 | W19: 107.6 | X19: 106.4 | Y19: 105.1 | Z19: 105.4 | AA19: 107.4 | AB19: 102.8 | AC19: 105.8 | AD19: 109.3
A20: Rural | B20: 2013 | C20: July | D20: 113.4 | E20: 114.9 | F20: 110.5 | G20: 109.3 | H20: 106.2 | I20: 110.3 | J20: 129.2 | K20: 107.1 | L20: 104.3 | M20: 106.4 | N20: 109.1 | O20: 112.1 | P20: 113.1 | Q20: 109.8 | R20: 110.5 | S20: 109.5 | T20: 110.3 | U20: NA | V20: 109.5 | W20: 108.3 | X20: 106.9 | Y20: 106.8 | Z20: 106.4 | AA20: 107.8 | AB20: 102.5 | AC20: 106.5 | AD20: 110.7
A21: Urban | B21: 2013 | C21: July | D21: 117.8 | E21: 119.2 | F21: 114 | G21: 108.3 | H21: 101.1 | I21: 113.2 | J21: 160.9 | K21: 105.1 | L21: 101.3 | M21: 107.5 | N21: 110.4 | O21: 113.1 | P21: 117.5 | Q21: 111.7 | R21: 109.8 | S21: 107.8 | T21: 109.5 | U21: 107.7 | V21: 108.6 | W21: 108.1 | X21: 107.1 | Y21: 107.3 | Z21: 105.9 | AA21: 110.1 | AB21: 103.2 | AC21: 107.3 | AD21: 111.4
A22: Rural+Urban | B22: 2013 | C22: July | D22: 114.8 | E22: 116.4 | F22: 111.9 | G22: 108.9 | H22: 104.3 | I22: 111.7 | J22: 140 | K22: 106.4 | L22: 103.3 | M22: 106.8 | N22: 109.6 | O22: 112.6 | P22: 114.7 | Q22: 110.3 | R22: 110.2 | S22: 108.8 | T22: 110 | U22: 107.7 | V22: 109.2 | W22: 108.2 | X22: 107 | Y22: 107.1 | Z22: 106.1 | AA22: 109.1 | AB22: 102.8 | AC22: 106.9 | AD22: 111
A23: Rural | B23: 2013 | C23: August | D23: 114.3 | E23: 115.4 | F23: 111.1 | G23: 110 | H23: 106.4 | I23: 110.8 | J23: 138.9 | K23: 107.4 | L23: 104.1 | M23: 106.9 | N23: 109.7 | O23: 112.6 | P23: 114.9 | Q23: 110.7 | R23: 111.3 | S23: 110.2 | T23: 111.1 | U23: NA | V23: 109.9 | W23: 108.7 | X23: 107.5 | Y23: 107.8 | Z23: 106.8 | AA23: 108.7 | AB23: 105 | AC23: 107.5 | AD23: 112.1
A24: Urban | B24: 2013 | C24: August | D24: 118.3 | E24: 120.4 | F24: 112.7 | G24: 108.9 | H24: 101.1 | I24: 108.7 | J24: 177 | K24: 104.7 | L24: 101 | M24: 108.5 | N24: 110.9 | O24: 114.3 | P24: 119.6 | Q24: 112.4 | R24: 110.6 | S24: 108.3 | T24: 110.2 | U24: 108.9 | V24: 109.3 | W24: 108.7 | X24: 107.6 | Y24: 108.1 | Z24: 106.5 | AA24: 110.8 | AB24: 106 | AC24: 108.3 | AD24: 112.7
A25: Rural+Urban | B25: 2013 | C25: August | D25: 115.6 | E25: 117.2 | F25: 111.7 | G25: 109.6 | H25: 104.5 | I25: 109.8 | J25: 151.8 | K25: 106.5 | L25: 103.1 | M25: 107.4 | N25: 110.2 | O25: 113.4 | P25: 116.6 | Q25: 111.2 | R25: 111 | S25: 109.4 | T25: 110.7 | U25: 108.9 | V25: 109.7 | W25: 108.7 | X25: 107.5 | Y25: 108 | Z25: 106.6 | AA25: 109.9 | AB25: 105.4 | AC25: 107.9 | AD25: 112.4
A26: Rural | B26: 2013 | C26: September | D26: 115.4 | E26: 115.7 | F26: 111.7 | G26: 111 | H26: 107.4 | I26: 110.9 | J26: 154 | K26: 108.1 | L26: 104.2 | M26: 107.9 | N26: 110.4 | O26: 114 | P26: 117.8 | Q26: 111.7 | R26: 112.7 | S26: 111.4 | T26: 112.5 | U26: NA | V26: 111.1 | W26: 109.6 | X26: 108.3 | Y26: 109.3 | Z26: 107.7 | AA26: 109.8 | AB26: 106.7 | AC26: 108.7 | AD26: 114.2
A27: Urban | B27: 2013 | C27: September | D27: 118.6 | E27: 119.1 | F27: 113.2 | G27: 109.6 | H27: 101.7 | I27: 103.2 | J27: 174.3 | K27: 105.1 | L27: 100.8 | M27: 109.1 | N27: 111.1 | O27: 115.4 | P27: 119.2 | Q27: 112.9 | R27: 111.4 | S27: 109 | T27: 111.1 | U27: 109.7 | V27: 109.5 | W27: 109.6 | X27: 107.9 | Y27: 110.4 | Z27: 107.4 | AA27: 111.2 | AB27: 106.9 | AC27: 109.4 | AD27: 113.2
A28: Rural+Urban | B28: 2013 | C28: September | D28: 116.4 | E28: 116.9 | F28: 112.3 | G28: 110.5 | H28: 105.3 | I28: 107.3 | J28: 160.9 | K28: 107.1 | L28: 103.1 | M28: 108.3 | N28: 110.7 | O28: 114.6 | P28: 118.3 | Q28: 112 | R28: 112.2 | S28: 110.4 | T28: 111.9 | U28: 109.7 | V28: 110.5 | W28: 109.6 | X28: 108.1 | Y28: 109.9 | Z28: 107.5 | AA28: 110.6 | AB28: 106.8 | AC28: 109 | AD28: 113.7
A29: Rural | B29: 2013 | C29: October | D29: 116.3 | E29: 115.4 | F29: 112.6 | G29: 111.7 | H29: 107.7 | I29: 113.2 | J29: 164.9 | K29: 108.3 | L29: 103.9 | M29: 108.2 | N29: 111.1 | O29: 114.9 | P29: 119.8 | Q29: 112.2 | R29: 113.6 | S29: 112.3 | T29: 113.4 | U29: NA | V29: 111.6 | W29: 110.4 | X29: 108.9 | Y29: 109.3 | Z29: 108.3 | AA29: 110.2 | AB29: 107.5 | AC29: 109.1 | AD29: 115.5
A30: Urban | B30: 2013 | C30: October | D30: 118.9 | E30: 118.1 | F30: 114.5 | G30: 110.4 | H30: 102.3 | I30: 106.2 | J30: 183.5 | K30: 105.3 | L30: 100.2 | M30: 109.6 | N30: 111.4 | O30: 116 | P30: 120.8 | Q30: 113.5 | R30: 112.5 | S30: 109.7 | T30: 112 | U30: 110.5 | V30: 109.7 | W30: 110.2 | X30: 108.2 | Y30: 109.7 | Z30: 108 | AA30: 111.3 | AB30: 107.3 | AC30: 109.4 | AD30: 114
A31: Rural+Urban | B31: 2013 | C31: October | D31: 117.1 | E31: 116.3 | F31: 113.3 | G31: 111.2 | H31: 105.7 | I31: 109.9 | J31: 171.2 | K31: 107.3 | L31: 102.7 | M31: 108.7 | N31: 111.2 | O31: 115.4 | P31: 120.2 | Q31: 112.5 | R31: 113.2 | S31: 111.2 | T31: 112.8 | U31: 110.5 | V31: 110.9 | W31: 110.3 | X31: 108.6 | Y31: 109.5 | Z31: 108.1 | AA31: 110.8 | AB31: 107.4 | AC31: 109.2 | AD31: 114.8
A32: Rural | B32: 2013 | C32: November | D32: 117.3 | E32: 114.9 | F32: 116.2 | G32: 112.8 | H32: 108.9 | I32: 116.6 | J32: 178.1 | K32: 109.1 | L32: 103.6 | M32: 109 | N32: 111.8 | O32: 116 | P32: 122.5 | Q32: 112.8 | R32: 114.6 | S32: 113.1 | T32: 114.4 | U32: NA | V32: 112.6 | W32: 111.3 | X32: 109.7 | Y32: 109.6 | Z32: 108.7 | AA32: 111 | AB32: 108.2 | AC32: 109.8 | AD32: 117.4
A33: Urban | B33: 2013 | C33: November | D33: 119.8 | E33: 116.3 | F33: 122.6 | G33: 112 | H33: 103.2 | I33: 110 | J33: 192.8 | K33: 106.3 | L33: 99.5 | M33: 110.3 | N33: 111.8 | O33: 117.1 | P33: 122.9 | Q33: 114.1 | R33: 113.5 | S33: 110.3 | T33: 113 | U33: 111.1 | V33: 110 | W33: 110.9 | X33: 108.6 | Y33: 109.5 | Z33: 108.5 | AA33: 111.3 | AB33: 107.9 | AC33: 109.6 | AD33: 115
A34: Rural+Urban | B34: 2013 | C34: November | D34: 118.1 | E34: 115.4 | F34: 118.7 | G34: 112.5 | H34: 106.8 | I34: 113.5 | J34: 183.1 | K34: 108.2 | L34: 102.2 | M34: 109.4 | N34: 111.8 | O34: 116.5 | P34: 122.6 | Q34: 113.1 | R34: 114.2 | S34: 111.9 | T34: 113.8 | U34: 111.1 | V34: 111.6 | W34: 111.1 | X34: 109.3 | Y34: 109.5 | Z34: 108.6 | AA34: 111.2 | AB34: 108.1 | AC34: 109.7 | AD34: 116.3
A35: Rural | B35: 2013 | C35: December | D35: 118.4 | E35: 115.9 | F35: 120.4 | G35: 113.8 | H35: 109.5 | I35: 115.5 | J35: 145.7 | K35: 109.5 | L35: 102.9 | M35: 109.8 | N35: 112.1 | O35: 116.8 | P35: 118.7 | Q35: 113.6 | R35: 115.8 | S35: 114 | T35: 115.5 | U35: NA | V35: 112.8 | W35: 112.1 | X35: 110.1 | Y35: 109.9 | Z35: 109.2 | AA35: 111.6 | AB35: 108.1 | AC35: 110.1 | AD35: 115.5
A36: Urban | B36: 2013 | C36: December | D36: 120.5 | E36: 118.1 | F36: 128.5 | G36: 112.8 | H36: 103.4 | I36: 110.7 | J36: 144.8 | K36: 107.1 | L36: 98.6 | M36: 111.9 | N36: 112.1 | O36: 118.1 | P36: 117.8 | Q36: 115 | R36: 114.2 | S36: 110.9 | T36: 113.7 | U36: 110.7 | V36: 110.4 | W36: 111.3 | X36: 109 | Y36: 109.7 | Z36: 108.9 | AA36: 111.4 | AB36: 107.7 | AC36: 109.8 | AD36: 113.3
A37: Rural+Urban | B37: 2013 | C37: December | D37: 119.1 | E37: 116.7 | F37: 123.5 | G37: 113.4 | H37: 107.3 | I37: 113.3 | J37: 145.4 | K37: 108.7 | L37: 101.5 | M37: 110.5 | N37: 112.1 | O37: 117.4 | P37: 118.4 | Q37: 114 | R37: 115.2 | S37: 112.7 | T37: 114.8 | U37: 110.7 | V37: 111.9 | W37: 111.7 | X37: 109.7 | Y37: 109.8 | Z37: 109 | AA37: 111.5 | AB37: 107.9 | AC37: 110 | AD37: 114.5
A38: Rural | B38: 2014 | C38: January | D38: 118.9 | E38: 117.1 | F38: 120.5 | G38: 114.4 | H38: 109 | I38: 115.5 | J38: 123.9 | K38: 109.6 | L38: 101.8 | M38: 110.2 | N38: 112.4 | O38: 117.3 | P38: 116 | Q38: 114 | R38: 116.5 | S38: 114.5 | T38: 116.2 | U38: NA | V38: 113 | W38: 112.6 | X38: 110.6 | Y38: 110.5 | Z38: 109.6 | AA38: 111.8 | AB38: 108.3 | AC38: 110.6 | AD38: 114.2
A39: Urban | B39: 2014 | C39: January | D39: 121.2 | E39: 122 | F39: 129.9 | G39: 113.6 | H39: 102.9 | I39: 112.1 | J39: 118.9 | K39: 107.5 | L39: 96.9 | M39: 112.7 | N39: 112.1 | O39: 119 | P39: 115.5 | Q39: 115.7 | R39: 114.8 | S39: 111.3 | T39: 114.3 | U39: 111.6 | V39: 111 | W39: 111.9 | X39: 109.7 | Y39: 110.8 | Z39: 109.8 | AA39: 111.5 | AB39: 108 | AC39: 110.5 | AD39: 112.9
A40: Rural+Urban | B40: 2014 | C40: January | D40: 119.6 | E40: 118.8 | F40: 124.1 | G40: 114.1 | H40: 106.8 | I40: 113.9 | J40: 122.2 | K40: 108.9 | L40: 100.2 | M40: 111 | N40: 112.3 | O40: 118.1 | P40: 115.8 | Q40: 114.5 | R40: 115.8 | S40: 113.2 | T40: 115.4 | U40: 111.6 | V40: 112.2 | W40: 112.3 | X40: 110.3 | Y40: 110.7 | Z40: 109.7 | AA40: 111.6 | AB40: 108.2 | AC40: 110.6 | AD40: 113.6
A41: Rural | B41: 2014 | C41: February | D41: 119.4 | E41: 117.7 | F41: 121.2 | G41: 115 | H41: 109 | I41: 116.6 | J41: 116 | K41: 109.8 | L41: 101.1 | M41: 110.4 | N41: 112.9 | O41: 117.8 | P41: 115.3 | Q41: 114.2 | R41: 117.1 | S41: 114.5 | T41: 116.7 | U41: NA | V41: 113.2 | W41: 112.9 | X41: 110.9 | Y41: 110.8 | Z41: 109.9 | AA41: 112 | AB41: 108.7 | AC41: 110.9 | AD41: 114
A42: Urban | B42: 2014 | C42: February | D42: 121.9 | E42: 122 | F42: 124.5 | G42: 115.2 | H42: 102.5 | I42: 114.1 | J42: 111.5 | K42: 108.2 | L42: 95.4 | M42: 113.5 | N42: 112.1 | O42: 119.9 | P42: 115.2 | Q42: 116.2 | R42: 115.3 | S42: 111.7 | T42: 114.7 | U42: 112.5 | V42: 111.1 | W42: 112.6 | X42: 110.4 | Y42: 111.3 | Z42: 110.3 | AA42: 111.6 | AB42: 108.7 | AC42: 111 | AD42: 113.1
A43: Rural+Urban | B43: 2014 | C43: February | D43: 120.2 | E43: 119.2 | F43: 122.5 | G43: 115.1 | H43: 106.6 | I43: 115.4 | J43: 114.5 | K43: 109.3 | L43: 99.2 | M43: 111.4 | N43: 112.6 | O43: 118.8 | P43: 115.3 | Q43: 114.7 | R43: 116.4 | S43: 113.3 | T43: 115.9 | U43: 112.5 | V43: 112.4 | W43: 112.8 | X43: 110.7 | Y43: 111.1 | Z43: 110.1 | AA43: 111.8 | AB43: 108.7 | AC43: 110.9 | AD43: 113.6
A44: Rural | B44: 2014 | C44: March | D44: 120.1 | E44: 118.1 | F44: 120.7 | G44: 116.1 | H44: 109.3 | I44: 119.6 | J44: 117.9 | K44: 110.2 | L44: 101.2 | M44: 110.7 | N44: 113 | O44: 118.3 | P44: 116.2 | Q44: 114.6 | R44: 117.5 | S44: 114.9 | T44: 117.2 | U44: NA | V44: 113.4 | W44: 113.4 | X44: 111.4 | Y44: 111.2 | Z44: 110.2 | AA44: 112.4 | AB44: 108.9 | AC44: 111.3 | AD44: 114.6
A45: Urban | B45: 2014 | C45: March | D45: 122.1 | E45: 121.4 | F45: 121.5 | G45: 116.2 | H45: 102.8 | I45: 117.7 | J45: 113.3 | K45: 108.9 | L45: 96.3 | M45: 114.1 | N45: 112.2 | O45: 120.5 | P45: 116 | Q45: 116.7 | R45: 115.8 | S45: 112.1 | T45: 115.2 | U45: 113.2 | V45: 110.9 | W45: 113 | X45: 110.8 | Y45: 111.6 | Z45: 110.9 | AA45: 111.8 | AB45: 109.2 | AC45: 111.4 | AD45: 113.7
A46: Rural+Urban | B46: 2014 | C46: Marcrh | D46: 120.7 | E46: 119.3 | F46: 121 | G46: 116.1 | H46: 106.9 | I46: 118.7 | J46: 116.3 | K46: 109.8 | L46: 99.6 | M46: 111.8 | N46: 112.7 | O46: 119.3 | P46: 116.1 | Q46: 115.2 | R46: 116.8 | S46: 113.7 | T46: 116.4 | U46: 113.2 | V46: 112.5 | W46: 113.2 | X46: 111.2 | Y46: 111.4 | Z46: 110.6 | AA46: 112 | AB46: 109 | AC46: 111.3 | AD46: 114.2
A47: Rural | B47: 2014 | C47: April | D47: 120.2 | E47: 118.9 | F47: 118.1 | G47: 117 | H47: 109.7 | I47: 125.5 | J47: 120.5 | K47: 111 | L47: 102.6 | M47: 111.2 | N47: 113.5 | O47: 118.7 | P47: 117.2 | Q47: 115.4 | R47: 118.1 | S47: 116.1 | T47: 117.8 | U47: NA | V47: 113.4 | W47: 113.7 | X47: 111.8 | Y47: 111.2 | Z47: 110.5 | AA47: 113 | AB47: 108.9 | AC47: 111.5 | AD47: 115.4
A48: Urban | B48: 2014 | C48: April | D48: 122.5 | E48: 121.7 | F48: 113.3 | G48: 117 | H48: 103.1 | I48: 126.7 | J48: 121.2 | K48: 111 | L48: 100.3 | M48: 115.3 | N48: 112.7 | O48: 121 | P48: 118.2 | Q48: 117.6 | R48: 116.3 | S48: 112.5 | T48: 115.7 | U48: 113.9 | V48: 110.9 | W48: 113.4 | X48: 111 | Y48: 111.2 | Z48: 111.2 | AA48: 112.5 | AB48: 109.1 | AC48: 111.4 | AD48: 114.7
A49: Rural+Urban | B49: 2014 | C49: April | D49: 120.9 | E49: 119.9 | F49: 116.2 | G49: 117 | H49: 107.3 | I49: 126.1 | J49: 120.7 | K49: 111 | L49: 101.8 | M49: 112.6 | N49: 113.2 | O49: 119.8 | P49: 117.6 | Q49: 116 | R49: 117.4 | S49: 114.6 | T49: 117 | U49: 113.9 | V49: 112.5 | W49: 113.6 | X49: 111.5 | Y49: 111.2 | Z49: 110.9 | AA49: 112.7 | AB49: 109 | AC49: 111.5 | AD49: 115.1
A50: Rural | B50: 2014 | C50: May | D50: 120.3 | E50: 120.2 | F50: 116.9 | G50: 118 | H50: 110.1 | I50: 126.3 | J50: 123.9 | K50: 111.5 | L50: 103.5 | M50: 111.6 | N50: 114.2 | O50: 119.2 | P50: 118.2 | Q50: 116.3 | R50: 118.7 | S50: 116.8 | T50: 118.5 | U50: NA | V50: 113.4 | W50: 114.1 | X50: 112.1 | Y50: 111.4 | Z50: 110.9 | AA50: 113.1 | AB50: 108.9 | AC50: 111.8 | AD50: 116
A51: Urban | B51: 2014 | C51: May | D51: 122.7 | E51: 124.1 | F51: 114.2 | G51: 119.1 | H51: 103.5 | I51: 129.2 | J51: 127 | K51: 112.6 | L51: 101.3 | M51: 117 | N51: 112.9 | O51: 121.7 | P51: 120 | Q51: 118.3 | R51: 116.8 | S51: 112.9 | T51: 116.2 | U51: 114.3 | V51: 111.1 | W51: 114.1 | X51: 111.2 | Y51: 111.3 | Z51: 111.5 | AA51: 112.9 | AB51: 109.3 | AC51: 111.7 | AD51: 115.6
A52: Rural+Urban | B52: 2014 | C52: May | D52: 121.1 | E52: 121.6 | F52: 115.9 | G52: 118.4 | H52: 107.7 | I52: 127.7 | J52: 125 | K52: 111.9 | L52: 102.8 | M52: 113.4 | N52: 113.7 | O52: 120.4 | P52: 118.9 | Q52: 116.8 | R52: 118 | S52: 115.2 | T52: 117.6 | U52: 114.3 | V52: 112.5 | W52: 114.1 | X52: 111.8 | Y52: 111.3 | Z52: 111.2 | AA52: 113 | AB52: 109.1 | AC52: 111.8 | AD52: 115.8
A53: Rural | B53: 2014 | C53: June | D53: 120.7 | E53: 121.6 | F53: 116.1 | G53: 119.3 | H53: 110.3 | I53: 125.8 | J53: 129.3 | K53: 112.2 | L53: 103.6 | M53: 112.3 | N53: 114.9 | O53: 120.1 | P53: 119.5 | Q53: 117.3 | R53: 119.7 | S53: 117.3 | T53: 119.3 | U53: NA | V53: 114.4 | W53: 114.9 | X53: 112.8 | Y53: 112.2 | Z53: 111.4 | AA53: 114.3 | AB53: 108 | AC53: 112.3 | AD53: 117
A54: Urban | B54: 2014 | C54: June | D54: 123.1 | E54: 125.9 | F54: 115.4 | G54: 120.4 | H54: 103.4 | I54: 131.2 | J54: 137.5 | K54: 112.8 | L54: 101.4 | M54: 118.3 | N54: 113.2 | O54: 122.4 | P54: 122 | Q54: 119 | R54: 117.4 | S54: 113.2 | T54: 116.7 | U54: 113.9 | V54: 111.2 | W54: 114.3 | X54: 111.4 | Y54: 111.5 | Z54: 111.8 | AA54: 115.1 | AB54: 108.7 | AC54: 112.2 | AD54: 116.4
A55: Rural+Urban | B55: 2014 | C55: June | D55: 121.5 | E55: 123.1 | F55: 115.8 | G55: 119.7 | H55: 107.8 | I55: 128.3 | J55: 132.1 | K55: 112.4 | L55: 102.9 | M55: 114.3 | N55: 114.2 | O55: 121.2 | P55: 120.4 | Q55: 117.8 | R55: 118.8 | S55: 115.6 | T55: 118.3 | U55: 113.9 | V55: 113.2 | W55: 114.6 | X55: 112.3 | Y55: 111.8 | Z55: 111.6 | AA55: 114.8 | AB55: 108.3 | AC55: 112.3 | AD55: 116.7
A56: Rural | B56: 2014 | C56: July | D56: 121.7 | E56: 122.5 | F56: 117.7 | G56: 120.6 | H56: 110.4 | I56: 129.1 | J56: 150.1 | K56: 113.2 | L56: 104.8 | M56: 113.3 | N56: 115.6 | O56: 120.9 | P56: 123.3 | Q56: 118 | R56: 120.7 | S56: 118.3 | T56: 120.3 | U56: NA | V56: 115.3 | W56: 115.4 | X56: 113.4 | Y56: 113.2 | Z56: 111.8 | AA56: 115.5 | AB56: 108.8 | AC56: 113.1 | AD56: 119.5
A57: Urban | B57: 2014 | C57: July | D57: 123.8 | E57: 126.4 | F57: 118 | G57: 121.6 | H57: 103.5 | I57: 133.7 | J57: 172.4 | K57: 113.1 | L57: 102.7 | M57: 120 | N57: 113.8 | O57: 123.4 | P57: 127.1 | Q57: 121 | R57: 118 | S57: 113.6 | T57: 117.4 | U57: 114.8 | V57: 111.6 | W57: 114.9 | X57: 111.5 | Y57: 113 | Z57: 112.4 | AA57: 117.8 | AB57: 109.7 | AC57: 113.5 | AD57: 118.9
A58: Rural+Urban | B58: 2014 | C58: July | D58: 122.4 | E58: 123.9 | F58: 117.8 | G58: 121 | H58: 107.9 | I58: 131.2 | J58: 157.7 | K58: 113.2 | L58: 104.1 | M58: 115.5 | N58: 114.8 | O58: 122.1 | P58: 124.7 | Q58: 118.8 | R58: 119.6 | S58: 116.3 | T58: 119.1 | U58: 114.8 | V58: 113.9 | W58: 115.2 | X58: 112.7 | Y58: 113.1 | Z58: 112.1 | AA58: 116.8 | AB58: 109.2 | AC58: 113.3 | AD58: 119.2
A59: Rural | B59: 2014 | C59: August | D59: 121.8 | E59: 122.8 | F59: 117.8 | G59: 121.9 | H59: 110.6 | I59: 129.7 | J59: 161.1 | K59: 114.1 | L59: 105.1 | M59: 114.6 | N59: 115.8 | O59: 121.7 | P59: 125.3 | Q59: 118.8 | R59: 120.9 | S59: 118.8 | T59: 120.7 | U59: NA | V59: 115.4 | W59: 115.9 | X59: 114 | Y59: 113.2 | Z59: 112.2 | AA59: 116.2 | AB59: 109.4 | AC59: 113.5 | AD59: 120.7
A60: Urban | B60: 2014 | C60: August | D60: 124.8 | E60: 127.3 | F60: 116.5 | G60: 122.2 | H60: 103.6 | I60: 132.7 | J60: 181.9 | K60: 115.2 | L60: 102.7 | M60: 122.1 | N60: 114.4 | O60: 124.7 | P60: 128.9 | Q60: 123 | R60: 118.6 | S60: 114.1 | T60: 117.9 | U60: 115.5 | V60: 111.8 | W60: 115.3 | X60: 112.2 | Y60: 112.5 | Z60: 112.9 | AA60: 119.2 | AB60: 110.5 | AC60: 113.9 | AD60: 119.9
A61: Rural+Urban | B61: 2014 | C61: August | D61: 122.7 | E61: 124.4 | F61: 117.3 | G61: 122 | H61: 108 | I61: 131.1 | J61: 168.2 | K61: 114.5 | L61: 104.3 | M61: 117.1 | N61: 115.2 | O61: 123.1 | P61: 126.6 | Q61: 119.9 | R61: 120 | S61: 116.8 | T61: 119.6 | U61: 115.5 | V61: 114 | W61: 115.6 | X61: 113.3 | Y61: 112.8 | Z61: 112.6 | AA61: 118 | AB61: 109.9 | AC61: 113.7 | AD61: 120.3
A62: Rural | B62: 2014 | C62: September | D62: 122.3 | E62: 122.4 | F62: 117.8 | G62: 122.7 | H62: 110.4 | I62: 129.8 | J62: 158.8 | K62: 115 | L62: 104.7 | M62: 114.9 | N62: 116.5 | O62: 122.6 | P62: 125.3 | Q62: 119.5 | R62: 121.7 | S62: 119.2 | T62: 121.3 | U62: NA | V62: 115.8 | W62: 116.7 | X62: 114.5 | Y62: 112.8 | Z62: 112.6 | AA62: 116.6 | AB62: 109.1 | AC62: 113.7 | AD62: 120.9
A63: Urban | B63: 2014 | C63: September | D63: 124.2 | E63: 125.4 | F63: 116.4 | G63: 122.7 | H63: 103.5 | I63: 124.5 | J63: 168.6 | K63: 116.9 | L63: 101.9 | M63: 122.9 | N63: 114.8 | O63: 125.2 | P63: 126.7 | Q63: 124.3 | R63: 119.2 | S63: 114.5 | T63: 118.4 | U63: 116.1 | V63: 111.8 | W63: 115.5 | X63: 112.3 | Y63: 111.2 | Z63: 113.4 | AA63: 120 | AB63: 110 | AC63: 113.6 | AD63: 119.2
A64: Rural+Urban | B64: 2014 | C64: September | D64: 122.9 | E64: 123.5 | F64: 117.3 | G64: 122.7 | H64: 107.9 | I64: 127.3 | J64: 162.1 | K64: 115.6 | L64: 103.8 | M64: 117.6 | N64: 115.8 | O64: 123.8 | P64: 125.8 | Q64: 120.8 | R64: 120.7 | S64: 117.2 | T64: 120.1 | U64: 116.1 | V64: 114.3 | W64: 116.1 | X64: 113.7 | Y64: 112 | Z64: 113.1 | AA64: 118.6 | AB64: 109.5 | AC64: 113.7 | AD64: 120.1
A65: Rural | B65: 2014 | C65: October | D65: 122.6 | E65: 122.5 | F65: 118.3 | G65: 123.2 | H65: 110.5 | I65: 128.9 | J65: 155.3 | K65: 115.5 | L65: 104 | M65: 115.3 | N65: 116.8 | O65: 123.2 | P65: 125.1 | Q65: 120 | R65: 122.7 | S65: 120.3 | T65: 122.3 | U65: NA | V65: 116.4 | W65: 117.5 | X65: 115.3 | Y65: 112.6 | Z65: 113 | AA65: 116.9 | AB65: 109.3 | AC65: 114 | AD65: 121
A66: Urban | B66: 2014 | C66: October | D66: 124.6 | E66: 126.1 | F66: 117.8 | G66: 123.1 | H66: 103.5 | I66: 123.5 | J66: 159.6 | K66: 117.4 | L66: 101.2 | M66: 123.8 | N66: 115.2 | O66: 125.9 | P66: 125.8 | Q66: 124.3 | R66: 119.6 | S66: 114.9 | T66: 118.9 | U66: 116.7 | V66: 112 | W66: 115.8 | X66: 112.6 | Y66: 111 | Z66: 113.6 | AA66: 120.2 | AB66: 110.1 | AC66: 113.7 | AD66: 119.1
A67: Rural+Urban | B67: 2014 | C67: October | D67: 123.2 | E67: 123.8 | F67: 118.1 | G67: 123.2 | H67: 107.9 | I67: 126.4 | J67: 156.8 | K67: 116.1 | L67: 103.1 | M67: 118.1 | N67: 116.1 | O67: 124.5 | P67: 125.4 | Q67: 121.1 | R67: 121.5 | S67: 118.1 | T67: 121 | U67: 116.7 | V67: 114.7 | W67: 116.7 | X67: 114.3 | Y67: 111.8 | Z67: 113.3 | AA67: 118.8 | AB67: 109.6 | AC67: 113.9 | AD67: 120.1
A68: Rural | B68: 2014 | C68: November | D68: 122.7 | E68: 122.6 | F68: 119.9 | G68: 124 | H68: 110.5 | I68: 128.8 | J68: 152 | K68: 116.2 | L68: 103.3 | M68: 115.8 | N68: 116.8 | O68: 124.5 | P68: 124.9 | Q68: 120.8 | R68: 123.3 | S68: 120.5 | T68: 122.9 | U68: NA | V68: 117.3 | W68: 118.1 | X68: 115.9 | Y68: 112 | Z68: 113.3 | AA68: 117.2 | AB68: 108.8 | AC68: 114.1 | AD68: 121.1
A69: Urban | B69: 2014 | C69: November | D69: 124.5 | E69: 125.6 | F69: 122.7 | G69: 124.6 | H69: 103.2 | I69: 122.2 | J69: 153.2 | K69: 119.3 | L69: 99.8 | M69: 124.6 | N69: 115.8 | O69: 126.9 | P69: 125.4 | Q69: 125.8 | R69: 120.3 | S69: 115.4 | T69: 119.5 | U69: 117.1 | V69: 112.6 | W69: 116.4 | X69: 113 | Y69: 109.7 | Z69: 114 | AA69: 120.3 | AB69: 109.6 | AC69: 113.4 | AD69: 119
A70: Rural+Urban | B70: 2014 | C70: November | D70: 123.3 | E70: 123.7 | F70: 121 | G70: 124.2 | H70: 107.8 | I70: 125.7 | J70: 152.4 | K70: 117.2 | L70: 102.1 | M70: 118.7 | N70: 116.4 | O70: 125.6 | P70: 125.1 | Q70: 122.1 | R70: 122.1 | S70: 118.4 | T70: 121.6 | U70: 117.1 | V70: 115.5 | W70: 117.3 | X70: 114.8 | Y70: 110.8 | Z70: 113.7 | AA70: 119 | AB70: 109.1 | AC70: 113.8 | AD70: 120.1
A71: Rural | B71: 2014 | C71: December | D71: 122.4 | E71: 122.4 | F71: 121.8 | G71: 124.2 | H71: 110.2 | I71: 128.6 | J71: 140.3 | K71: 116.3 | L71: 102 | M71: 116 | N71: 117.3 | O71: 124.8 | P71: 123.3 | Q71: 121.7 | R71: 123.8 | S71: 120.6 | T71: 123.3 | U71: NA | V71: 117.4 | W71: 118.2 | X71: 116.2 | Y71: 111.5 | Z71: 113.3 | AA71: 117.7 | AB71: 109.4 | AC71: 114.2 | AD71: 120.3
A72: Urban | B72: 2014 | C72: December | D72: 124 | E72: 124.7 | F72: 126.3 | G72: 124.9 | H72: 103 | I72: 122.3 | J72: 141 | K72: 120.1 | L72: 97.8 | M72: 125.4 | N72: 116.1 | O72: 127.6 | P72: 124 | Q72: 126.4 | R72: 120.7 | S72: 115.8 | T72: 120 | U72: 116.5 | V72: 113 | W72: 116.8 | X72: 113.2 | Y72: 108.8 | Z72: 114.3 | AA72: 120.7 | AB72: 110.4 | AC72: 113.4 | AD72: 118.4
A73: Rural+Urban | B73: 2014 | C73: December | D73: 122.9 | E73: 123.2 | F73: 123.5 | G73: 124.5 | H73: 107.6 | I73: 125.7 | J73: 140.5 | K73: 117.6 | L73: 100.6 | M73: 119.1 | N73: 116.8 | O73: 126.1 | P73: 123.6 | Q73: 123 | R73: 122.6 | S73: 118.6 | T73: 122 | U73: 116.5 | V73: 115.7 | W73: 117.5 | X73: 115.1 | Y73: 110.1 | Z73: 113.9 | AA73: 119.5 | AB73: 109.8 | AC73: 113.8 | AD73: 119.4
A74: Rural | B74: 2015 | C74: January | D74: 123.1 | E74: 123.1 | F74: 122.1 | G74: 124.9 | H74: 111 | I74: 130.4 | J74: 132.3 | K74: 117.2 | L74: 100.5 | M74: 117.2 | N74: 117.9 | O74: 125.6 | P74: 122.8 | Q74: 122.7 | R74: 124.4 | S74: 121.6 | T74: 124 | U74: NA | V74: 118.4 | W74: 118.9 | X74: 116.6 | Y74: 111 | Z74: 114 | AA74: 118.2 | AB74: 110.2 | AC74: 114.5 | AD74: 120.3
A75: Urban | B75: 2015 | C75: January | D75: 124 | E75: 125.5 | F75: 126.6 | G75: 125.2 | H75: 104.3 | I75: 121.3 | J75: 134.4 | K75: 122.9 | L75: 96.1 | M75: 126.6 | N75: 116.5 | O75: 128 | P75: 123.5 | Q75: 127.4 | R75: 121 | S75: 116.1 | T75: 120.2 | U75: 117.3 | V75: 113.4 | W75: 117.2 | X75: 113.7 | Y75: 107.9 | Z75: 114.6 | AA75: 120.8 | AB75: 111.4 | AC75: 113.4 | AD75: 118.5
A76: Rural+Urban | B76: 2015 | C76: January | D76: 123.4 | E76: 123.9 | F76: 123.8 | G76: 125 | H76: 108.5 | I76: 126.2 | J76: 133 | K76: 119.1 | L76: 99 | M76: 120.3 | N76: 117.3 | O76: 126.7 | P76: 123.1 | Q76: 124 | R76: 123.1 | S76: 119.3 | T76: 122.5 | U76: 117.3 | V76: 116.5 | W76: 118.1 | X76: 115.5 | Y76: 109.4 | Z76: 114.3 | AA76: 119.7 | AB76: 110.7 | AC76: 114 | AD76: 119.5
A77: Rural | B77: 2015 | C77: February | D77: 123.4 | E77: 124.4 | F77: 122.1 | G77: 125.8 | H77: 111.5 | I77: 129.4 | J77: 128.2 | K77: 118.8 | L77: 100 | M77: 118.6 | N77: 118.8 | O77: 126.8 | P77: 122.8 | Q77: 124.2 | R77: 125.4 | S77: 122.7 | T77: 125 | U77: NA | V77: 120 | W77: 119.6 | X77: 117.7 | Y77: 110.9 | Z77: 114.8 | AA77: 118.7 | AB77: 110.8 | AC77: 115 | AD77: 120.6
A78: Urban | B78: 2015 | C78: February | D78: 124.3 | E78: 126.5 | F78: 119.5 | G78: 125.6 | H78: 104.9 | I78: 121.6 | J78: 131.8 | K78: 125.1 | L78: 95 | M78: 127.7 | N78: 116.8 | O78: 128.6 | P78: 123.7 | Q78: 128.1 | R78: 121.3 | S78: 116.5 | T78: 120.6 | U78: 118.1 | V78: 114 | W78: 117.7 | X78: 114.1 | Y78: 106.8 | Z78: 114.9 | AA78: 120.4 | AB78: 111.7 | AC78: 113.2 | AD78: 118.7
A79: Rural+Urban | B79: 2015 | C79: February | D79: 123.7 | E79: 125.1 | F79: 121.1 | G79: 125.7 | H79: 109.1 | I79: 125.8 | J79: 129.4 | K79: 120.9 | L79: 98.3 | M79: 121.6 | N79: 118 | O79: 127.6 | P79: 123.1 | Q79: 125.2 | R79: 123.8 | S79: 120.1 | T79: 123.3 | U79: 118.1 | V79: 117.7 | W79: 118.7 | X79: 116.3 | Y79: 108.7 | Z79: 114.9 | AA79: 119.7 | AB79: 111.2 | AC79: 114.1 | AD79: 119.7
A80: Rural | B80: 2015 | C80: March | D80: 123.3 | E80: 124.7 | F80: 118.9 | G80: 126 | H80: 111.8 | I80: 130.9 | J80: 128 | K80: 119.9 | L80: 98.9 | M80: 119.4 | N80: 118.9 | O80: 127.7 | P80: 123.1 | Q80: 124.7 | R80: 126 | S80: 122.9 | T80: 125.5 | U80: NA | V80: 120.6 | W80: 120.2 | X80: 118.2 | Y80: 111.6 | Z80: 115.5 | AA80: 119.4 | AB80: 110.8 | AC80: 115.5 | AD80: 121.1
A81: Urban | B81: 2015 | C81: March | D81: 124 | E81: 126.7 | F81: 113.5 | G81: 125.9 | H81: 104.8 | I81: 123.8 | J81: 131.4 | K81: 127.2 | L81: 93.2 | M81: 127.4 | N81: 117 | O81: 129.2 | P81: 123.9 | Q81: 128.8 | R81: 121.7 | S81: 116.9 | T81: 120.9 | U81: 118.6 | V81: 114.4 | W81: 118 | X81: 114.3 | Y81: 108.4 | Z81: 115.4 | AA81: 120.6 | AB81: 111.3 | AC81: 113.8 | AD81: 119.1
A82: Rural+Urban | B82: 2015 | C82: March | D82: 123.5 | E82: 125.4 | F82: 116.8 | G82: 126 | H82: 109.2 | I82: 127.6 | J82: 129.2 | K82: 122.4 | L82: 97 | M82: 122.1 | N82: 118.1 | O82: 128.4 | P82: 123.4 | Q82: 125.8 | R82: 124.3 | S82: 120.4 | T82: 123.7 | U82: 118.6 | V82: 118.3 | W82: 119.2 | X82: 116.7 | Y82: 109.9 | Z82: 115.4 | AA82: 120.1 | AB82: 111 | AC82: 114.7 | AD82: 120.2
A83: Rural | B83: 2015 | C83: April | D83: 123.3 | E83: 125.5 | F83: 117.2 | G83: 126.8 | H83: 111.9 | I83: 134.2 | J83: 127.5 | K83: 121.5 | L83: 97.8 | M83: 119.8 | N83: 119.4 | O83: 128.7 | P83: 123.6 | Q83: 125.7 | R83: 126.4 | S83: 123.3 | T83: 126 | U83: NA | V83: 121.2 | W83: 120.9 | X83: 118.6 | Y83: 111.9 | Z83: 116.2 | AA83: 119.9 | AB83: 111.6 | AC83: 116 | AD83: 121.5
A84: Urban | B84: 2015 | C84: April | D84: 123.8 | E84: 128.2 | F84: 110 | G84: 126.3 | H84: 104.5 | I84: 130.6 | J84: 130.8 | K84: 131.3 | L84: 91.6 | M84: 127.7 | N84: 117.2 | O84: 129.5 | P84: 124.6 | Q84: 130.1 | R84: 122.1 | S84: 117.2 | T84: 121.3 | U84: 119.2 | V84: 114.7 | W84: 118.4 | X84: 114.6 | Y84: 108.4 | Z84: 115.6 | AA84: 121.7 | AB84: 111.8 | AC84: 114.2 | AD84: 119.7
A85: Rural+Urban | B85: 2015 | C85: April | D85: 123.5 | E85: 126.4 | F85: 114.4 | G85: 126.6 | H85: 109.2 | I85: 132.5 | J85: 128.6 | K85: 124.8 | L85: 95.7 | M85: 122.4 | N85: 118.5 | O85: 129.1 | P85: 124 | Q85: 126.9 | R85: 124.7 | S85: 120.8 | T85: 124.1 | U85: 119.2 | V85: 118.7 | W85: 119.7 | X85: 117.1 | Y85: 110.1 | Z85: 115.9 | AA85: 121 | AB85: 111.7 | AC85: 115.1 | AD85: 120.7
A86: Rural | B86: 2015 | C86: May | D86: 123.5 | E86: 127.1 | F86: 117.3 | G86: 127.7 | H86: 112.5 | I86: 134.1 | J86: 128.5 | K86: 124.3 | L86: 97.6 | M86: 120.7 | N86: 120.2 | O86: 129.8 | P86: 124.4 | Q86: 126.7 | R86: 127.3 | S86: 124.1 | T86: 126.8 | U86: NA | V86: 121.9 | W86: 121.5 | X86: 119.4 | Y86: 113.3 | Z86: 116.7 | AA86: 120.5 | AB86: 112.3 | AC86: 116.9 | AD86: 122.4
A87: Urban | B87: 2015 | C87: May | D87: 123.8 | E87: 129.7 | F87: 111.3 | G87: 126.6 | H87: 105.2 | I87: 130.8 | J87: 135.6 | K87: 142.6 | L87: 90.8 | M87: 128.8 | N87: 117.7 | O87: 129.9 | P87: 126.1 | Q87: 131.3 | R87: 122.4 | S87: 117.4 | T87: 121.6 | U87: 119.6 | V87: 114.9 | W87: 118.7 | X87: 114.9 | Y87: 110.8 | Z87: 116 | AA87: 122 | AB87: 112.4 | AC87: 115.2 | AD87: 120.7
A88: Rural+Urban | B88: 2015 | C88: May | D88: 123.6 | E88: 128 | F88: 115 | G88: 127.3 | H88: 109.8 | I88: 132.6 | J88: 130.9 | K88: 130.5 | L88: 95.3 | M88: 123.4 | N88: 119.2 | O88: 129.8 | P88: 125 | Q88: 127.9 | R88: 125.4 | S88: 121.3 | T88: 124.7 | U88: 119.6 | V88: 119.2 | W88: 120.2 | X88: 117.7 | Y88: 112 | Z88: 116.3 | AA88: 121.4 | AB88: 112.3 | AC88: 116.1 | AD88: 121.6
A89: Rural | B89: 2015 | C89: June | D89: 124.1 | E89: 130.4 | F89: 122.1 | G89: 128.7 | H89: 114.1 | I89: 133.2 | J89: 135.2 | K89: 131.9 | L89: 96.3 | M89: 123 | N89: 121.1 | O89: 131.2 | P89: 126.6 | Q89: 128.2 | R89: 128.4 | S89: 125.1 | T89: 128 | U89: NA | V89: 122.6 | W89: 122.8 | X89: 120.4 | Y89: 114.2 | Z89: 117.9 | AA89: 122 | AB89: 113 | AC89: 117.9 | AD89: 124.1
A90: Urban | B90: 2015 | C90: June | D90: 123.6 | E90: 134.4 | F90: 120.9 | G90: 127.3 | H90: 106 | I90: 132.3 | J90: 146.7 | K90: 148.1 | L90: 89.8 | M90: 130.5 | N90: 118 | O90: 130.5 | P90: 128.5 | Q90: 132.1 | R90: 123.2 | S90: 117.6 | T90: 122.3 | U90: 119 | V90: 115.1 | W90: 119.2 | X90: 115.4 | Y90: 111.7 | Z90: 116.2 | AA90: 123.8 | AB90: 112.5 | AC90: 116 | AD90: 121.7
A91: Rural+Urban | B91: 2015 | C91: June | D91: 123.9 | E91: 131.8 | F91: 121.6 | G91: 128.2 | H91: 111.1 | I91: 132.8 | J91: 139.1 | K91: 137.4 | L91: 94.1 | M91: 125.5 | N91: 119.8 | O91: 130.9 | P91: 127.3 | Q91: 129.2 | R91: 126.4 | S91: 122 | T91: 125.7 | U91: 119 | V91: 119.8 | W91: 121.1 | X91: 118.5 | Y91: 112.9 | Z91: 116.9 | AA91: 123.1 | AB91: 112.8 | AC91: 117 | AD91: 123
A92: Rural | B92: 2015 | C92: July | D92: 124 | E92: 131.5 | F92: 122 | G92: 128.7 | H92: 113.5 | I92: 133.3 | J92: 140.8 | K92: 133.8 | L92: 94.1 | M92: 123.4 | N92: 121 | O92: 131.7 | P92: 127.5 | Q92: 129.4 | R92: 128.8 | S92: 125.5 | T92: 128.3 | U92: NA | V92: 123 | W92: 123 | X92: 120.8 | Y92: 114.1 | Z92: 118 | AA92: 122.9 | AB92: 112.7 | AC92: 118.1 | AD92: 124.7
A93: Urban | B93: 2015 | C93: July | D93: 123.2 | E93: 134.3 | F93: 119.5 | G93: 127.7 | H93: 106.3 | I93: 132.8 | J93: 153.5 | K93: 149.5 | L93: 85.7 | M93: 131.5 | N93: 118.3 | O93: 131.1 | P93: 129.5 | Q93: 133.1 | R93: 123.5 | S93: 117.9 | T93: 122.7 | U93: 119.9 | V93: 115.3 | W93: 119.5 | X93: 116 | Y93: 111.5 | Z93: 116.6 | AA93: 125.4 | AB93: 111.7 | AC93: 116.3 | AD93: 122.4
A94: Rural+Urban | B94: 2015 | C94: July | D94: 123.7 | E94: 132.5 | F94: 121 | G94: 128.3 | H94: 110.9 | I94: 133.1 | J94: 145.1 | K94: 139.1 | L94: 91.3 | M94: 126.1 | N94: 119.9 | O94: 131.4 | P94: 128.2 | Q94: 130.4 | R94: 126.7 | S94: 122.3 | T94: 126.1 | U94: 119.9 | V94: 120.1 | W94: 121.3 | X94: 119 | Y94: 112.7 | Z94: 117.2 | AA94: 124.4 | AB94: 112.3 | AC94: 117.2 | AD94: 123.6
A95: Rural | B95: 2015 | C95: August | D95: 124.7 | E95: 131.3 | F95: 121.3 | G95: 128.8 | H95: 114 | I95: 134.2 | J95: 153.6 | K95: 137.9 | L95: 93.1 | M95: 123.9 | N95: 121.5 | O95: 132.5 | P95: 129.8 | Q95: 130.1 | R95: 129.5 | S95: 126.3 | T95: 129 | U95: NA | V95: 123.8 | W95: 123.7 | X95: 121.1 | Y95: 113.6 | Z95: 118.5 | AA95: 123.6 | AB95: 112.5 | AC95: 118.2 | AD95: 126.1
A96: Urban | B96: 2015 | C96: August | D96: 123.1 | E96: 131.7 | F96: 118.1 | G96: 128 | H96: 106.8 | I96: 130.1 | J96: 165.5 | K96: 156 | L96: 85.3 | M96: 132.7 | N96: 118.8 | O96: 131.7 | P96: 131.1 | Q96: 134.2 | R96: 123.7 | S96: 118.2 | T96: 122.9 | U96: 120.9 | V96: 115.3 | W96: 120 | X96: 116.6 | Y96: 109.9 | Z96: 117.2 | AA96: 126.2 | AB96: 112 | AC96: 116.2 | AD96: 123.2
A97: Rural+Urban | B97: 2015 | C97: August | D97: 124.2 | E97: 131.4 | F97: 120.1 | G97: 128.5 | H97: 111.4 | I97: 132.3 | J97: 157.6 | K97: 144 | L97: 90.5 | M97: 126.8 | N97: 120.4 | O97: 132.1 | P97: 130.3 | Q97: 131.2 | R97: 127.2 | S97: 122.9 | T97: 126.6 | U97: 120.9 | V97: 120.6 | W97: 122 | X97: 119.4 | Y97: 111.7 | Z97: 117.8 | AA97: 125.1 | AB97: 112.3 | AC97: 117.2 | AD97: 124.8
A98: Rural | B98: 2015 | C98: September | D98: 125.1 | E98: 131.1 | F98: 120.7 | G98: 129.2 | H98: 114.7 | I98: 132.3 | J98: 158.9 | K98: 142.1 | L98: 92.5 | M98: 125.4 | N98: 121.9 | O98: 132.7 | P98: 131 | Q98: 131 | R98: 130.4 | S98: 126.8 | T98: 129.9 | U98: NA | V98: 123.7 | W98: 124.5 | X98: 121.4 | Y98: 113.8 | Z98: 119.6 | AA98: 124.5 | AB98: 113.7 | AC98: 118.8 | AD98: 127
A99: Urban | B99: 2015 | C99: September | D99: 123.4 | E99: 129 | F99: 115.6 | G99: 128.3 | H99: 107 | I99: 124 | J99: 168.5 | K99: 165.4 | L99: 86.3 | M99: 134.4 | N99: 119.1 | O99: 132.3 | P99: 131.5 | Q99: 134.7 | R99: 124 | S99: 118.6 | T99: 123.2 | U99: 121.6 | V99: 115.1 | W99: 120.4 | X99: 117.1 | Y99: 109.1 | Z99: 117.3 | AA99: 126.5 | AB99: 112.9 | AC99: 116.2 | AD99: 123.5
A100: Rural+Urban | B100: 2015 | C100: September | D100: 124.6 | E100: 130.4 | F100: 118.7 | G100: 128.9 | H100: 111.9 | I100: 128.4 | J100: 162.2 | K100: 150 | L100: 90.4 | M100: 128.4 | N100: 120.7 | O100: 132.5 | P100: 131.2 | Q100: 132 | R100: 127.9 | S100: 123.4 | T100: 127.2 | U100: 121.6 | V100: 120.4 | W100: 122.6 | X100: 119.8 | Y100: 111.3 | Z100: 118.3 | AA100: 125.7 | AB100: 113.4 | AC100: 117.5 | AD100: 125.4
...

Sheet Problem_Statement

Sheet 1.CPI Contribution Analysis
C1: Consumer Price Index (CPI) data, Government of India
C2: Reference Month: May 2023
B3: Sector | C3: Year | D3: Month | E3: Cereals and products | F3: Meat and fish | G3: Egg | H3: Milk and products | I3: Oils and fats | J3: Fruits | K3: Vegetables | L3: Pulses and products | M3: Sugar and Confectionery | N3: Spices | O3: Non-alcoholic beverages | P3: Prepared meals, snacks, sweets etc. | Q3: Food and beverages | R3: Pan, tobacco and intoxicants | S3: Clothing | T3: Footwear | U3: Clothing and footwear | V3: Housing | W3: Fuel and light | X3: Household goods and services | Y3: Health | Z3: Transport and communication | AA3: Recreation and amusement | AB3: Education | AC3: Personal care and effects | AD3: Miscellaneous | AE3: General index
B4: Rural | C4: 2023 | D4: May | E4: 173.2 | F4: 211.5 | G4: 171 | H4: 179.6 | I4: 173.3 | J4: 169 | K4: 148.7 | L4: 174.9 | M4: 121.9 | N4: 221 | O4: 178.7 | P4: 191.1 | Q4: 176.8 | R4: 199.9 | S4: 191.2 | T4: 187.9 | U4: 190.8 | V4: - | W4: 182.5 | X4: 179.8 | Y4: 187.8 | Z4: 169.7 | AA4: 173.8 | AB4: 180.3 | AC4: 184.9 | AD4: 179.5 | AE4: 179.8
B5: Urban | C5: 2023 | D5: May | E5: 174.7 | F5: 219.4 | G5: 176.7 | H5: 179.4 | I5: 164.4 | J5: 175.8 | K5: 185 | L5: 176.9 | M5: 124.2 | N5: 211.9 | O5: 165.9 | P5: 197.7 | Q5: 183.1 | R5: 204.2 | S5: 181.3 | T5: 168.1 | U5: 179.3 | V5: 175.6 | W5: 183.4 | X5: 170.1 | Y5: 182.2 | Z5: 160.4 | AA5: 169.2 | AB5: 174.8 | AC5: 185.6 | AD5: 171.6 | AE5: 178.2
B6: Rural+Urban | C6: 2023 | D6: May | E6: 173.7 | F6: 214.3 | G6: 173.2 | H6: 179.5 | I6: 170 | J6: 172.2 | K6: 161 | L6: 175.6 | M6: 122.7 | N6: 218 | O6: 173.4 | P6: 194.2 | Q6: 179.1 | R6: 201 | S6: 187.3 | T6: 179.7 | U6: 186.2 | V6: 175.6 | W6: 182.8 | X6: 175.2 | Y6: 185.7 | Z6: 164.8 | AA6: 171.2 | AB6: 177.1 | AC6: 185.2 | AD6: 175.7 | AE6: 179.1
C9: May'2023 | K9: May'2023
B10: Category | C10: Rural | D10: Urban | E10: Rural+Urban | F10: New Food Category | H10: New Food Category | I10: Rural | J10: Urban | K10: Rural+Urban | L10: Rural | M10: Urban | N10: Rural+Urban
B11: Cereals and products | C11: 173.2 | D11: 174.7 | E11: 173.7 | F11: Food | H11: Food | I11: =SUMIFS(C$11:C$37,$F$11:$F$37,$H11) -> 2099.6 | J11: =SUMIFS(D$11:D$37,$F$11:$F$37,$H11) -> 2137.4 | K11: =SUMIFS(E$11:E$37,$F$11:$F$37,$H11) -> 2112.7 | L11: =I11/$I$21 -> 0.46670223 | M11: =J11/$J$21 -> 0.46055722 | N11: =K11/$K$21 -> 0.45391458
B12: Meat and fish | C12: 211.5 | D12: 219.4 | E12: 214.3 | F12: Food | H12: Luxury | I12: =SUMIFS(C$11:C$37,$F$11:$F$37,$H12) -> 749.7 | J12: =SUMIFS(D$11:D$37,$F$11:$F$37,$H12) -> 756.7 | K12: =SUMIFS(E$11:E$37,$F$11:$F$37,$H12) -> 751.6 | L12: =I12/$I$21 -> 0.16664444 | M12: =J12/$J$21 -> 0.16305027 | N12: =K12/$K$21 -> 0.16148161
B13: Egg | C13: 171 | D13: 176.7 | E13: 173.2 | F13: Food | H13: Clothing | I13: =SUMIFS(C$11:C$37,$F$11:$F$37,$H13) -> 569.9 | J13: =SUMIFS(D$11:D$37,$F$11:$F$37,$H13) -> 528.7 | K13: =SUMIFS(E$11:E$37,$F$11:$F$37,$H13) -> 553.2 | L13: =I13/$I$21 -> 0.12667823 | M13: =J13/$J$21 -> 0.11392187 | N13: =K13/$K$21 -> 0.11885528
B14: Milk and products | C14: 179.6 | D14: 179.4 | E14: 179.5 | F14: Food | H14: Housing | I14: =SUMIFS(C$11:C$37,$F$11:$F$37,$H14) -> 179.8 | J14: =SUMIFS(D$11:D$37,$F$11:$F$37,$H14) -> 345.7 | K14: =SUMIFS(E$11:E$37,$F$11:$F$37,$H14) -> 350.8 | L14: =I14/$I$21 -> 0.039966213 | M14: =J14/$J$21 -> 0.074489862 | N14: =K14/$K$21 -> 0.075369543
B15: Oils and fats | C15: 173.3 | D15: 164.4 | E15: 170 | F15: Food | H15: Fuel and light | I15: =SUMIFS(C$11:C$37,$F$11:$F$37,$H15) -> 182.5 | J15: =SUMIFS(D$11:D$37,$F$11:$F$37,$H15) -> 183.4 | K15: =SUMIFS(E$11:E$37,$F$11:$F$37,$H15) -> 182.8 | L15: =I15/$I$21 -> 0.040566373 | M15: =J15/$J$21 -> 0.039518197 | N15: =K15/$K$21 -> 0.039274665
B16: Fruits | C16: 169 | D16: 175.8 | E16: 172.2 | F16: Food | H16: Health | I16: =SUMIFS(C$11:C$37,$F$11:$F$37,$H16) -> 187.8 | J16: =SUMIFS(D$11:D$37,$F$11:$F$37,$H16) -> 182.2 | K16: =SUMIFS(E$11:E$37,$F$11:$F$37,$H16) -> 185.7 | L16: =I16/$I$21 -> 0.041744465 | M16: =J16/$J$21 -> 0.039259626 | N16: =K16/$K$21 -> 0.039897731
B17: Vegetables | C17: 148.7 | D17: 185 | E17: 161 | F17: Food | H17: Transportation | I17: =SUMIFS(C$11:C$37,$F$11:$F$37,$H17) -> 169.7 | J17: =SUMIFS(D$11:D$37,$F$11:$F$37,$H17) -> 160.4 | K17: =SUMIFS(E$11:E$37,$F$11:$F$37,$H17) -> 164.8 | L17: =I17/$I$21 -> 0.03772117 | M17: =J17/$J$21 -> 0.034562262 | N17: =K17/$K$21 -> 0.035407356
B18: Pulses and products | C18: 174.9 | D18: 176.9 | E18: 175.6 | F18: Food | H18: Education | I18: =SUMIFS(C$11:C$37,$F$11:$F$37,$H18) -> 180.3 | J18: =SUMIFS(D$11:D$37,$F$11:$F$37,$H18) -> 174.8 | K18: =SUMIFS(E$11:E$37,$F$11:$F$37,$H18) -> 177.1 | L18: =I18/$I$21 -> 0.040077354 | M18: =J18/$J$21 -> 0.037665108 | N18: =K18/$K$21 -> 0.038050017
B19: Sugar and Confectionery | C19: 121.9 | D19: 124.2 | E19: 122.7 | F19: Food | H19: Other expenses | I19: =SUMIFS(C$11:C$37,$F$11:$F$37,$H19) -> 179.5 | J19: =SUMIFS(D$11:D$37,$F$11:$F$37,$H19) -> 171.6 | K19: =SUMIFS(E$11:E$37,$F$11:$F$37,$H19) -> 175.7 | L19: =I19/$I$21 -> 0.039899529 | M19: =J19/$J$21 -> 0.036975587 | N19: =K19/$K$21 -> 0.037749227
B20: Spices | C20: 221 | D20: 211.9 | E20: 218 | F20: Food | H20: GI | I20: =SUMIFS(C$11:C$37,$F$11:$F$37,$H20) -> 179.8 | J20: =SUMIFS(D$11:D$37,$F$11:$F$37,$H20) -> 178.2 | K20: =SUMIFS(E$11:E$37,$F$11:$F$37,$H20) -> 179.1
B21: Non-alcoholic beverages | C21: 178.7 | D21: 165.9 | E21: 173.4 | F21: Food | H21: Total (Exc GI) | I21: =SUM(I11:I19) -> 4498.8 | J21: =SUM(J11:J19) -> 4640.9 | K21: =SUM(K11:K19) -> 4654.4 | L21: =SUM(L11:L19) -> 1 | M21: =SUM(M11:M19) -> 1 | N21: =SUM(N11:N19) -> 1
B22: Prepared meals, snacks, sweets etc. | C22: 191.1 | D22: 197.7 | E22: 194.2 | F22: Luxury
B23: Food and beverages | C23: 176.8 | D23: 183.1 | E23: 179.1 | F23: Food
B24: Pan, tobacco and intoxicants | C24: 199.9 | D24: 204.2 | E24: 201 | F24: Luxury
B25: Clothing | C25: 191.2 | D25: 181.3 | E25: 187.3 | F25: Clothing
B26: Footwear | C26: 187.9 | D26: 168.1 | E26: 179.7 | F26: Clothing
B27: Clothing and footwear | C27: 190.8 | D27: 179.3 | E27: 186.2 | F27: Clothing
B28: Housing | C28: - | D28: 175.6 | E28: 175.6 | F28: Housing
B29: Fuel and light | C29: 182.5 | D29: 183.4 | E29: 182.8 | F29: Fuel and light
B30: Household goods and services | C30: 179.8 | D30: 170.1 | E30: 175.2 | F30: Housing
B31: Health | C31: 187.8 | D31: 182.2 | E31: 185.7 | F31: Health
B32: Transport and communication | C32: 169.7 | D32: 160.4 | E32: 164.8 | F32: Transportation
B33: Recreation and amusement | C33: 173.8 | D33: 169.2 | E33: 171.2 | F33: Luxury
B34: Education | C34: 180.3 | D34: 174.8 | E34: 177.1 | F34: Education
B35: Personal care and effects | C35: 184.9 | D35: 185.6 | E35: 185.2 | F35: Luxury
B36: Miscellaneous | C36: 179.5 | D36: 171.6 | E36: 175.7 | F36: Other expenses
B37: General index | C37: 179.8 | D37: 178.2 | E37: 179.1 | F37: GI
H43: Insight
H45: 1. Food has the highest contribution to CPI across all three categories, accounting for approximately 47% in Rural, 46% in Urban, and 45% in Rural + Urban areas.
H46: 2. Luxury is the second-largest contributor, accounting for approximately 17% in Rural, 16% in Urban, and 16% in Rural + Urban areas.
H47: 3. Clothing contributes approximately 13% in Rural, 11% in Urban, and 12% in Rural + Urban areas.
H48: 4. Housing has a higher contribution in Urban areas (7%) compared with Rural areas (4%), while the Rural + Urban contribution is approximately 8%.
H49: 5. Fuel & Light, Health, Transportation, Education, and Other Expenses each have relatively smaller individual contributions, generally around 4% across the Rural, Urban, and Rural + Urban categories.

Sheet 2.CPI YOY Analysis
G9: CPI Index and YoY Inflation — March Data
F10: Year | G10: Rural + Urban Index | H10: Rural Index | I10: Urban Index | J10: Rural + Urban YoY | K10: Rural YoY | L10: Urban YoY
F11: 2016 | G11: {=INDEX(Working_Data!$AD:$AD,MATCH(1,(Working_Data!$A:$A="Rural+Urban")*(Working_Data!$B:$B=$F11)*(Working_Data!$C:$C="March"),0))} -> 126 | H11: {=INDEX(Working_Data!$AD:$AD,MATCH(1,(Working_Data!$A:$A="Rural")*(Working_Data!$B:$B=$F11)*(Working_Data!$C:$C="March"),0))} -> 128 | I11: {=INDEX(Working_Data!$AD:$AD,MATCH(1,(Working_Data!$A:$A="Urban")*(Working_Data!$B:$B=$F11)*(Working_Data!$C:$C="March"),0))} -> 123.8 | J11: - | K11: - | L11: -
F12: 2017 | G12: {=INDEX(Working_Data!$AD:$AD,MATCH(1,(Working_Data!$A:$A="Rural+Urban")*(Working_Data!$B:$B=$F12)*(Working_Data!$C:$C="March"),0))} -> 130.9 | H12: {=INDEX(Working_Data!$AD:$AD,MATCH(1,(Working_Data!$A:$A="Rural")*(Working_Data!$B:$B=$F12)*(Working_Data!$C:$C="March"),0))} -> 132.8 | I12: {=INDEX(Working_Data!$AD:$AD,MATCH(1,(Working_Data!$A:$A="Urban")*(Working_Data!$B:$B=$F12)*(Working_Data!$C:$C="March"),0))} -> 128.7 | J12: =(G12-G11)/G11 -> 0.038888889 | K12: =(H12-H11)/H11 -> 0.0375 | L12: =(I12-I11)/I11 -> 0.039579968
F13: 2018 | G13: {=INDEX(Working_Data!$AD:$AD,MATCH(1,(Working_Data!$A:$A="Rural+Urban")*(Working_Data!$B:$B=$F13)*(Working_Data!$C:$C="March"),0))} -> 136.5 | H13: {=INDEX(Working_Data!$AD:$AD,MATCH(1,(Working_Data!$A:$A="Rural")*(Working_Data!$B:$B=$F13)*(Working_Data!$C:$C="March"),0))} -> 138.7 | I13: {=INDEX(Working_Data!$AD:$AD,MATCH(1,(Working_Data!$A:$A="Urban")*(Working_Data!$B:$B=$F13)*(Working_Data!$C:$C="March"),0))} -> 134 | J13: =(G13-G12)/G12 -> 0.042780749 | K13: =(H13-H12)/H12 -> 0.044427711 | L13: =(I13-I12)/I12 -> 0.041181041
F14: 2019 | G14: {=INDEX(Working_Data!$AD:$AD,MATCH(1,(Working_Data!$A:$A="Rural+Urban")*(Working_Data!$B:$B=$F14)*(Working_Data!$C:$C="March"),0))} -> 140.4 | H14: {=INDEX(Working_Data!$AD:$AD,MATCH(1,(Working_Data!$A:$A="Rural")*(Working_Data!$B:$B=$F14)*(Working_Data!$C:$C="March"),0))} -> 141.2 | I14: {=INDEX(Working_Data!$AD:$AD,MATCH(1,(Working_Data!$A:$A="Urban")*(Working_Data!$B:$B=$F14)*(Working_Data!$C:$C="March"),0))} -> 139.5 | J14: =(G14-G13)/G13 -> 0.028571429 | K14: =(H14-H13)/H13 -> 0.018024513 | L14: =(I14-I13)/I13 -> 0.041044776
F15: 2020 | G15: {=INDEX(Working_Data!$AD:$AD,MATCH(1,(Working_Data!$A:$A="Rural+Urban")*(Working_Data!$B:$B=$F15)*(Working_Data!$C:$C="March"),0))} -> 148.6 | H15: {=INDEX(Working_Data!$AD:$AD,MATCH(1,(Working_Data!$A:$A="Rural")*(Working_Data!$B:$B=$F15)*(Working_Data!$C:$C="March"),0))} -> 149.8 | I15: {=INDEX(Working_Data!$AD:$AD,MATCH(1,(Working_Data!$A:$A="Urban")*(Working_Data!$B:$B=$F15)*(Working_Data!$C:$C="March"),0))} -> 147.3 | J15: =(G15-G14)/G14 -> 0.058404558 | K15: =(H15-H14)/H14 -> 0.060906516 | L15: =(I15-I14)/I14 -> 0.055913978
F16: 2021 | G16: {=INDEX(Working_Data!$AD:$AD,MATCH(1,(Working_Data!$A:$A="Rural+Urban")*(Working_Data!$B:$B=$F16)*(Working_Data!$C:$C="March"),0))} -> 156.8 | H16: {=INDEX(Working_Data!$AD:$AD,MATCH(1,(Working_Data!$A:$A="Rural")*(Working_Data!$B:$B=$F16)*(Working_Data!$C:$C="March"),0))} -> 156.7 | I16: {=INDEX(Working_Data!$AD:$AD,MATCH(1,(Working_Data!$A:$A="Urban")*(Working_Data!$B:$B=$F16)*(Working_Data!$C:$C="March"),0))} -> 156.9 | J16: =(G16-G15)/G15 -> 0.055181696 | K16: =(H16-H15)/H15 -> 0.046061415 | L16: =(I16-I15)/I15 -> 0.065173116
F17: 2022 | G17: {=INDEX(Working_Data!$AD:$AD,MATCH(1,(Working_Data!$A:$A="Rural+Urban")*(Working_Data!$B:$B=$F17)*(Working_Data!$C:$C="March"),0))} -> 167.7 | H17: {=INDEX(Working_Data!$AD:$AD,MATCH(1,(Working_Data!$A:$A="Rural")*(Working_Data!$B:$B=$F17)*(Working_Data!$C:$C="March"),0))} -> 168.7 | I17: {=INDEX(Working_Data!$AD:$AD,MATCH(1,(Working_Data!$A:$A="Urban")*(Working_Data!$B:$B=$F17)*(Working_Data!$C:$C="March"),0))} -> 166.5 | J17: =(G17-G16)/G16 -> 0.069515306 | K17: =(H17-H16)/H16 -> 0.076579451 | L17: =(I17-I16)/I16 -> 0.061185468
F18: 2023 | G18: {=INDEX(Working_Data!$AD:$AD,MATCH(1,(Working_Data!$A:$A="Rural+Urban")*(Working_Data!$B:$B=$F18)*(Working_Data!$C:$C="March"),0))} -> 177.2 | H18: {=INDEX(Working_Data!$AD:$AD,MATCH(1,(Working_Data!$A:$A="Rural")*(Working_Data!$B:$B=$F18)*(Working_Data!$C:$C="March"),0))} -> 178 | I18: {=INDEX(Working_Data!$AD:$AD,MATCH(1,(Working_Data!$A:$A="Urban")*(Working_Data!$B:$B=$F18)*(Working_Data!$C:$C="March"),0))} -> 176.3 | J18: =(G18-G17)/G17 -> 0.056648778 | K18: =(H18-H17)/H17 -> 0.055127445 | L18: =(I18-I17)/I17 -> 0.058858859
F19: Reason for the Highest Inflation in 2022
F22: Insight: The highest Rural + Urban YoY inflation in the analysis was recorded in 2022 at 7.0%, based on March data. The increase was largely driven by supply-side shocks and higher global commodity prices following the Russia-Ukraine conflict. The RBI reported that food and beverages were the primary source of the inflation build-up in 2022-23, with higher global food prices, supply shortages and adverse weather conditions contributing significantly. Heat waves and uneven rainfall affected agricultural supply, while higher international energy prices increased fuel and transportation costs. This impact is also visible in the data: Rural YoY inflation increased from 4.6% in 2021 to 7.7% in 2022. The stronger rise in rural inflation is consistent with the significant role of food and agricultural supply shocks during this period.

Sheet 3.Food Inflation Analysis
E5: Monthly Food Bucket CPI and MoM Inflation (Jun-22 to May-23)
A6: Month | B6: Year | C6: Cereals and products | D6: Meat and fish | E6: Egg | F6: Milk and products | G6: Oils and fats | H6: Fruits | I6: Vegetables | J6: Pulses and products | K6: Sugar and Confectionery | L6: Spices | M6: Non-alcoholic beverages | N6: Food and beverages | O6: Food Bucket | P6: MoM Inflation
A7: June | B7: 2022 | C7: {=INDEX(Working_Data!$D:$AZ,MATCH(1,(Working_Data!$A:$A="Rural+Urban")*(Working_Data!$B:$B=$B7)*(Working_Data!$C:$C=$A7),0),MATCH(C$6,Working_Data!$D$1:$AZ$1,0))} -> 155 | D7: {=INDEX(Working_Data!$D:$AZ,MATCH(1,(Working_Data!$A:$A="Rural+Urban")*(Working_Data!$B:$B=$B7)*(Working_Data!$C:$C=$A7),0),MATCH(D$6,Working_Data!$D$1:$AZ$1,0))} -> 219.4 | E7: {=INDEX(Working_Data!$D:$AZ,MATCH(1,(Working_Data!$A:$A="Rural+Urban")*(Working_Data!$B:$B=$B7)*(Working_Data!$C:$C=$A7),0),MATCH(E$6,Working_Data!$D$1:$AZ$1,0))} -> 170.8 | F7: {=INDEX(Working_Data!$D:$AZ,MATCH(1,(Working_Data!$A:$A="Rural+Urban")*(Working_Data!$B:$B=$B7)*(Working_Data!$C:$C=$A7),0),MATCH(F$6,Working_Data!$D$1:$AZ$1,0))} -> 165.8 | G7: {=INDEX(Working_Data!$D:$AZ,MATCH(1,(Working_Data!$A:$A="Rural+Urban")*(Working_Data!$B:$B=$B7)*(Working_Data!$C:$C=$A7),0),MATCH(G$6,Working_Data!$D$1:$AZ$1,0))} -> 200.9 | H7: {=INDEX(Working_Data!$D:$AZ,MATCH(1,(Working_Data!$A:$A="Rural+Urban")*(Working_Data!$B:$B=$B7)*(Working_Data!$C:$C=$A7),0),MATCH(H$6,Working_Data!$D$1:$AZ$1,0))} -> 169.7 | I7: {=INDEX(Working_Data!$D:$AZ,MATCH(1,(Working_Data!$A:$A="Rural+Urban")*(Working_Data!$B:$B=$B7)*(Working_Data!$C:$C=$A7),0),MATCH(I$6,Working_Data!$D$1:$AZ$1,0))} -> 182.3 | J7: {=INDEX(Working_Data!$D:$AZ,MATCH(1,(Working_Data!$A:$A="Rural+Urban")*(Working_Data!$B:$B=$B7)*(Working_Data!$C:$C=$A7),0),MATCH(J$6,Working_Data!$D$1:$AZ$1,0))} -> 164.3 | ... N7: {=INDEX(Working_Data!$D:$AZ,MATCH(1,(Working_Data!$A:$A="Rural+Urban")*(Working_Data!$B:$B=$B7)*(Working_Data!$C:$C=$A7),0),MATCH(N$6,Working_Data!$D$1:$AZ$1,0))} -> 174.9 | O7: =SUM(C7:N7) -> 2078 | P7: -
A8: July | B8: 2022 | C8: {=INDEX(Working_Data!$D:$AZ,MATCH(1,(Working_Data!$A:$A="Rural+Urban")*(Working_Data!$B:$B=$B8)*(Working_Data!$C:$C=$A8),0),MATCH(C$6,Working_Data!$D$1:$AZ$1,0))} -> 156.5 | D8: {=INDEX(Working_Data!$D:$AZ,MATCH(1,(Working_Data!$A:$A="Rural+Urban")*(Working_Data!$B:$B=$B8)*(Working_Data!$C:$C=$A8),0),MATCH(D$6,Working_Data!$D$1:$AZ$1,0))} -> 213 | E8: {=INDEX(Working_Data!$D:$AZ,MATCH(1,(Working_Data!$A:$A="Rural+Urban")*(Working_Data!$B:$B=$B8)*(Working_Data!$C:$C=$A8),0),MATCH(E$6,Working_Data!$D$1:$AZ$1,0))} -> 175.2 | F8: {=INDEX(Working_Data!$D:$AZ,MATCH(1,(Working_Data!$A:$A="Rural+Urban")*(Working_Data!$B:$B=$B8)*(Working_Data!$C:$C=$A8),0),MATCH(F$6,Working_Data!$D$1:$AZ$1,0))} -> 166.6 | G8: {=INDEX(Working_Data!$D:$AZ,MATCH(1,(Working_Data!$A:$A="Rural+Urban")*(Working_Data!$B:$B=$B8)*(Working_Data!$C:$C=$A8),0),MATCH(G$6,Working_Data!$D$1:$AZ$1,0))} -> 195.8 | H8: {=INDEX(Working_Data!$D:$AZ,MATCH(1,(Working_Data!$A:$A="Rural+Urban")*(Working_Data!$B:$B=$B8)*(Working_Data!$C:$C=$A8),0),MATCH(H$6,Working_Data!$D$1:$AZ$1,0))} -> 174.2 | I8: {=INDEX(Working_Data!$D:$AZ,MATCH(1,(Working_Data!$A:$A="Rural+Urban")*(Working_Data!$B:$B=$B8)*(Working_Data!$C:$C=$A8),0),MATCH(I$6,Working_Data!$D$1:$AZ$1,0))} -> 182.1 | J8: {=INDEX(Working_Data!$D:$AZ,MATCH(1,(Working_Data!$A:$A="Rural+Urban")*(Working_Data!$B:$B=$B8)*(Working_Data!$C:$C=$A8),0),MATCH(J$6,Working_Data!$D$1:$AZ$1,0))} -> 164.3 | ... N8: {=INDEX(Working_Data!$D:$AZ,MATCH(1,(Working_Data!$A:$A="Rural+Urban")*(Working_Data!$B:$B=$B8)*(Working_Data!$C:$C=$A8),0),MATCH(N$6,Working_Data!$D$1:$AZ$1,0))} -> 175 | O8: =SUM(C8:N8) -> 2081.1 | P8: =(O8-O7)/O7 -> 0.0014918191
A9: August | B9: 2022 | C9: {=INDEX(Working_Data!$D:$AZ,MATCH(1,(Working_Data!$A:$A="Rural+Urban")*(Working_Data!$B:$B=$B9)*(Working_Data!$C:$C=$A9),0),MATCH(C$6,Working_Data!$D$1:$AZ$1,0))} -> 160.3 | D9: {=INDEX(Working_Data!$D:$AZ,MATCH(1,(Working_Data!$A:$A="Rural+Urban")*(Working_Data!$B:$B=$B9)*(Working_Data!$C:$C=$A9),0),MATCH(D$6,Working_Data!$D$1:$AZ$1,0))} -> 206.5 | E9: {=INDEX(Working_Data!$D:$AZ,MATCH(1,(Working_Data!$A:$A="Rural+Urban")*(Working_Data!$B:$B=$B9)*(Working_Data!$C:$C=$A9),0),MATCH(E$6,Working_Data!$D$1:$AZ$1,0))} -> 169.2 | F9: {=INDEX(Working_Data!$D:$AZ,MATCH(1,(Working_Data!$A:$A="Rural+Urban")*(Working_Data!$B:$B=$B9)*(Working_Data!$C:$C=$A9),0),MATCH(F$6,Working_Data!$D$1:$AZ$1,0))} -> 168.1 | G9: {=INDEX(Working_Data!$D:$AZ,MATCH(1,(Working_Data!$A:$A="Rural+Urban")*(Working_Data!$B:$B=$B9)*(Working_Data!$C:$C=$A9),0),MATCH(G$6,Working_Data!$D$1:$AZ$1,0))} -> 192.4 | H9: {=INDEX(Working_Data!$D:$AZ,MATCH(1,(Working_Data!$A:$A="Rural+Urban")*(Working_Data!$B:$B=$B9)*(Working_Data!$C:$C=$A9),0),MATCH(H$6,Working_Data!$D$1:$AZ$1,0))} -> 172.9 | I9: {=INDEX(Working_Data!$D:$AZ,MATCH(1,(Working_Data!$A:$A="Rural+Urban")*(Working_Data!$B:$B=$B9)*(Working_Data!$C:$C=$A9),0),MATCH(I$6,Working_Data!$D$1:$AZ$1,0))} -> 186.7 | J9: {=INDEX(Working_Data!$D:$AZ,MATCH(1,(Working_Data!$A:$A="Rural+Urban")*(Working_Data!$B:$B=$B9)*(Working_Data!$C:$C=$A9),0),MATCH(J$6,Working_Data!$D$1:$AZ$1,0))} -> 167.2 | ... N9: {=INDEX(Working_Data!$D:$AZ,MATCH(1,(Working_Data!$A:$A="Rural+Urban")*(Working_Data!$B:$B=$B9)*(Working_Data!$C:$C=$A9),0),MATCH(N$6,Working_Data!$D$1:$AZ$1,0))} -> 176.3 | O9: =SUM(C9:N9) -> 2082.9 | P9: =(O9-O8)/O8 -> 0.0008649272
A10: September | B10: 2022 | C10: {=INDEX(Working_Data!$D:$AZ,MATCH(1,(Working_Data!$A:$A="Rural+Urban")*(Working_Data!$B:$B=$B10)*(Working_Data!$C:$C=$A10),0),MATCH(C$6,Working_Data!$D$1:$AZ$1,0))} -> 163.5 | D10: {=INDEX(Working_Data!$D:$AZ,MATCH(1,(Working_Data!$A:$A="Rural+Urban")*(Working_Data!$B:$B=$B10)*(Working_Data!$C:$C=$A10),0),MATCH(D$6,Working_Data!$D$1:$AZ$1,0))} -> 209.2 | E10: {=INDEX(Working_Data!$D:$AZ,MATCH(1,(Working_Data!$A:$A="Rural+Urban")*(Working_Data!$B:$B=$B10)*(Working_Data!$C:$C=$A10),0),MATCH(E$6,Working_Data!$D$1:$AZ$1,0))} -> 169.7 | F10: {=INDEX(Working_Data!$D:$AZ,MATCH(1,(Working_Data!$A:$A="Rural+Urban")*(Working_Data!$B:$B=$B10)*(Working_Data!$C:$C=$A10),0),MATCH(F$6,Working_Data!$D$1:$AZ$1,0))} -> 169.7 | G10: {=INDEX(Working_Data!$D:$AZ,MATCH(1,(Working_Data!$A:$A="Rural+Urban")*(Working_Data!$B:$B=$B10)*(Working_Data!$C:$C=$A10),0),MATCH(G$6,Working_Data!$D$1:$AZ$1,0))} -> 188.7 | H10: {=INDEX(Working_Data!$D:$AZ,MATCH(1,(Working_Data!$A:$A="Rural+Urban")*(Working_Data!$B:$B=$B10)*(Working_Data!$C:$C=$A10),0),MATCH(H$6,Working_Data!$D$1:$AZ$1,0))} -> 165.7 | I10: {=INDEX(Working_Data!$D:$AZ,MATCH(1,(Working_Data!$A:$A="Rural+Urban")*(Working_Data!$B:$B=$B10)*(Working_Data!$C:$C=$A10),0),MATCH(I$6,Working_Data!$D$1:$AZ$1,0))} -> 191.8 | J10: {=INDEX(Working_Data!$D:$AZ,MATCH(1,(Working_Data!$A:$A="Rural+Urban")*(Working_Data!$B:$B=$B10)*(Working_Data!$C:$C=$A10),0),MATCH(J$6,Working_Data!$D$1:$AZ$1,0))} -> 169.1 | ... N10: {=INDEX(Working_Data!$D:$AZ,MATCH(1,(Working_Data!$A:$A="Rural+Urban")*(Working_Data!$B:$B=$B10)*(Working_Data!$C:$C=$A10),0),MATCH(N$6,Working_Data!$D$1:$AZ$1,0))} -> 177.8 | O10: =SUM(C10:N10) -> 2093.5 | P10: =(O10-O9)/O9 -> 0.0050890585
A11: October | B11: 2022 | C11: {=INDEX(Working_Data!$D:$AZ,MATCH(1,(Working_Data!$A:$A="Rural+Urban")*(Working_Data!$B:$B=$B11)*(Working_Data!$C:$C=$A11),0),MATCH(C$6,Working_Data!$D$1:$AZ$1,0))} -> 165.2 | D11: {=INDEX(Working_Data!$D:$AZ,MATCH(1,(Working_Data!$A:$A="Rural+Urban")*(Working_Data!$B:$B=$B11)*(Working_Data!$C:$C=$A11),0),MATCH(D$6,Working_Data!$D$1:$AZ$1,0))} -> 210.9 | E11: {=INDEX(Working_Data!$D:$AZ,MATCH(1,(Working_Data!$A:$A="Rural+Urban")*(Working_Data!$B:$B=$B11)*(Working_Data!$C:$C=$A11),0),MATCH(E$6,Working_Data!$D$1:$AZ$1,0))} -> 170.9 | F11: {=INDEX(Working_Data!$D:$AZ,MATCH(1,(Working_Data!$A:$A="Rural+Urban")*(Working_Data!$B:$B=$B11)*(Working_Data!$C:$C=$A11),0),MATCH(F$6,Working_Data!$D$1:$AZ$1,0))} -> 170.9 | G11: {=INDEX(Working_Data!$D:$AZ,MATCH(1,(Working_Data!$A:$A="Rural+Urban")*(Working_Data!$B:$B=$B11)*(Working_Data!$C:$C=$A11),0),MATCH(G$6,Working_Data!$D$1:$AZ$1,0))} -> 186.5 | H11: {=INDEX(Working_Data!$D:$AZ,MATCH(1,(Working_Data!$A:$A="Rural+Urban")*(Working_Data!$B:$B=$B11)*(Working_Data!$C:$C=$A11),0),MATCH(H$6,Working_Data!$D$1:$AZ$1,0))} -> 163.8 | I11: {=INDEX(Working_Data!$D:$AZ,MATCH(1,(Working_Data!$A:$A="Rural+Urban")*(Working_Data!$B:$B=$B11)*(Working_Data!$C:$C=$A11),0),MATCH(I$6,Working_Data!$D$1:$AZ$1,0))} -> 199.7 | J11: {=INDEX(Working_Data!$D:$AZ,MATCH(1,(Working_Data!$A:$A="Rural+Urban")*(Working_Data!$B:$B=$B11)*(Working_Data!$C:$C=$A11),0),MATCH(J$6,Working_Data!$D$1:$AZ$1,0))} -> 169.8 | ... N11: {=INDEX(Working_Data!$D:$AZ,MATCH(1,(Working_Data!$A:$A="Rural+Urban")*(Working_Data!$B:$B=$B11)*(Working_Data!$C:$C=$A11),0),MATCH(N$6,Working_Data!$D$1:$AZ$1,0))} -> 179.6 | O11: =SUM(C11:N11) -> 2109 | P11: =(O11-O10)/O10 -> 0.0074038691
A12: November | B12: 2022 | C12: {=INDEX(Working_Data!$D:$AZ,MATCH(1,(Working_Data!$A:$A="Rural+Urban")*(Working_Data!$B:$B=$B12)*(Working_Data!$C:$C=$A12),0),MATCH(C$6,Working_Data!$D$1:$AZ$1,0))} -> 167.4 | D12: {=INDEX(Working_Data!$D:$AZ,MATCH(1,(Working_Data!$A:$A="Rural+Urban")*(Working_Data!$B:$B=$B12)*(Working_Data!$C:$C=$A12),0),MATCH(D$6,Working_Data!$D$1:$AZ$1,0))} -> 209.4 | E12: {=INDEX(Working_Data!$D:$AZ,MATCH(1,(Working_Data!$A:$A="Rural+Urban")*(Working_Data!$B:$B=$B12)*(Working_Data!$C:$C=$A12),0),MATCH(E$6,Working_Data!$D$1:$AZ$1,0))} -> 181.4 | F12: {=INDEX(Working_Data!$D:$AZ,MATCH(1,(Working_Data!$A:$A="Rural+Urban")*(Working_Data!$B:$B=$B12)*(Working_Data!$C:$C=$A12),0),MATCH(F$6,Working_Data!$D$1:$AZ$1,0))} -> 172.3 | G12: {=INDEX(Working_Data!$D:$AZ,MATCH(1,(Working_Data!$A:$A="Rural+Urban")*(Working_Data!$B:$B=$B12)*(Working_Data!$C:$C=$A12),0),MATCH(G$6,Working_Data!$D$1:$AZ$1,0))} -> 188.9 | H12: {=INDEX(Working_Data!$D:$AZ,MATCH(1,(Working_Data!$A:$A="Rural+Urban")*(Working_Data!$B:$B=$B12)*(Working_Data!$C:$C=$A12),0),MATCH(H$6,Working_Data!$D$1:$AZ$1,0))} -> 160.7 | I12: {=INDEX(Working_Data!$D:$AZ,MATCH(1,(Working_Data!$A:$A="Rural+Urban")*(Working_Data!$B:$B=$B12)*(Working_Data!$C:$C=$A12),0),MATCH(I$6,Working_Data!$D$1:$AZ$1,0))} -> 183.1 | J12: {=INDEX(Working_Data!$D:$AZ,MATCH(1,(Working_Data!$A:$A="Rural+Urban")*(Working_Data!$B:$B=$B12)*(Working_Data!$C:$C=$A12),0),MATCH(J$6,Working_Data!$D$1:$AZ$1,0))} -> 170.5 | ... N12: {=INDEX(Working_Data!$D:$AZ,MATCH(1,(Working_Data!$A:$A="Rural+Urban")*(Working_Data!$B:$B=$B12)*(Working_Data!$C:$C=$A12),0),MATCH(N$6,Working_Data!$D$1:$AZ$1,0))} -> 178.3 | O12: =SUM(C12:N12) -> 2107.3 | P12: =(O12-O11)/O11 -> -0.00080606923
A13: December | B13: 2022 | C13: {=INDEX(Working_Data!$D:$AZ,MATCH(1,(Working_Data!$A:$A="Rural+Urban")*(Working_Data!$B:$B=$B13)*(Working_Data!$C:$C=$A13),0),MATCH(C$6,Working_Data!$D$1:$AZ$1,0))} -> 169.2 | D13: {=INDEX(Working_Data!$D:$AZ,MATCH(1,(Working_Data!$A:$A="Rural+Urban")*(Working_Data!$B:$B=$B13)*(Working_Data!$C:$C=$A13),0),MATCH(D$6,Working_Data!$D$1:$AZ$1,0))} -> 209 | E13: {=INDEX(Working_Data!$D:$AZ,MATCH(1,(Working_Data!$A:$A="Rural+Urban")*(Working_Data!$B:$B=$B13)*(Working_Data!$C:$C=$A13),0),MATCH(E$6,Working_Data!$D$1:$AZ$1,0))} -> 190.2 | F13: {=INDEX(Working_Data!$D:$AZ,MATCH(1,(Working_Data!$A:$A="Rural+Urban")*(Working_Data!$B:$B=$B13)*(Working_Data!$C:$C=$A13),0),MATCH(F$6,Working_Data!$D$1:$AZ$1,0))} -> 173.6 | G13: {=INDEX(Working_Data!$D:$AZ,MATCH(1,(Working_Data!$A:$A="Rural+Urban")*(Working_Data!$B:$B=$B13)*(Working_Data!$C:$C=$A13),0),MATCH(G$6,Working_Data!$D$1:$AZ$1,0))} -> 188.5 | H13: {=INDEX(Working_Data!$D:$AZ,MATCH(1,(Working_Data!$A:$A="Rural+Urban")*(Working_Data!$B:$B=$B13)*(Working_Data!$C:$C=$A13),0),MATCH(H$6,Working_Data!$D$1:$AZ$1,0))} -> 158 | I13: {=INDEX(Working_Data!$D:$AZ,MATCH(1,(Working_Data!$A:$A="Rural+Urban")*(Working_Data!$B:$B=$B13)*(Working_Data!$C:$C=$A13),0),MATCH(I$6,Working_Data!$D$1:$AZ$1,0))} -> 159.9 | J13: {=INDEX(Working_Data!$D:$AZ,MATCH(1,(Working_Data!$A:$A="Rural+Urban")*(Working_Data!$B:$B=$B13)*(Working_Data!$C:$C=$A13),0),MATCH(J$6,Working_Data!$D$1:$AZ$1,0))} -> 170.8 | ... N13: {=INDEX(Working_Data!$D:$AZ,MATCH(1,(Working_Data!$A:$A="Rural+Urban")*(Working_Data!$B:$B=$B13)*(Working_Data!$C:$C=$A13),0),MATCH(N$6,Working_Data!$D$1:$AZ$1,0))} -> 175.9 | O13: =SUM(C13:N13) -> 2093.1 | P13: =(O13-O12)/O12 -> -0.0067384805
A14: January | B14: 2023 | C14: {=INDEX(Working_Data!$D:$AZ,MATCH(1,(Working_Data!$A:$A="Rural+Urban")*(Working_Data!$B:$B=$B14)*(Working_Data!$C:$C=$A14),0),MATCH(C$6,Working_Data!$D$1:$AZ$1,0))} -> 173.8 | D14: {=INDEX(Working_Data!$D:$AZ,MATCH(1,(Working_Data!$A:$A="Rural+Urban")*(Working_Data!$B:$B=$B14)*(Working_Data!$C:$C=$A14),0),MATCH(D$6,Working_Data!$D$1:$AZ$1,0))} -> 210.7 | E14: {=INDEX(Working_Data!$D:$AZ,MATCH(1,(Working_Data!$A:$A="Rural+Urban")*(Working_Data!$B:$B=$B14)*(Working_Data!$C:$C=$A14),0),MATCH(E$6,Working_Data!$D$1:$AZ$1,0))} -> 194.5 | F14: {=INDEX(Working_Data!$D:$AZ,MATCH(1,(Working_Data!$A:$A="Rural+Urban")*(Working_Data!$B:$B=$B14)*(Working_Data!$C:$C=$A14),0),MATCH(F$6,Working_Data!$D$1:$AZ$1,0))} -> 174.6 | G14: {=INDEX(Working_Data!$D:$AZ,MATCH(1,(Working_Data!$A:$A="Rural+Urban")*(Working_Data!$B:$B=$B14)*(Working_Data!$C:$C=$A14),0),MATCH(G$6,Working_Data!$D$1:$AZ$1,0))} -> 187.2 | H14: {=INDEX(Working_Data!$D:$AZ,MATCH(1,(Working_Data!$A:$A="Rural+Urban")*(Working_Data!$B:$B=$B14)*(Working_Data!$C:$C=$A14),0),MATCH(H$6,Working_Data!$D$1:$AZ$1,0))} -> 158.3 | I14: {=INDEX(Working_Data!$D:$AZ,MATCH(1,(Working_Data!$A:$A="Rural+Urban")*(Working_Data!$B:$B=$B14)*(Working_Data!$C:$C=$A14),0),MATCH(I$6,Working_Data!$D$1:$AZ$1,0))} -> 153.9 | J14: {=INDEX(Working_Data!$D:$AZ,MATCH(1,(Working_Data!$A:$A="Rural+Urban")*(Working_Data!$B:$B=$B14)*(Working_Data!$C:$C=$A14),0),MATCH(J$6,Working_Data!$D$1:$AZ$1,0))} -> 170.9 | ... N14: {=INDEX(Working_Data!$D:$AZ,MATCH(1,(Working_Data!$A:$A="Rural+Urban")*(Working_Data!$B:$B=$B14)*(Working_Data!$C:$C=$A14),0),MATCH(N$6,Working_Data!$D$1:$AZ$1,0))} -> 176.7 | O14: =SUM(C14:N14) -> 2101.5 | P14: =(O14-O13)/O13 -> 0.0040131862
A15: February | B15: 2023 | C15: {=INDEX(Working_Data!$D:$AZ,MATCH(1,(Working_Data!$A:$A="Rural+Urban")*(Working_Data!$B:$B=$B15)*(Working_Data!$C:$C=$A15),0),MATCH(C$6,Working_Data!$D$1:$AZ$1,0))} -> 174.4 | D15: {=INDEX(Working_Data!$D:$AZ,MATCH(1,(Working_Data!$A:$A="Rural+Urban")*(Working_Data!$B:$B=$B15)*(Working_Data!$C:$C=$A15),0),MATCH(D$6,Working_Data!$D$1:$AZ$1,0))} -> 207.7 | E15: {=INDEX(Working_Data!$D:$AZ,MATCH(1,(Working_Data!$A:$A="Rural+Urban")*(Working_Data!$B:$B=$B15)*(Working_Data!$C:$C=$A15),0),MATCH(E$6,Working_Data!$D$1:$AZ$1,0))} -> 175.2 | F15: {=INDEX(Working_Data!$D:$AZ,MATCH(1,(Working_Data!$A:$A="Rural+Urban")*(Working_Data!$B:$B=$B15)*(Working_Data!$C:$C=$A15),0),MATCH(F$6,Working_Data!$D$1:$AZ$1,0))} -> 177.3 | G15: {=INDEX(Working_Data!$D:$AZ,MATCH(1,(Working_Data!$A:$A="Rural+Urban")*(Working_Data!$B:$B=$B15)*(Working_Data!$C:$C=$A15),0),MATCH(G$6,Working_Data!$D$1:$AZ$1,0))} -> 179.3 | H15: {=INDEX(Working_Data!$D:$AZ,MATCH(1,(Working_Data!$A:$A="Rural+Urban")*(Working_Data!$B:$B=$B15)*(Working_Data!$C:$C=$A15),0),MATCH(H$6,Working_Data!$D$1:$AZ$1,0))} -> 169.5 | I15: {=INDEX(Working_Data!$D:$AZ,MATCH(1,(Working_Data!$A:$A="Rural+Urban")*(Working_Data!$B:$B=$B15)*(Working_Data!$C:$C=$A15),0),MATCH(I$6,Working_Data!$D$1:$AZ$1,0))} -> 152.7 | J15: {=INDEX(Working_Data!$D:$AZ,MATCH(1,(Working_Data!$A:$A="Rural+Urban")*(Working_Data!$B:$B=$B15)*(Working_Data!$C:$C=$A15),0),MATCH(J$6,Working_Data!$D$1:$AZ$1,0))} -> 171 | ... N15: {=INDEX(Working_Data!$D:$AZ,MATCH(1,(Working_Data!$A:$A="Rural+Urban")*(Working_Data!$B:$B=$B15)*(Working_Data!$C:$C=$A15),0),MATCH(N$6,Working_Data!$D$1:$AZ$1,0))} -> 177 | O15: =SUM(C15:N15) -> 2086.1 | P15: =(O15-O14)/O14 -> -0.007328099
A16: March | B16: 2023 | C16: {=INDEX(Working_Data!$D:$AZ,MATCH(1,(Working_Data!$A:$A="Rural+Urban")*(Working_Data!$B:$B=$B16)*(Working_Data!$C:$C=$A16),0),MATCH(C$6,Working_Data!$D$1:$AZ$1,0))} -> 174.4 | D16: {=INDEX(Working_Data!$D:$AZ,MATCH(1,(Working_Data!$A:$A="Rural+Urban")*(Working_Data!$B:$B=$B16)*(Working_Data!$C:$C=$A16),0),MATCH(D$6,Working_Data!$D$1:$AZ$1,0))} -> 207.7 | E16: {=INDEX(Working_Data!$D:$AZ,MATCH(1,(Working_Data!$A:$A="Rural+Urban")*(Working_Data!$B:$B=$B16)*(Working_Data!$C:$C=$A16),0),MATCH(E$6,Working_Data!$D$1:$AZ$1,0))} -> 175.2 | F16: {=INDEX(Working_Data!$D:$AZ,MATCH(1,(Working_Data!$A:$A="Rural+Urban")*(Working_Data!$B:$B=$B16)*(Working_Data!$C:$C=$A16),0),MATCH(F$6,Working_Data!$D$1:$AZ$1,0))} -> 177.3 | G16: {=INDEX(Working_Data!$D:$AZ,MATCH(1,(Working_Data!$A:$A="Rural+Urban")*(Working_Data!$B:$B=$B16)*(Working_Data!$C:$C=$A16),0),MATCH(G$6,Working_Data!$D$1:$AZ$1,0))} -> 179.2 | H16: {=INDEX(Working_Data!$D:$AZ,MATCH(1,(Working_Data!$A:$A="Rural+Urban")*(Working_Data!$B:$B=$B16)*(Working_Data!$C:$C=$A16),0),MATCH(H$6,Working_Data!$D$1:$AZ$1,0))} -> 169.5 | I16: {=INDEX(Working_Data!$D:$AZ,MATCH(1,(Working_Data!$A:$A="Rural+Urban")*(Working_Data!$B:$B=$B16)*(Working_Data!$C:$C=$A16),0),MATCH(I$6,Working_Data!$D$1:$AZ$1,0))} -> 152.8 | J16: {=INDEX(Working_Data!$D:$AZ,MATCH(1,(Working_Data!$A:$A="Rural+Urban")*(Working_Data!$B:$B=$B16)*(Working_Data!$C:$C=$A16),0),MATCH(J$6,Working_Data!$D$1:$AZ$1,0))} -> 171.1 | ... N16: {=INDEX(Working_Data!$D:$AZ,MATCH(1,(Working_Data!$A:$A="Rural+Urban")*(Working_Data!$B:$B=$B16)*(Working_Data!$C:$C=$A16),0),MATCH(N$6,Working_Data!$D$1:$AZ$1,0))} -> 177 | O16: =SUM(C16:N16) -> 2086.2 | P16: =(O16-O15)/O15 -> 4.7936341e-05
A17: April | B17: 2023 | C17: {=INDEX(Working_Data!$D:$AZ,MATCH(1,(Working_Data!$A:$A="Rural+Urban")*(Working_Data!$B:$B=$B17)*(Working_Data!$C:$C=$A17),0),MATCH(C$6,Working_Data!$D$1:$AZ$1,0))} -> 173.8 | D17: {=INDEX(Working_Data!$D:$AZ,MATCH(1,(Working_Data!$A:$A="Rural+Urban")*(Working_Data!$B:$B=$B17)*(Working_Data!$C:$C=$A17),0),MATCH(D$6,Working_Data!$D$1:$AZ$1,0))} -> 209.3 | E17: {=INDEX(Working_Data!$D:$AZ,MATCH(1,(Working_Data!$A:$A="Rural+Urban")*(Working_Data!$B:$B=$B17)*(Working_Data!$C:$C=$A17),0),MATCH(E$6,Working_Data!$D$1:$AZ$1,0))} -> 169.6 | F17: {=INDEX(Working_Data!$D:$AZ,MATCH(1,(Working_Data!$A:$A="Rural+Urban")*(Working_Data!$B:$B=$B17)*(Working_Data!$C:$C=$A17),0),MATCH(F$6,Working_Data!$D$1:$AZ$1,0))} -> 178.4 | G17: {=INDEX(Working_Data!$D:$AZ,MATCH(1,(Working_Data!$A:$A="Rural+Urban")*(Working_Data!$B:$B=$B17)*(Working_Data!$C:$C=$A17),0),MATCH(G$6,Working_Data!$D$1:$AZ$1,0))} -> 174.9 | H17: {=INDEX(Working_Data!$D:$AZ,MATCH(1,(Working_Data!$A:$A="Rural+Urban")*(Working_Data!$B:$B=$B17)*(Working_Data!$C:$C=$A17),0),MATCH(H$6,Working_Data!$D$1:$AZ$1,0))} -> 176.3 | I17: {=INDEX(Working_Data!$D:$AZ,MATCH(1,(Working_Data!$A:$A="Rural+Urban")*(Working_Data!$B:$B=$B17)*(Working_Data!$C:$C=$A17),0),MATCH(I$6,Working_Data!$D$1:$AZ$1,0))} -> 155.4 | J17: {=INDEX(Working_Data!$D:$AZ,MATCH(1,(Working_Data!$A:$A="Rural+Urban")*(Working_Data!$B:$B=$B17)*(Working_Data!$C:$C=$A17),0),MATCH(J$6,Working_Data!$D$1:$AZ$1,0))} -> 173.4 | ... N17: {=INDEX(Working_Data!$D:$AZ,MATCH(1,(Working_Data!$A:$A="Rural+Urban")*(Working_Data!$B:$B=$B17)*(Working_Data!$C:$C=$A17),0),MATCH(N$6,Working_Data!$D$1:$AZ$1,0))} -> 177.9 | O17: =SUM(C17:N17) -> 2096.1 | P17: =(O17-O16)/O16 -> 0.0047454702
A18: May | B18: 2023 | C18: {=INDEX(Working_Data!$D:$AZ,MATCH(1,(Working_Data!$A:$A="Rural+Urban")*(Working_Data!$B:$B=$B18)*(Working_Data!$C:$C=$A18),0),MATCH(C$6,Working_Data!$D$1:$AZ$1,0))} -> 173.7 | D18: {=INDEX(Working_Data!$D:$AZ,MATCH(1,(Working_Data!$A:$A="Rural+Urban")*(Working_Data!$B:$B=$B18)*(Working_Data!$C:$C=$A18),0),MATCH(D$6,Working_Data!$D$1:$AZ$1,0))} -> 214.3 | E18: {=INDEX(Working_Data!$D:$AZ,MATCH(1,(Working_Data!$A:$A="Rural+Urban")*(Working_Data!$B:$B=$B18)*(Working_Data!$C:$C=$A18),0),MATCH(E$6,Working_Data!$D$1:$AZ$1,0))} -> 173.2 | F18: {=INDEX(Working_Data!$D:$AZ,MATCH(1,(Working_Data!$A:$A="Rural+Urban")*(Working_Data!$B:$B=$B18)*(Working_Data!$C:$C=$A18),0),MATCH(F$6,Working_Data!$D$1:$AZ$1,0))} -> 179.5 | G18: {=INDEX(Working_Data!$D:$AZ,MATCH(1,(Working_Data!$A:$A="Rural+Urban")*(Working_Data!$B:$B=$B18)*(Working_Data!$C:$C=$A18),0),MATCH(G$6,Working_Data!$D$1:$AZ$1,0))} -> 170 | H18: {=INDEX(Working_Data!$D:$AZ,MATCH(1,(Working_Data!$A:$A="Rural+Urban")*(Working_Data!$B:$B=$B18)*(Working_Data!$C:$C=$A18),0),MATCH(H$6,Working_Data!$D$1:$AZ$1,0))} -> 172.2 | I18: {=INDEX(Working_Data!$D:$AZ,MATCH(1,(Working_Data!$A:$A="Rural+Urban")*(Working_Data!$B:$B=$B18)*(Working_Data!$C:$C=$A18),0),MATCH(I$6,Working_Data!$D$1:$AZ$1,0))} -> 161 | J18: {=INDEX(Working_Data!$D:$AZ,MATCH(1,(Working_Data!$A:$A="Rural+Urban")*(Working_Data!$B:$B=$B18)*(Working_Data!$C:$C=$A18),0),MATCH(J$6,Working_Data!$D$1:$AZ$1,0))} -> 175.6 | ... N18: {=INDEX(Working_Data!$D:$AZ,MATCH(1,(Working_Data!$A:$A="Rural+Urban")*(Working_Data!$B:$B=$B18)*(Working_Data!$C:$C=$A18),0),MATCH(N$6,Working_Data!$D$1:$AZ$1,0))} -> 179.1 | O18: =SUM(C18:N18) -> 2112.7 | P18: =(O18-O17)/O17 -> 0.0079194695
P21: Insight: The broader food bucket showed fluctuations during the 12 months ending May 2023. Month-on-month food inflation was highest in May 2023 at 0.79%, while the lowest was recorded in February 2023 at -0.73%. The negative value indicates a month-on-month decline in the overall food bucket index during February 2023.
F37: YoY Inflation by Food Category (Jun-22 to May-23)
F38: Food Category | G38: 44713 | H38: 45047 | I38: Absolute Change
F39: Cereals and products | G39: {=TRANSPOSE(C7:N7)} -> 155 | H39: {=TRANSPOSE(C18:N18)} -> 173.7 | I39: =(H39-G39)/G39 -> 0.12064516
F40: Meat and fish | G40: 219.4 | H40: 214.3 | I40: =(H40-G40)/G40 -> -0.023245214
F41: Egg | G41: 170.8 | H41: 173.2 | I41: =(H41-G41)/G41 -> 0.014051522
F42: Milk and products | G42: 165.8 | H42: 179.5 | I42: =(H42-G42)/G42 -> 0.082629674
F43: Oils and fats | G43: 200.9 | H43: 170 | I43: =(H43-G43)/G43 -> -0.15380786
F44: Fruits | G44: 169.7 | H44: 172.2 | I44: =(H44-G44)/G44 -> 0.01473188
F45: Vegetables | G45: 182.3 | H45: 161 | I45: =(H45-G45)/G45 -> -0.11684037
F46: Pulses and products | G46: 164.3 | H46: 175.6 | I46: =(H46-G46)/G46 -> 0.068776628
F47: Sugar and Confectionery | G47: 119.9 | H47: 122.7 | I47: =(H47-G47)/G47 -> 0.023352794
F48: Spices | G48: 187.1 | H48: 218 | I48: =(H48-G48)/G48 -> 0.16515232
F49: Non-alcoholic beverages | G49: 167.9 | H49: 173.4 | I49: =(H49-G49)/G49 -> 0.032757594
F50: Food and beverages | G50: 174.9 | H50: 179.1 | I50: =(H50-G50)/G50 -> 0.024013722 | K50: Insight: Comparing June 2022 with May 2023, Spices recorded the highest positive inflation at 16.5%, followed by Cereals and products at 12.1% and Milk and products at 8.3%. In contrast, Oils and fats declined by 15.4% and Vegetables declined by 11.7% over the same period. Spices were therefore the largest positive individual food-category contributor in this analysis.

Sheet 4.COVID Inflation Analysis
A2: Category Mapping | D2: Monthly CPI Inflation Analysis (Food, Essential Services & Health) | Q2: Pre- vs Post-COVID CPI Inflation Comparison
A3: Original CPI category | B3: New Category | D3: Period | E3: Month | F3: Year | G3: Food | H3: Essential Services | I3: Health | J3: Food MoM % | K3: Essential Services MoM % | L3: Health MoM % | M3: Food YoY % | N3: Essential Services YoY % | O3: Health YoY % | Q3: Category | R3: Pre-COVID Avg YoY | S3: Post-COVID Avg YoY | T3: Change
A4: Cereals and products | B4: Food | D4: Feb'18 | E4: February | F4: 2018 | G4: {=SUM(INDEX(Working_Data!$D:$P,MATCH(1,(Working_Data!$A:$A="Rural+Urban")*(Working_Data!$B:$B=$F4)*(Working_Data!$C:$C=$E4),0),0))} -> 1760.4 | H4: {=SUM(INDEX(Working_Data!$R:$AA,MATCH(1,(Working_Data!$A:$A="Rural+Urban")*(Working_Data!$B:$B=$F4)*(Working_Data!$C:$C=$E4),0),{1,2,3,4,5,6,8,10}))} -> 1094.4 | I4: {=INDEX(Working_Data!$X:$X,MATCH(1,(Working_Data!$A:$A="Rural+Urban")*(Working_Data!$B:$B=$F4)*(Working_Data!$C:$C=$E4),0))} -> 133.8 | J4: - | K4: - | L4: - | M4: - | N4: - | O4: - | Q4: Food | R4: =AVERAGE(M17:M28) -> 0.04856139 | S4: =AVERAGE(M29:M40) -> 0.081946472 | T4: =S4-R4 -> 0.033385081
A5: Meat and fish | B5: Food | D5: Mar'18 | E5: March | F5: 2018 | G5: {=SUM(INDEX(Working_Data!$D:$P,MATCH(1,(Working_Data!$A:$A="Rural+Urban")*(Working_Data!$B:$B=$F5)*(Working_Data!$C:$C=$E5),0),0))} -> 1756 | H5: {=SUM(INDEX(Working_Data!$R:$AA,MATCH(1,(Working_Data!$A:$A="Rural+Urban")*(Working_Data!$B:$B=$F5)*(Working_Data!$C:$C=$E5),0),{1,2,3,4,5,6,8,10}))} -> 1098.5 | I5: {=INDEX(Working_Data!$X:$X,MATCH(1,(Working_Data!$A:$A="Rural+Urban")*(Working_Data!$B:$B=$F5)*(Working_Data!$C:$C=$E5),0))} -> 134.3 | J5: =(G5-G4)/G4 -> -0.0024994319 | K5: =(H5-H4)/H4 -> 0.003746345 | L5: =(I5-I4)/I4 -> 0.0037369208 | M5: - | N5: - | O5: - | Q5: Essential Services | R5: =AVERAGE(N17:N28) -> 0.027262133 | S5: =AVERAGE(N29:N40) -> 0.029809891 | T5: =S5-R5 -> 0.0025477577
A6: Egg | B6: Food | D6: Apr'18 | E6: April | F6: 2018 | G6: {=SUM(INDEX(Working_Data!$D:$P,MATCH(1,(Working_Data!$A:$A="Rural+Urban")*(Working_Data!$B:$B=$F6)*(Working_Data!$C:$C=$E6),0),0))} -> 1757.1 | H6: {=SUM(INDEX(Working_Data!$R:$AA,MATCH(1,(Working_Data!$A:$A="Rural+Urban")*(Working_Data!$B:$B=$F6)*(Working_Data!$C:$C=$E6),0),{1,2,3,4,5,6,8,10}))} -> 1105.3 | I6: {=INDEX(Working_Data!$X:$X,MATCH(1,(Working_Data!$A:$A="Rural+Urban")*(Working_Data!$B:$B=$F6)*(Working_Data!$C:$C=$E6),0))} -> 135.2 | J6: =(G6-G5)/G5 -> 0.00062642369 | K6: =(H6-H5)/H5 -> 0.0061902594 | L6: =(I6-I5)/I5 -> 0.0067014147 | M6: - | N6: - | O6: - | Q6: Health | R6: =AVERAGE(O17:O28) -> 0.066277763 | S6: =AVERAGE(O29:O40) -> 0.046161016 | T6: =S6-R6 -> -0.020116747
A7: Milk and products | B7: Food | D7: May'18 | E7: May | F7: 2018 | G7: {=SUM(INDEX(Working_Data!$D:$P,MATCH(1,(Working_Data!$A:$A="Rural+Urban")*(Working_Data!$B:$B=$F7)*(Working_Data!$C:$C=$E7),0),0))} -> 1759.8 | H7: {=SUM(INDEX(Working_Data!$R:$AA,MATCH(1,(Working_Data!$A:$A="Rural+Urban")*(Working_Data!$B:$B=$F7)*(Working_Data!$C:$C=$E7),0),{1,2,3,4,5,6,8,10}))} -> 1110.6 | I7: {=INDEX(Working_Data!$X:$X,MATCH(1,(Working_Data!$A:$A="Rural+Urban")*(Working_Data!$B:$B=$F7)*(Working_Data!$C:$C=$E7),0))} -> 136 | J7: =(G7-G6)/G6 -> 0.0015366228 | K7: =(H7-H6)/H6 -> 0.0047950783 | L7: =(I7-I6)/I6 -> 0.0059171598 | M7: - | N7: - | O7: -
A8: Oils and fats | B8: Food | D8: Jun'18 | E8: June | F8: 2018 | G8: {=SUM(INDEX(Working_Data!$D:$P,MATCH(1,(Working_Data!$A:$A="Rural+Urban")*(Working_Data!$B:$B=$F8)*(Working_Data!$C:$C=$E8),0),0))} -> 1774.1 | H8: {=SUM(INDEX(Working_Data!$R:$AA,MATCH(1,(Working_Data!$A:$A="Rural+Urban")*(Working_Data!$B:$B=$F8)*(Working_Data!$C:$C=$E8),0),{1,2,3,4,5,6,8,10}))} -> 1114.7 | I8: {=INDEX(Working_Data!$X:$X,MATCH(1,(Working_Data!$A:$A="Rural+Urban")*(Working_Data!$B:$B=$F8)*(Working_Data!$C:$C=$E8),0))} -> 136.2 | J8: =(G8-G7)/G7 -> 0.0081259234 | K8: =(H8-H7)/H7 -> 0.0036916982 | L8: =(I8-I7)/I7 -> 0.0014705882 | M8: - | N8: - | O8: -
A9: Fruits | B9: Food | D9: Jul'18 | E9: July | F9: 2018 | G9: {=SUM(INDEX(Working_Data!$D:$P,MATCH(1,(Working_Data!$A:$A="Rural+Urban")*(Working_Data!$B:$B=$F9)*(Working_Data!$C:$C=$E9),0),0))} -> 1795.3 | H9: {=SUM(INDEX(Working_Data!$R:$AA,MATCH(1,(Working_Data!$A:$A="Rural+Urban")*(Working_Data!$B:$B=$F9)*(Working_Data!$C:$C=$E9),0),{1,2,3,4,5,6,8,10}))} -> 1121 | I9: {=INDEX(Working_Data!$X:$X,MATCH(1,(Working_Data!$A:$A="Rural+Urban")*(Working_Data!$B:$B=$F9)*(Working_Data!$C:$C=$E9),0))} -> 137 | J9: =(G9-G8)/G8 -> 0.011949721 | K9: =(H9-H8)/H8 -> 0.0056517449 | L9: =(I9-I8)/I8 -> 0.0058737151 | M9: - | N9: - | O9: -
A10: Vegetables | B10: Food | D10: Aug'18 | E10: August | F10: 2018 | G10: {=SUM(INDEX(Working_Data!$D:$P,MATCH(1,(Working_Data!$A:$A="Rural+Urban")*(Working_Data!$B:$B=$F10)*(Working_Data!$C:$C=$E10),0),0))} -> 1798.7 | H10: {=SUM(INDEX(Working_Data!$R:$AA,MATCH(1,(Working_Data!$A:$A="Rural+Urban")*(Working_Data!$B:$B=$F10)*(Working_Data!$C:$C=$E10),0),{1,2,3,4,5,6,8,10}))} -> 1127.4 | I10: {=INDEX(Working_Data!$X:$X,MATCH(1,(Working_Data!$A:$A="Rural+Urban")*(Working_Data!$B:$B=$F10)*(Working_Data!$C:$C=$E10),0))} -> 137.7 | J10: =(G10-G9)/G9 -> 0.0018938339 | K10: =(H10-H9)/H9 -> 0.0057091882 | L10: =(I10-I9)/I9 -> 0.0051094891 | M10: - | N10: - | O10: -
A11: Pulses and products | B11: Food | D11: Sep'18 | E11: September | F11: 2018 | G11: {=SUM(INDEX(Working_Data!$D:$P,MATCH(1,(Working_Data!$A:$A="Rural+Urban")*(Working_Data!$B:$B=$F11)*(Working_Data!$C:$C=$E11),0),0))} -> 1779.5 | H11: {=SUM(INDEX(Working_Data!$R:$AA,MATCH(1,(Working_Data!$A:$A="Rural+Urban")*(Working_Data!$B:$B=$F11)*(Working_Data!$C:$C=$E11),0),{1,2,3,4,5,6,8,10}))} -> 1132.8 | I11: {=INDEX(Working_Data!$X:$X,MATCH(1,(Working_Data!$A:$A="Rural+Urban")*(Working_Data!$B:$B=$F11)*(Working_Data!$C:$C=$E11),0))} -> 138.4 | J11: =(G11-G10)/G10 -> -0.010674376 | K11: =(H11-H10)/H10 -> 0.0047897818 | L11: =(I11-I10)/I10 -> 0.0050835149 | M11: - | N11: - | O11: -
A12: Sugar and Confectionery | B12: Food | D12: Oct'18 | E12: October | F12: 2018 | G12: {=SUM(INDEX(Working_Data!$D:$P,MATCH(1,(Working_Data!$A:$A="Rural+Urban")*(Working_Data!$B:$B=$F12)*(Working_Data!$C:$C=$E12),0),0))} -> 1776.2 | H12: {=SUM(INDEX(Working_Data!$R:$AA,MATCH(1,(Working_Data!$A:$A="Rural+Urban")*(Working_Data!$B:$B=$F12)*(Working_Data!$C:$C=$E12),0),{1,2,3,4,5,6,8,10}))} -> 1141.7 | I12: {=INDEX(Working_Data!$X:$X,MATCH(1,(Working_Data!$A:$A="Rural+Urban")*(Working_Data!$B:$B=$F12)*(Working_Data!$C:$C=$E12),0))} -> 142.1 | J12: =(G12-G11)/G11 -> -0.0018544535 | K12: =(H12-H11)/H11 -> 0.0078566384 | L12: =(I12-I11)/I11 -> 0.026734104 | M12: - | N12: - | O12: -
A13: Spices | B13: Food | D13: Nov'18 | E13: November | F13: 2018 | G13: {=SUM(INDEX(Working_Data!$D:$P,MATCH(1,(Working_Data!$A:$A="Rural+Urban")*(Working_Data!$B:$B=$F13)*(Working_Data!$C:$C=$E13),0),0))} -> 1775.7 | H13: {=SUM(INDEX(Working_Data!$R:$AA,MATCH(1,(Working_Data!$A:$A="Rural+Urban")*(Working_Data!$B:$B=$F13)*(Working_Data!$C:$C=$E13),0),{1,2,3,4,5,6,8,10}))} -> 1141.3 | I13: {=INDEX(Working_Data!$X:$X,MATCH(1,(Working_Data!$A:$A="Rural+Urban")*(Working_Data!$B:$B=$F13)*(Working_Data!$C:$C=$E13),0))} -> 142.1 | J13: =(G13-G12)/G12 -> -0.00028149983 | K13: =(H13-H12)/H12 -> -0.00035035473 | L13: =(I13-I12)/I12 -> 0 | M13: - | N13: - | O13: -
A14: Non-alcoholic beverages | B14: Food | D14: Dec'18 | E14: December | F14: 2018 | G14: {=SUM(INDEX(Working_Data!$D:$P,MATCH(1,(Working_Data!$A:$A="Rural+Urban")*(Working_Data!$B:$B=$F14)*(Working_Data!$C:$C=$E14),0),0))} -> 1762.8 | H14: {=SUM(INDEX(Working_Data!$R:$AA,MATCH(1,(Working_Data!$A:$A="Rural+Urban")*(Working_Data!$B:$B=$F14)*(Working_Data!$C:$C=$E14),0),{1,2,3,4,5,6,8,10}))} -> 1140.4 | I14: {=INDEX(Working_Data!$X:$X,MATCH(1,(Working_Data!$A:$A="Rural+Urban")*(Working_Data!$B:$B=$F14)*(Working_Data!$C:$C=$E14),0))} -> 144.9 | J14: =(G14-G13)/G13 -> -0.0072647407 | K14: =(H14-H13)/H13 -> -0.00078857443 | L14: =(I14-I13)/I13 -> 0.019704433 | M14: - | N14: - | O14: -
A15: Prepared meals, snacks, sweets etc. | B15: Food | D15: Jan'19 | E15: January | F15: 2019 | G15: {=SUM(INDEX(Working_Data!$D:$P,MATCH(1,(Working_Data!$A:$A="Rural+Urban")*(Working_Data!$B:$B=$F15)*(Working_Data!$C:$C=$E15),0),0))} -> 1753.4 | H15: {=SUM(INDEX(Working_Data!$R:$AA,MATCH(1,(Working_Data!$A:$A="Rural+Urban")*(Working_Data!$B:$B=$F15)*(Working_Data!$C:$C=$E15),0),{1,2,3,4,5,6,8,10}))} -> 1137.3 | I15: {=INDEX(Working_Data!$X:$X,MATCH(1,(Working_Data!$A:$A="Rural+Urban")*(Working_Data!$B:$B=$F15)*(Working_Data!$C:$C=$E15),0))} -> 145.1 | J15: =(G15-G14)/G14 -> -0.0053324257 | K15: =(H15-H14)/H14 -> -0.0027183444 | L15: =(I15-I14)/I14 -> 0.0013802622 | M15: - | N15: - | O15: -
A16: Food and beverages | B16: Food | D16: Feb'19 | E16: February | F16: 2019 | G16: {=SUM(INDEX(Working_Data!$D:$P,MATCH(1,(Working_Data!$A:$A="Rural+Urban")*(Working_Data!$B:$B=$F16)*(Working_Data!$C:$C=$E16),0),0))} -> 1757.1 | H16: {=SUM(INDEX(Working_Data!$R:$AA,MATCH(1,(Working_Data!$A:$A="Rural+Urban")*(Working_Data!$B:$B=$F16)*(Working_Data!$C:$C=$E16),0),{1,2,3,4,5,6,8,10}))} -> 1138.7 | I16: {=INDEX(Working_Data!$X:$X,MATCH(1,(Working_Data!$A:$A="Rural+Urban")*(Working_Data!$B:$B=$F16)*(Working_Data!$C:$C=$E16),0))} -> 145.6 | J16: =(G16-G15)/G15 -> 0.0021101859 | K16: =(H16-H15)/H15 -> 0.0012309857 | L16: =(I16-I15)/I15 -> 0.0034458994 | M16: =(G16-G4)/G4 -> -0.001874574 | N16: =(H16-H4)/H4 -> 0.040478801 | O16: =(I16-I4)/I4 -> 0.08819133
A17: Clothing | B17: Essential Services | D17: Mar'19 | E17: March | F17: 2019 | G17: {=SUM(INDEX(Working_Data!$D:$P,MATCH(1,(Working_Data!$A:$A="Rural+Urban")*(Working_Data!$B:$B=$F17)*(Working_Data!$C:$C=$E17),0),0))} -> 1762.9 | H17: {=SUM(INDEX(Working_Data!$R:$AA,MATCH(1,(Working_Data!$A:$A="Rural+Urban")*(Working_Data!$B:$B=$F17)*(Working_Data!$C:$C=$E17),0),{1,2,3,4,5,6,8,10}))} -> 1141.9 | I17: {=INDEX(Working_Data!$X:$X,MATCH(1,(Working_Data!$A:$A="Rural+Urban")*(Working_Data!$B:$B=$F17)*(Working_Data!$C:$C=$E17),0))} -> 146.2 | J17: =(G17-G16)/G16 -> 0.0033008935 | K17: =(H17-H16)/H16 -> 0.0028102222 | L17: =(I17-I16)/I16 -> 0.0041208791 | M17: =(G17-G5)/G5 -> 0.003929385 | N17: =(H17-H5)/H5 -> 0.039508421 | O17: =(I17-I5)/I5 -> 0.088607595
A18: Footwear | B18: Essential Services | D18: Apr'19 | E18: April | F18: 2019 | G18: {=SUM(INDEX(Working_Data!$D:$P,MATCH(1,(Working_Data!$A:$A="Rural+Urban")*(Working_Data!$B:$B=$F18)*(Working_Data!$C:$C=$E18),0),0))} -> 1770.6333 | H18: {=SUM(INDEX(Working_Data!$R:$AA,MATCH(1,(Working_Data!$A:$A="Rural+Urban")*(Working_Data!$B:$B=$F18)*(Working_Data!$C:$C=$E18),0),{1,2,3,4,5,6,8,10}))} -> 1142.4333 | I18: {=INDEX(Working_Data!$X:$X,MATCH(1,(Working_Data!$A:$A="Rural+Urban")*(Working_Data!$B:$B=$F18)*(Working_Data!$C:$C=$E18),0))} -> 146.23333 | J18: =(G18-G17)/G17 -> 0.0043867113 | K18: =(H18-H17)/H17 -> 0.00046705783 | L18: =(I18-I17)/I17 -> 0.00022799818 | M18: =(G18-G6)/G6 -> 0.0077020849 | N18: =(H18-H6)/H6 -> 0.033595706 | O18: =(I18-I6)/I6 -> 0.081607495
A19: Clothing and footwear | B19: Essential Services | D19: May'19 | E19: May | F19: 2019 | G19: {=SUM(INDEX(Working_Data!$D:$P,MATCH(1,(Working_Data!$A:$A="Rural+Urban")*(Working_Data!$B:$B=$F19)*(Working_Data!$C:$C=$E19),0),0))} -> 1791.9 | H19: {=SUM(INDEX(Working_Data!$R:$AA,MATCH(1,(Working_Data!$A:$A="Rural+Urban")*(Working_Data!$B:$B=$F19)*(Working_Data!$C:$C=$E19),0),{1,2,3,4,5,6,8,10}))} -> 1146.7 | I19: {=INDEX(Working_Data!$X:$X,MATCH(1,(Working_Data!$A:$A="Rural+Urban")*(Working_Data!$B:$B=$F19)*(Working_Data!$C:$C=$E19),0))} -> 146.9 | J19: =(G19-G18)/G18 -> 0.012010768 | K19: =(H19-H18)/H18 -> 0.0037347183 | L19: =(I19-I18)/I18 -> 0.0045589241 | M19: =(G19-G7)/G7 -> 0.018240709 | N19: =(H19-H7)/H7 -> 0.032504952 | O19: =(I19-I7)/I7 -> 0.080147059
A20: Housing | B20: Essential Services | D20: Jun'19 | E20: June | F20: 2019 | G20: {=SUM(INDEX(Working_Data!$D:$P,MATCH(1,(Working_Data!$A:$A="Rural+Urban")*(Working_Data!$B:$B=$F20)*(Working_Data!$C:$C=$E20),0),0))} -> 1814.1 | H20: {=SUM(INDEX(Working_Data!$R:$AA,MATCH(1,(Working_Data!$A:$A="Rural+Urban")*(Working_Data!$B:$B=$F20)*(Working_Data!$C:$C=$E20),0),{1,2,3,4,5,6,8,10}))} -> 1147.9 | I20: {=INDEX(Working_Data!$X:$X,MATCH(1,(Working_Data!$A:$A="Rural+Urban")*(Working_Data!$B:$B=$F20)*(Working_Data!$C:$C=$E20),0))} -> 147.4 | J20: =(G20-G19)/G19 -> 0.012389084 | K20: =(H20-H19)/H19 -> 0.0010464812 | L20: =(I20-I19)/I19 -> 0.003403676 | M20: =(G20-G8)/G8 -> 0.022546643 | N20: =(H20-H8)/H8 -> 0.029783798 | O20: =(I20-I8)/I8 -> 0.082232012
A21: Fuel and light | B21: Essential Services | D21: Jul'19 | E21: July | F21: 2019 | G21: {=SUM(INDEX(Working_Data!$D:$P,MATCH(1,(Working_Data!$A:$A="Rural+Urban")*(Working_Data!$B:$B=$F21)*(Working_Data!$C:$C=$E21),0),0))} -> 1837.5 | H21: {=SUM(INDEX(Working_Data!$R:$AA,MATCH(1,(Working_Data!$A:$A="Rural+Urban")*(Working_Data!$B:$B=$F21)*(Working_Data!$C:$C=$E21),0),{1,2,3,4,5,6,8,10}))} -> 1150.7 | I21: {=INDEX(Working_Data!$X:$X,MATCH(1,(Working_Data!$A:$A="Rural+Urban")*(Working_Data!$B:$B=$F21)*(Working_Data!$C:$C=$E21),0))} -> 147.9 | J21: =(G21-G20)/G20 -> 0.012898958 | K21: =(H21-H20)/H20 -> 0.0024392369 | L21: =(I21-I20)/I20 -> 0.0033921303 | M21: =(G21-G9)/G9 -> 0.023505821 | N21: =(H21-H9)/H9 -> 0.026494202 | O21: =(I21-I9)/I9 -> 0.079562044
A22: Household goods and services | B22: Essential Services | D22: Aug'19 | E22: August | F22: 2019 | G22: {=SUM(INDEX(Working_Data!$D:$P,MATCH(1,(Working_Data!$A:$A="Rural+Urban")*(Working_Data!$B:$B=$F22)*(Working_Data!$C:$C=$E22),0),0))} -> 1846.5 | H22: {=SUM(INDEX(Working_Data!$R:$AA,MATCH(1,(Working_Data!$A:$A="Rural+Urban")*(Working_Data!$B:$B=$F22)*(Working_Data!$C:$C=$E22),0),{1,2,3,4,5,6,8,10}))} -> 1152.9 | I22: {=INDEX(Working_Data!$X:$X,MATCH(1,(Working_Data!$A:$A="Rural+Urban")*(Working_Data!$B:$B=$F22)*(Working_Data!$C:$C=$E22),0))} -> 148.5 | J22: =(G22-G21)/G21 -> 0.0048979592 | K22: =(H22-H21)/H21 -> 0.0019118797 | L22: =(I22-I21)/I21 -> 0.0040567951 | M22: =(G22-G10)/G10 -> 0.026574748 | N22: =(H22-H10)/H10 -> 0.022618414 | O22: =(I22-I10)/I10 -> 0.078431373
A23: Transport and communication | B23: Essential Services | D23: Sep'19 | E23: September | F23: 2019 | G23: {=SUM(INDEX(Working_Data!$D:$P,MATCH(1,(Working_Data!$A:$A="Rural+Urban")*(Working_Data!$B:$B=$F23)*(Working_Data!$C:$C=$E23),0),0))} -> 1857.7 | H23: {=SUM(INDEX(Working_Data!$R:$AA,MATCH(1,(Working_Data!$A:$A="Rural+Urban")*(Working_Data!$B:$B=$F23)*(Working_Data!$C:$C=$E23),0),{1,2,3,4,5,6,8,10}))} -> 1155 | I23: {=INDEX(Working_Data!$X:$X,MATCH(1,(Working_Data!$A:$A="Rural+Urban")*(Working_Data!$B:$B=$F23)*(Working_Data!$C:$C=$E23),0))} -> 149 | J23: =(G23-G22)/G22 -> 0.0060655294 | K23: =(H23-H22)/H22 -> 0.0018214936 | L23: =(I23-I22)/I22 -> 0.0033670034 | M23: =(G23-G11)/G11 -> 0.043944928 | N23: =(H23-H11)/H11 -> 0.019597458 | O23: =(I23-I11)/I11 -> 0.076589595
A24: Education | B24: Essential Services | D24: Oct'19 | E24: October | F24: 2019 | G24: {=SUM(INDEX(Working_Data!$D:$P,MATCH(1,(Working_Data!$A:$A="Rural+Urban")*(Working_Data!$B:$B=$F24)*(Working_Data!$C:$C=$E24),0),0))} -> 1885.6 | H24: {=SUM(INDEX(Working_Data!$R:$AA,MATCH(1,(Working_Data!$A:$A="Rural+Urban")*(Working_Data!$B:$B=$F24)*(Working_Data!$C:$C=$E24),0),{1,2,3,4,5,6,8,10}))} -> 1158.7 | I24: {=INDEX(Working_Data!$X:$X,MATCH(1,(Working_Data!$A:$A="Rural+Urban")*(Working_Data!$B:$B=$F24)*(Working_Data!$C:$C=$E24),0))} -> 149.4 | J24: =(G24-G23)/G23 -> 0.015018571 | K24: =(H24-H23)/H23 -> 0.0032034632 | L24: =(I24-I23)/I23 -> 0.0026845638 | M24: =(G24-G12)/G12 -> 0.061592163 | N24: =(H24-H12)/H12 -> 0.014890076 | O24: =(I24-I12)/I12 -> 0.051372273
A25: Health | B25: Health | D25: Nov'19 | E25: November | F25: 2019 | G25: {=SUM(INDEX(Working_Data!$D:$P,MATCH(1,(Working_Data!$A:$A="Rural+Urban")*(Working_Data!$B:$B=$F25)*(Working_Data!$C:$C=$E25),0),0))} -> 1910.9 | H25: {=SUM(INDEX(Working_Data!$R:$AA,MATCH(1,(Working_Data!$A:$A="Rural+Urban")*(Working_Data!$B:$B=$F25)*(Working_Data!$C:$C=$E25),0),{1,2,3,4,5,6,8,10}))} -> 1162.7 | I25: {=INDEX(Working_Data!$X:$X,MATCH(1,(Working_Data!$A:$A="Rural+Urban")*(Working_Data!$B:$B=$F25)*(Working_Data!$C:$C=$E25),0))} -> 149.9 | J25: =(G25-G24)/G24 -> 0.01341748 | K25: =(H25-H24)/H24 -> 0.0034521446 | L25: =(I25-I24)/I24 -> 0.0033467202 | M25: =(G25-G13)/G13 -> 0.076138987 | N25: =(H25-H13)/H13 -> 0.018750548 | O25: =(I25-I13)/I13 -> 0.054890922
A26: Pan, tobacco and intoxicants | B26: — | D26: Dec'19 | E26: December | F26: 2019 | G26: {=SUM(INDEX(Working_Data!$D:$P,MATCH(1,(Working_Data!$A:$A="Rural+Urban")*(Working_Data!$B:$B=$F26)*(Working_Data!$C:$C=$E26),0),0))} -> 1946.1 | H26: {=SUM(INDEX(Working_Data!$R:$AA,MATCH(1,(Working_Data!$A:$A="Rural+Urban")*(Working_Data!$B:$B=$F26)*(Working_Data!$C:$C=$E26),0),{1,2,3,4,5,6,8,10}))} -> 1168.4 | I26: {=INDEX(Working_Data!$X:$X,MATCH(1,(Working_Data!$A:$A="Rural+Urban")*(Working_Data!$B:$B=$F26)*(Working_Data!$C:$C=$E26),0))} -> 150.4 | J26: =(G26-G25)/G25 -> 0.018420639 | K26: =(H26-H25)/H25 -> 0.0049023824 | L26: =(I26-I25)/I25 -> 0.003335557 | M26: =(G26-G14)/G14 -> 0.1039823 | N26: =(H26-H14)/H14 -> 0.024552788 | O26: =(I26-I14)/I14 -> 0.037957212
A27: Recreation and amusement | B27: — | D27: Jan'20 | E27: January | F27: 2020 | G27: {=SUM(INDEX(Working_Data!$D:$P,MATCH(1,(Working_Data!$A:$A="Rural+Urban")*(Working_Data!$B:$B=$F27)*(Working_Data!$C:$C=$E27),0),0))} -> 1940.4 | H27: {=SUM(INDEX(Working_Data!$R:$AA,MATCH(1,(Working_Data!$A:$A="Rural+Urban")*(Working_Data!$B:$B=$F27)*(Working_Data!$C:$C=$E27),0),{1,2,3,4,5,6,8,10}))} -> 1172.9 | I27: {=INDEX(Working_Data!$X:$X,MATCH(1,(Working_Data!$A:$A="Rural+Urban")*(Working_Data!$B:$B=$F27)*(Working_Data!$C:$C=$E27),0))} -> 151.2 | J27: =(G27-G26)/G26 -> -0.0029289348 | K27: =(H27-H26)/H26 -> 0.0038514207 | L27: =(I27-I26)/I26 -> 0.0053191489 | M27: =(G27-G15)/G15 -> 0.10664994 | N27: =(H27-H15)/H15 -> 0.031302207 | O27: =(I27-I15)/I15 -> 0.042039972
... A30: General index | B30: — | D30: Apr'20 | E30: April | F30: 2020 | G30: {=SUM(INDEX(Working_Data!$D:$P,MATCH(1,(Working_Data!$A:$A="Rural+Urban")*(Working_Data!$B:$B=$F30)*(Working_Data!$C:$C=$E30),0),0))} -> 1958.6 | H30: {=SUM(INDEX(Working_Data!$R:$AA,MATCH(1,(Working_Data!$A:$A="Rural+Urban")*(Working_Data!$B:$B=$F30)*(Working_Data!$C:$C=$E30),0),{1,2,3,4,5,6,8,10}))} -> 1260.7 | I30: {=INDEX(Working_Data!$X:$X,MATCH(1,(Working_Data!$A:$A="Rural+Urban")*(Working_Data!$B:$B=$F30)*(Working_Data!$C:$C=$E30),0))} -> 150.7 | J30: =(G30-G29)/G29 -> 0.033343885 | K30: =(H30-H29)/H29 -> 0.069568168 | L30: =(I30-I29)/I29 -> -0.010505581 | M30: =(G30-G18)/G18 -> 0.10615787 | N30: =(H30-H18)/H18 -> 0.10352172 | O30: =(I30-I18)/I18 -> 0.030544791
D31: May'20 | E31: May | F31: 2020 | G31: {=SUM(INDEX(Working_Data!$D:$P,MATCH(1,(Working_Data!$A:$A="Rural+Urban")*(Working_Data!$B:$B=$F31)*(Working_Data!$C:$C=$E31),0),0))} -> 1940.2667 | H31: {=SUM(INDEX(Working_Data!$R:$AA,MATCH(1,(Working_Data!$A:$A="Rural+Urban")*(Working_Data!$B:$B=$F31)*(Working_Data!$C:$C=$E31),0),{1,2,3,4,5,6,8,10}))} -> 1052.4333 | I31: {=INDEX(Working_Data!$X:$X,MATCH(1,(Working_Data!$A:$A="Rural+Urban")*(Working_Data!$B:$B=$F31)*(Working_Data!$C:$C=$E31),0))} -> 152.46667 | J31: =(G31-G30)/G30 -> -0.0093604275 | K31: =(H31-H30)/H30 -> -0.16519923 | L31: =(I31-I30)/I30 -> 0.01172307 | M31: =(G31-G19)/G19 -> 0.082798519 | N31: =(H31-H19)/H19 -> -0.082206913 | O31: =(I31-I19)/I19 -> 0.037894259
D32: Jun'20 | E32: June | F32: 2020 | G32: {=SUM(INDEX(Working_Data!$D:$P,MATCH(1,(Working_Data!$A:$A="Rural+Urban")*(Working_Data!$B:$B=$F32)*(Working_Data!$C:$C=$E32),0),0))} -> 1966.8 | H32: {=SUM(INDEX(Working_Data!$R:$AA,MATCH(1,(Working_Data!$A:$A="Rural+Urban")*(Working_Data!$B:$B=$F32)*(Working_Data!$C:$C=$E32),0),{1,2,3,4,5,6,8,10}))} -> 1182.7 | I32: {=INDEX(Working_Data!$X:$X,MATCH(1,(Working_Data!$A:$A="Rural+Urban")*(Working_Data!$B:$B=$F32)*(Working_Data!$C:$C=$E32),0))} -> 154.4 | J32: =(G32-G31)/G31 -> 0.013675096 | K32: =(H32-H31)/H31 -> 0.12377664 | L32: =(I32-I31)/I31 -> 0.012680367 | M32: =(G32-G20)/G20 -> 0.084173971 | N32: =(H32-H20)/H20 -> 0.03031623 | O32: =(I32-I20)/I20 -> 0.047489824
D33: Jul'20 | E33: July | F33: 2020 | G33: {=SUM(INDEX(Working_Data!$D:$P,MATCH(1,(Working_Data!$A:$A="Rural+Urban")*(Working_Data!$B:$B=$F33)*(Working_Data!$C:$C=$E33),0),0))} -> 1966.8 | H33: {=SUM(INDEX(Working_Data!$R:$AA,MATCH(1,(Working_Data!$A:$A="Rural+Urban")*(Working_Data!$B:$B=$F33)*(Working_Data!$C:$C=$E33),0),{1,2,3,4,5,6,8,10}))} -> 1182.7 | I33: {=INDEX(Working_Data!$X:$X,MATCH(1,(Working_Data!$A:$A="Rural+Urban")*(Working_Data!$B:$B=$F33)*(Working_Data!$C:$C=$E33),0))} -> 154.4 | J33: =(G33-G32)/G32 -> 0 | K33: =(H33-H32)/H32 -> 0 | L33: =(I33-I32)/I32 -> 0 | M33: =(G33-G21)/G21 -> 0.070367347 | N33: =(H33-H21)/H21 -> 0.02780916 | O33: =(I33-I21)/I21 -> 0.043948614
D34: Aug'20 | E34: August | F34: 2020 | G34: {=SUM(INDEX(Working_Data!$D:$P,MATCH(1,(Working_Data!$A:$A="Rural+Urban")*(Working_Data!$B:$B=$F34)*(Working_Data!$C:$C=$E34),0),0))} -> 1995.2 | H34: {=SUM(INDEX(Working_Data!$R:$AA,MATCH(1,(Working_Data!$A:$A="Rural+Urban")*(Working_Data!$B:$B=$F34)*(Working_Data!$C:$C=$E34),0),{1,2,3,4,5,6,8,10}))} -> 1192.1 | I34: {=INDEX(Working_Data!$X:$X,MATCH(1,(Working_Data!$A:$A="Rural+Urban")*(Working_Data!$B:$B=$F34)*(Working_Data!$C:$C=$E34),0))} -> 155 | J34: =(G34-G33)/G33 -> 0.014439699 | K34: =(H34-H33)/H33 -> 0.0079479158 | L34: =(I34-I33)/I33 -> 0.0038860104 | M34: =(G34-G22)/G22 -> 0.080530734 | N34: =(H34-H22)/H22 -> 0.034001214 | O34: =(I34-I22)/I22 -> 0.043771044
D35: Sep'20 | E35: September | F35: 2020 | G35: {=SUM(INDEX(Working_Data!$D:$P,MATCH(1,(Working_Data!$A:$A="Rural+Urban")*(Working_Data!$B:$B=$F35)*(Working_Data!$C:$C=$E35),0),0))} -> 2007 | H35: {=SUM(INDEX(Working_Data!$R:$AA,MATCH(1,(Working_Data!$A:$A="Rural+Urban")*(Working_Data!$B:$B=$F35)*(Working_Data!$C:$C=$E35),0),{1,2,3,4,5,6,8,10}))} -> 1194.7 | I35: {=INDEX(Working_Data!$X:$X,MATCH(1,(Working_Data!$A:$A="Rural+Urban")*(Working_Data!$B:$B=$F35)*(Working_Data!$C:$C=$E35),0))} -> 155.6 | J35: =(G35-G34)/G34 -> 0.0059141941 | K35: =(H35-H34)/H34 -> 0.0021810251 | L35: =(I35-I34)/I34 -> 0.0038709677 | M35: =(G35-G23)/G23 -> 0.080368197 | N35: =(H35-H23)/H23 -> 0.034372294 | O35: =(I35-I23)/I23 -> 0.044295302
D36: Oct'20 | E36: October | F36: 2020 | G36: {=SUM(INDEX(Working_Data!$D:$P,MATCH(1,(Working_Data!$A:$A="Rural+Urban")*(Working_Data!$B:$B=$F36)*(Working_Data!$C:$C=$E36),0),0))} -> 2048.6 | H36: {=SUM(INDEX(Working_Data!$R:$AA,MATCH(1,(Working_Data!$A:$A="Rural+Urban")*(Working_Data!$B:$B=$F36)*(Working_Data!$C:$C=$E36),0),{1,2,3,4,5,6,8,10}))} -> 1198 | I36: {=INDEX(Working_Data!$X:$X,MATCH(1,(Working_Data!$A:$A="Rural+Urban")*(Working_Data!$B:$B=$F36)*(Working_Data!$C:$C=$E36),0))} -> 156.3 | J36: =(G36-G35)/G35 -> 0.020727454 | K36: =(H36-H35)/H35 -> 0.0027621997 | L36: =(I36-I35)/I35 -> 0.0044987147 | M36: =(G36-G24)/G24 -> 0.086444633 | N36: =(H36-H24)/H24 -> 0.033917321 | O36: =(I36-I24)/I24 -> 0.046184739
D37: Nov'20 | E37: November | F37: 2020 | G37: {=SUM(INDEX(Working_Data!$D:$P,MATCH(1,(Working_Data!$A:$A="Rural+Urban")*(Working_Data!$B:$B=$F37)*(Working_Data!$C:$C=$E37),0),0))} -> 2095.6 | H37: {=SUM(INDEX(Working_Data!$R:$AA,MATCH(1,(Working_Data!$A:$A="Rural+Urban")*(Working_Data!$B:$B=$F37)*(Working_Data!$C:$C=$E37),0),{1,2,3,4,5,6,8,10}))} -> 1201.8 | I37: {=INDEX(Working_Data!$X:$X,MATCH(1,(Working_Data!$A:$A="Rural+Urban")*(Working_Data!$B:$B=$F37)*(Working_Data!$C:$C=$E37),0))} -> 157.2 | J37: =(G37-G36)/G36 -> 0.022942497 | K37: =(H37-H36)/H36 -> 0.0031719533 | L37: =(I37-I36)/I36 -> 0.0057581574 | M37: =(G37-G25)/G25 -> 0.096656026 | N37: =(H37-H25)/H25 -> 0.033628623 | O37: =(I37-I25)/I25 -> 0.048699133
D38: Dec'20 | E38: December | F38: 2020 | G38: {=SUM(INDEX(Working_Data!$D:$P,MATCH(1,(Working_Data!$A:$A="Rural+Urban")*(Working_Data!$B:$B=$F38)*(Working_Data!$C:$C=$E38),0),0))} -> 2109.1 | H38: {=SUM(INDEX(Working_Data!$R:$AA,MATCH(1,(Working_Data!$A:$A="Rural+Urban")*(Working_Data!$B:$B=$F38)*(Working_Data!$C:$C=$E38),0),{1,2,3,4,5,6,8,10}))} -> 1206.8 | I38: {=INDEX(Working_Data!$X:$X,MATCH(1,(Working_Data!$A:$A="Rural+Urban")*(Working_Data!$B:$B=$F38)*(Working_Data!$C:$C=$E38),0))} -> 158.3 | J38: =(G38-G37)/G37 -> 0.0064420691 | K38: =(H38-H37)/H37 -> 0.004160426 | L38: =(I38-I37)/I37 -> 0.0069974555 | M38: =(G38-G26)/G26 -> 0.083757258 | N38: =(H38-H26)/H26 -> 0.032865457 | O38: =(I38-I26)/I26 -> 0.052526596
D39: Jan'21 | E39: January | F39: 2021 | G39: {=SUM(INDEX(Working_Data!$D:$P,MATCH(1,(Working_Data!$A:$A="Rural+Urban")*(Working_Data!$B:$B=$F39)*(Working_Data!$C:$C=$E39),0),0))} -> 2076.5 | H39: {=SUM(INDEX(Working_Data!$R:$AA,MATCH(1,(Working_Data!$A:$A="Rural+Urban")*(Working_Data!$B:$B=$F39)*(Working_Data!$C:$C=$E39),0),{1,2,3,4,5,6,8,10}))} -> 1212.5 | I39: {=INDEX(Working_Data!$X:$X,MATCH(1,(Working_Data!$A:$A="Rural+Urban")*(Working_Data!$B:$B=$F39)*(Working_Data!$C:$C=$E39),0))} -> 159.3 | J39: =(G39-G38)/G38 -> -0.01545683 | K39: =(H39-H38)/H38 -> 0.004723235 | L39: =(I39-I38)/I38 -> 0.0063171194 | M39: =(G39-G27)/G27 -> 0.070140177 | N39: =(H39-H27)/H27 -> 0.033762469 | O39: =(I39-I27)/I27 -> 0.053571429
D40: Feb'21 | E40: February | F40: 2021 | G40: {=SUM(INDEX(Working_Data!$D:$P,MATCH(1,(Working_Data!$A:$A="Rural+Urban")*(Working_Data!$B:$B=$F40)*(Working_Data!$C:$C=$E40),0),0))} -> 2039.3 | H40: {=SUM(INDEX(Working_Data!$R:$AA,MATCH(1,(Working_Data!$A:$A="Rural+Urban")*(Working_Data!$B:$B=$F40)*(Working_Data!$C:$C=$E40),0),{1,2,3,4,5,6,8,10}))} -> 1228.1 | I40: {=INDEX(Working_Data!$X:$X,MATCH(1,(Working_Data!$A:$A="Rural+Urban")*(Working_Data!$B:$B=$F40)*(Working_Data!$C:$C=$E40),0))} -> 161.3 | J40: =(G40-G39)/G39 -> -0.01791476 | K40: =(H40-H39)/H39 -> 0.012865979 | L40: =(I40-I39)/I39 -> 0.012554928 | M40: =(G40-G28)/G28 -> 0.066802678 | N40: =(H40-H28)/H28 -> 0.043504121 | O40: =(I40-I28)/I28 -> 0.063282795
D41: Mar'21 | E41: March | F41: 2021 | G41: {=SUM(INDEX(Working_Data!$D:$P,MATCH(1,(Working_Data!$A:$A="Rural+Urban")*(Working_Data!$B:$B=$F41)*(Working_Data!$C:$C=$E41),0),0))} -> 2039.4 | H41: {=SUM(INDEX(Working_Data!$R:$AA,MATCH(1,(Working_Data!$A:$A="Rural+Urban")*(Working_Data!$B:$B=$F41)*(Working_Data!$C:$C=$E41),0),{1,2,3,4,5,6,8,10}))} -> 1235.1 | I41: {=INDEX(Working_Data!$X:$X,MATCH(1,(Working_Data!$A:$A="Rural+Urban")*(Working_Data!$B:$B=$F41)*(Working_Data!$C:$C=$E41),0))} -> 161.7 | J41: =(G41-G40)/G40 -> 4.9036434e-05 | K41: =(H41-H40)/H40 -> 0.0056998616 | L41: =(I41-I40)/I40 -> 0.0024798512 | M41: =(G41-G29)/G29 -> 0.075973409 | N41: =(H41-H29)/H29 -> 0.047849326 | O41: =(I41-I29)/I29 -> 0.061720289
D42: Apr'21 | E42: April | F42: 2021 | G42: {=SUM(INDEX(Working_Data!$D:$P,MATCH(1,(Working_Data!$A:$A="Rural+Urban")*(Working_Data!$B:$B=$F42)*(Working_Data!$C:$C=$E42),0),0))} -> 2064.1 | H42: {=SUM(INDEX(Working_Data!$R:$AA,MATCH(1,(Working_Data!$A:$A="Rural+Urban")*(Working_Data!$B:$B=$F42)*(Working_Data!$C:$C=$E42),0),{1,2,3,4,5,6,8,10}))} -> 1240.3 | I42: {=INDEX(Working_Data!$X:$X,MATCH(1,(Working_Data!$A:$A="Rural+Urban")*(Working_Data!$B:$B=$F42)*(Working_Data!$C:$C=$E42),0))} -> 162.3 | J42: =(G42-G41)/G41 -> 0.012111405 | K42: =(H42-H41)/H41 -> 0.0042101854 | L42: =(I42-I41)/I41 -> 0.0037105751 | M42: =(G42-G30)/G30 -> 0.053865006 | N42: =(H42-H30)/H30 -> -0.016181486 | O42: =(I42-I30)/I30 -> 0.076974121
... D53: Mar'22 | E53: March | F53: 2022 | G53: {=SUM(INDEX(Working_Data!$D:$P,MATCH(1,(Working_Data!$A:$A="Rural+Urban")*(Working_Data!$B:$B=$F53)*(Working_Data!$C:$C=$E53),0),0))} -> 2184.2 | H53: {=SUM(INDEX(Working_Data!$R:$AA,MATCH(1,(Working_Data!$A:$A="Rural+Urban")*(Working_Data!$B:$B=$F53)*(Working_Data!$C:$C=$E53),0),{1,2,3,4,5,6,8,10}))} -> 1327 | I53: {=INDEX(Working_Data!$X:$X,MATCH(1,(Working_Data!$A:$A="Rural+Urban")*(Working_Data!$B:$B=$F53)*(Working_Data!$C:$C=$E53),0))} -> 173 | J53: =(G53-G52)/G52 -> 0.010642236 | K53: =(H53-H52)/H52 -> 0.0067521432 | L53: =(I53-I52)/I52 -> 0.0046457607 | M53: =(G53-G41)/G41 -> 0.071001275 | N53: =(H53-H41)/H41 -> 0.074406931 | O53: =(I53-I41)/I41 -> 0.069882498
J56: Insight: Following the onset of COVID-19 in March 2020, food inflation increased from an average of 4.86% to 8.19%, while essential-services inflation increased slightly from 2.73% to 2.98%. Health inflation decreased from 6.63% to 4.62%. This indicates that the pandemic affected different CPI categories differently, with the largest increase observed in food inflation.

Sheet 5.Oil Price Data
A3: Analysis period: January 2021 to May 2023, based on the latest CPI data available in the provided dataset.
A4: Imported Crude Oil Price and CPI Category Correlation Analysis
A5: Area | B5: Original Category | C5: New Category | D5: Correlation | E5: 44166 | F5: 44197 | G5: 44228 | H5: 44256 | I5: 44287 | J5: 44317 | K5: 44348 | L5: 44378 | M5: 44409 | N5: 44440 | O5: 44470 | P5: 44501 | Q5: 44531 | R5: 44562 | S5: 44593 | T5: 44621 | U5: 44652 | V5: 44682 | W5: 44713 | X5: 44743 | Y5: 44774 | Z5: 44805 | AA5: 44835 | AB5: 44866 | AC5: 44896 | AD5: 44927 | AE5: 44958 | AF5: 44986 | AG5: 45017 | AH5: 45047 | AI5: 45078 | AJ5: 45108 | AK5: 45139 | AL5: 45170 | AM5: 45200 | AN5: 45231 | AO5: 45261
A6: Rural+Urban | B6: Cereals and products | C6: =_xlfn.XLOOKUP(B6,CPI_Category_Mapping[Category],CPI_Category_Mapping[New Food Category]) -> Food | D6: =CORREL(F6:AH6,'Crude Oil Price'!$B$5:$B$33) -> 0.25708758 | E6: {=INDEX(Working_Data!$D$2:$AD$2000,MATCH(1,(Working_Data!$A$2:$A$2000=$A6)*(Working_Data!$B$2:$B$2000=YEAR(E$5))*(Working_Data!$C$2:$C$2000=TEXT(E$5,"mmmm")),0),MATCH($B6,Working_Data!$D$1:$AD$1,0))} -> 146 | F6: {=INDEX(Working_Data!$D$2:$AD$2000,MATCH(1,(Working_Data!$A$2:$A$2000=$A6)*(Working_Data!$B$2:$B$2000=YEAR(F$5))*(Working_Data!$C$2:$C$2000=TEXT(F$5,"mmmm")),0),MATCH($B6,Working_Data!$D$1:$AD$1,0))} -> 144.9 | G6: {=INDEX(Working_Data!$D$2:$AD$2000,MATCH(1,(Working_Data!$A$2:$A$2000=$A6)*(Working_Data!$B$2:$B$2000=YEAR(G$5))*(Working_Data!$C$2:$C$2000=TEXT(G$5,"mmmm")),0),MATCH($B6,Working_Data!$D$1:$AD$1,0))} -> 144.3 | H6: {=INDEX(Working_Data!$D$2:$AD$2000,MATCH(1,(Working_Data!$A$2:$A$2000=$A6)*(Working_Data!$B$2:$B$2000=YEAR(H$5))*(Working_Data!$C$2:$C$2000=TEXT(H$5,"mmmm")),0),MATCH($B6,Working_Data!$D$1:$AD$1,0))} -> 144.1 | I6: {=INDEX(Working_Data!$D$2:$AD$2000,MATCH(1,(Working_Data!$A$2:$A$2000=$A6)*(Working_Data!$B$2:$B$2000=YEAR(I$5))*(Working_Data!$C$2:$C$2000=TEXT(I$5,"mmmm")),0),MATCH($B6,Working_Data!$D$1:$AD$1,0))} -> 144.3 | J6: {=INDEX(Working_Data!$D$2:$AD$2000,MATCH(1,(Working_Data!$A$2:$A$2000=$A6)*(Working_Data!$B$2:$B$2000=YEAR(J$5))*(Working_Data!$C$2:$C$2000=TEXT(J$5,"mmmm")),0),MATCH($B6,Working_Data!$D$1:$AD$1,0))} -> 146.3 | K6: {=INDEX(Working_Data!$D$2:$AD$2000,MATCH(1,(Working_Data!$A$2:$A$2000=$A6)*(Working_Data!$B$2:$B$2000=YEAR(K$5))*(Working_Data!$C$2:$C$2000=TEXT(K$5,"mmmm")),0),MATCH($B6,Working_Data!$D$1:$AD$1,0))} -> 146.7 | L6: {=INDEX(Working_Data!$D$2:$AD$2000,MATCH(1,(Working_Data!$A$2:$A$2000=$A6)*(Working_Data!$B$2:$B$2000=YEAR(L$5))*(Working_Data!$C$2:$C$2000=TEXT(L$5,"mmmm")),0),MATCH($B6,Working_Data!$D$1:$AD$1,0))} -> 146.4 | ... AH6: {=INDEX(Working_Data!$D$2:$AD$2000,MATCH(1,(Working_Data!$A$2:$A$2000=$A6)*(Working_Data!$B$2:$B$2000=YEAR(AH$5))*(Working_Data!$C$2:$C$2000=TEXT(AH$5,"mmmm")),0),MATCH($B6,Working_Data!$D$1:$AD$1,0))} -> 173.7 | AI6: - | AJ6: - | AK6: - | AL6: - | AM6: - | AN6: - | AO6: -
A7: Rural+Urban | B7: Meat and fish | C7: =_xlfn.XLOOKUP(B7,CPI_Category_Mapping[Category],CPI_Category_Mapping[New Food Category]) -> Food | D7: =CORREL(F7:AH7,'Crude Oil Price'!$B$5:$B$33) -> 0.7639664 | E7: {=INDEX(Working_Data!$D$2:$AD$2000,MATCH(1,(Working_Data!$A$2:$A$2000=$A7)*(Working_Data!$B$2:$B$2000=YEAR(E$5))*(Working_Data!$C$2:$C$2000=TEXT(E$5,"mmmm")),0),MATCH($B7,Working_Data!$D$1:$AD$1,0))} -> 191 | F7: {=INDEX(Working_Data!$D$2:$AD$2000,MATCH(1,(Working_Data!$A$2:$A$2000=$A7)*(Working_Data!$B$2:$B$2000=YEAR(F$5))*(Working_Data!$C$2:$C$2000=TEXT(F$5,"mmmm")),0),MATCH($B7,Working_Data!$D$1:$AD$1,0))} -> 190.1 | G7: {=INDEX(Working_Data!$D$2:$AD$2000,MATCH(1,(Working_Data!$A$2:$A$2000=$A7)*(Working_Data!$B$2:$B$2000=YEAR(G$5))*(Working_Data!$C$2:$C$2000=TEXT(G$5,"mmmm")),0),MATCH($B7,Working_Data!$D$1:$AD$1,0))} -> 186.5 | H7: {=INDEX(Working_Data!$D$2:$AD$2000,MATCH(1,(Working_Data!$A$2:$A$2000=$A7)*(Working_Data!$B$2:$B$2000=YEAR(H$5))*(Working_Data!$C$2:$C$2000=TEXT(H$5,"mmmm")),0),MATCH($B7,Working_Data!$D$1:$AD$1,0))} -> 192.2 | I7: {=INDEX(Working_Data!$D$2:$AD$2000,MATCH(1,(Working_Data!$A$2:$A$2000=$A7)*(Working_Data!$B$2:$B$2000=YEAR(I$5))*(Working_Data!$C$2:$C$2000=TEXT(I$5,"mmmm")),0),MATCH($B7,Working_Data!$D$1:$AD$1,0))} -> 198 | J7: {=INDEX(Working_Data!$D$2:$AD$2000,MATCH(1,(Working_Data!$A$2:$A$2000=$A7)*(Working_Data!$B$2:$B$2000=YEAR(J$5))*(Working_Data!$C$2:$C$2000=TEXT(J$5,"mmmm")),0),MATCH($B7,Working_Data!$D$1:$AD$1,0))} -> 200.5 | K7: {=INDEX(Working_Data!$D$2:$AD$2000,MATCH(1,(Working_Data!$A$2:$A$2000=$A7)*(Working_Data!$B$2:$B$2000=YEAR(K$5))*(Working_Data!$C$2:$C$2000=TEXT(K$5,"mmmm")),0),MATCH($B7,Working_Data!$D$1:$AD$1,0))} -> 202 | L7: {=INDEX(Working_Data!$D$2:$AD$2000,MATCH(1,(Working_Data!$A$2:$A$2000=$A7)*(Working_Data!$B$2:$B$2000=YEAR(L$5))*(Working_Data!$C$2:$C$2000=TEXT(L$5,"mmmm")),0),MATCH($B7,Working_Data!$D$1:$AD$1,0))} -> 206.8 | ... AH7: {=INDEX(Working_Data!$D$2:$AD$2000,MATCH(1,(Working_Data!$A$2:$A$2000=$A7)*(Working_Data!$B$2:$B$2000=YEAR(AH$5))*(Working_Data!$C$2:$C$2000=TEXT(AH$5,"mmmm")),0),MATCH($B7,Working_Data!$D$1:$AD$1,0))} -> 214.3 | AI7: - | AJ7: - | AK7: - | AL7: - | AM7: - | AN7: - | AO7: -
A8: Rural+Urban | B8: Egg | C8: =_xlfn.XLOOKUP(B8,CPI_Category_Mapping[Category],CPI_Category_Mapping[New Food Category]) -> Food | D8: =CORREL(F8:AH8,'Crude Oil Price'!$B$5:$B$33) -> -0.18636847 | E8: {=INDEX(Working_Data!$D$2:$AD$2000,MATCH(1,(Working_Data!$A$2:$A$2000=$A8)*(Working_Data!$B$2:$B$2000=YEAR(E$5))*(Working_Data!$C$2:$C$2000=TEXT(E$5,"mmmm")),0),MATCH($B8,Working_Data!$D$1:$AD$1,0))} -> 175.3 | F8: {=INDEX(Working_Data!$D$2:$AD$2000,MATCH(1,(Working_Data!$A$2:$A$2000=$A8)*(Working_Data!$B$2:$B$2000=YEAR(F$5))*(Working_Data!$C$2:$C$2000=TEXT(F$5,"mmmm")),0),MATCH($B8,Working_Data!$D$1:$AD$1,0))} -> 175.3 | G8: {=INDEX(Working_Data!$D$2:$AD$2000,MATCH(1,(Working_Data!$A$2:$A$2000=$A8)*(Working_Data!$B$2:$B$2000=YEAR(G$5))*(Working_Data!$C$2:$C$2000=TEXT(G$5,"mmmm")),0),MATCH($B8,Working_Data!$D$1:$AD$1,0))} -> 168.7 | H8: {=INDEX(Working_Data!$D$2:$AD$2000,MATCH(1,(Working_Data!$A$2:$A$2000=$A8)*(Working_Data!$B$2:$B$2000=YEAR(H$5))*(Working_Data!$C$2:$C$2000=TEXT(H$5,"mmmm")),0),MATCH($B8,Working_Data!$D$1:$AD$1,0))} -> 163.8 | I8: {=INDEX(Working_Data!$D$2:$AD$2000,MATCH(1,(Working_Data!$A$2:$A$2000=$A8)*(Working_Data!$B$2:$B$2000=YEAR(I$5))*(Working_Data!$C$2:$C$2000=TEXT(I$5,"mmmm")),0),MATCH($B8,Working_Data!$D$1:$AD$1,0))} -> 164.6 | J8: {=INDEX(Working_Data!$D$2:$AD$2000,MATCH(1,(Working_Data!$A$2:$A$2000=$A8)*(Working_Data!$B$2:$B$2000=YEAR(J$5))*(Working_Data!$C$2:$C$2000=TEXT(J$5,"mmmm")),0),MATCH($B8,Working_Data!$D$1:$AD$1,0))} -> 170.3 | K8: {=INDEX(Working_Data!$D$2:$AD$2000,MATCH(1,(Working_Data!$A$2:$A$2000=$A8)*(Working_Data!$B$2:$B$2000=YEAR(K$5))*(Working_Data!$C$2:$C$2000=TEXT(K$5,"mmmm")),0),MATCH($B8,Working_Data!$D$1:$AD$1,0))} -> 180.7 | L8: {=INDEX(Working_Data!$D$2:$AD$2000,MATCH(1,(Working_Data!$A$2:$A$2000=$A8)*(Working_Data!$B$2:$B$2000=YEAR(L$5))*(Working_Data!$C$2:$C$2000=TEXT(L$5,"mmmm")),0),MATCH($B8,Working_Data!$D$1:$AD$1,0))} -> 182.2 | ... AH8: {=INDEX(Working_Data!$D$2:$AD$2000,MATCH(1,(Working_Data!$A$2:$A$2000=$A8)*(Working_Data!$B$2:$B$2000=YEAR(AH$5))*(Working_Data!$C$2:$C$2000=TEXT(AH$5,"mmmm")),0),MATCH($B8,Working_Data!$D$1:$AD$1,0))} -> 173.2 | AI8: - | AJ8: - | AK8: - | AL8: - | AM8: - | AN8: - | AO8: -
A9: Rural+Urban | B9: Milk and products | C9: =_xlfn.XLOOKUP(B9,CPI_Category_Mapping[Category],CPI_Category_Mapping[New Food Category]) -> Food | D9: =CORREL(F9:AH9,'Crude Oil Price'!$B$5:$B$33) -> 0.35310879 | E9: {=INDEX(Working_Data!$D$2:$AD$2000,MATCH(1,(Working_Data!$A$2:$A$2000=$A9)*(Working_Data!$B$2:$B$2000=YEAR(E$5))*(Working_Data!$C$2:$C$2000=TEXT(E$5,"mmmm")),0),MATCH($B9,Working_Data!$D$1:$AD$1,0))} -> 154.1 | F9: {=INDEX(Working_Data!$D$2:$AD$2000,MATCH(1,(Working_Data!$A$2:$A$2000=$A9)*(Working_Data!$B$2:$B$2000=YEAR(F$5))*(Working_Data!$C$2:$C$2000=TEXT(F$5,"mmmm")),0),MATCH($B9,Working_Data!$D$1:$AD$1,0))} -> 154.1 | G9: {=INDEX(Working_Data!$D$2:$AD$2000,MATCH(1,(Working_Data!$A$2:$A$2000=$A9)*(Working_Data!$B$2:$B$2000=YEAR(G$5))*(Working_Data!$C$2:$C$2000=TEXT(G$5,"mmmm")),0),MATCH($B9,Working_Data!$D$1:$AD$1,0))} -> 154.7 | H9: {=INDEX(Working_Data!$D$2:$AD$2000,MATCH(1,(Working_Data!$A$2:$A$2000=$A9)*(Working_Data!$B$2:$B$2000=YEAR(H$5))*(Working_Data!$C$2:$C$2000=TEXT(H$5,"mmmm")),0),MATCH($B9,Working_Data!$D$1:$AD$1,0))} -> 154.9 | I9: {=INDEX(Working_Data!$D$2:$AD$2000,MATCH(1,(Working_Data!$A$2:$A$2000=$A9)*(Working_Data!$B$2:$B$2000=YEAR(I$5))*(Working_Data!$C$2:$C$2000=TEXT(I$5,"mmmm")),0),MATCH($B9,Working_Data!$D$1:$AD$1,0))} -> 155.4 | J9: {=INDEX(Working_Data!$D$2:$AD$2000,MATCH(1,(Working_Data!$A$2:$A$2000=$A9)*(Working_Data!$B$2:$B$2000=YEAR(J$5))*(Working_Data!$C$2:$C$2000=TEXT(J$5,"mmmm")),0),MATCH($B9,Working_Data!$D$1:$AD$1,0))} -> 156.1 | K9: {=INDEX(Working_Data!$D$2:$AD$2000,MATCH(1,(Working_Data!$A$2:$A$2000=$A9)*(Working_Data!$B$2:$B$2000=YEAR(K$5))*(Working_Data!$C$2:$C$2000=TEXT(K$5,"mmmm")),0),MATCH($B9,Working_Data!$D$1:$AD$1,0))} -> 156.2 | L9: {=INDEX(Working_Data!$D$2:$AD$2000,MATCH(1,(Working_Data!$A$2:$A$2000=$A9)*(Working_Data!$B$2:$B$2000=YEAR(L$5))*(Working_Data!$C$2:$C$2000=TEXT(L$5,"mmmm")),0),MATCH($B9,Working_Data!$D$1:$AD$1,0))} -> 157.5 | ... AH9: {=INDEX(Working_Data!$D$2:$AD$2000,MATCH(1,(Working_Data!$A$2:$A$2000=$A9)*(Working_Data!$B$2:$B$2000=YEAR(AH$5))*(Working_Data!$C$2:$C$2000=TEXT(AH$5,"mmmm")),0),MATCH($B9,Working_Data!$D$1:$AD$1,0))} -> 179.5 | AI9: - | AJ9: - | AK9: - | AL9: - | AM9: - | AN9: - | AO9: -
A10: Rural+Urban | B10: Oils and fats | C10: =_xlfn.XLOOKUP(B10,CPI_Category_Mapping[Category],CPI_Category_Mapping[New Food Category]) -> Food | D10: =CORREL(F10:AH10,'Crude Oil Price'!$B$5:$B$33) -> 0.80946651 | E10: {=INDEX(Working_Data!$D$2:$AD$2000,MATCH(1,(Working_Data!$A$2:$A$2000=$A10)*(Working_Data!$B$2:$B$2000=YEAR(E$5))*(Working_Data!$C$2:$C$2000=TEXT(E$5,"mmmm")),0),MATCH($B10,Working_Data!$D$1:$AD$1,0))} -> 146.6 | F10: {=INDEX(Working_Data!$D$2:$AD$2000,MATCH(1,(Working_Data!$A$2:$A$2000=$A10)*(Working_Data!$B$2:$B$2000=YEAR(F$5))*(Working_Data!$C$2:$C$2000=TEXT(F$5,"mmmm")),0),MATCH($B10,Working_Data!$D$1:$AD$1,0))} -> 150.9 | G10: {=INDEX(Working_Data!$D$2:$AD$2000,MATCH(1,(Working_Data!$A$2:$A$2000=$A10)*(Working_Data!$B$2:$B$2000=YEAR(G$5))*(Working_Data!$C$2:$C$2000=TEXT(G$5,"mmmm")),0),MATCH($B10,Working_Data!$D$1:$AD$1,0))} -> 158.7 | H10: {=INDEX(Working_Data!$D$2:$AD$2000,MATCH(1,(Working_Data!$A$2:$A$2000=$A10)*(Working_Data!$B$2:$B$2000=YEAR(H$5))*(Working_Data!$C$2:$C$2000=TEXT(H$5,"mmmm")),0),MATCH($B10,Working_Data!$D$1:$AD$1,0))} -> 163.9 | I10: {=INDEX(Working_Data!$D$2:$AD$2000,MATCH(1,(Working_Data!$A$2:$A$2000=$A10)*(Working_Data!$B$2:$B$2000=YEAR(I$5))*(Working_Data!$C$2:$C$2000=TEXT(I$5,"mmmm")),0),MATCH($B10,Working_Data!$D$1:$AD$1,0))} -> 170.1 | J10: {=INDEX(Working_Data!$D$2:$AD$2000,MATCH(1,(Working_Data!$A$2:$A$2000=$A10)*(Working_Data!$B$2:$B$2000=YEAR(J$5))*(Working_Data!$C$2:$C$2000=TEXT(J$5,"mmmm")),0),MATCH($B10,Working_Data!$D$1:$AD$1,0))} -> 178.7 | K10: {=INDEX(Working_Data!$D$2:$AD$2000,MATCH(1,(Working_Data!$A$2:$A$2000=$A10)*(Working_Data!$B$2:$B$2000=YEAR(K$5))*(Working_Data!$C$2:$C$2000=TEXT(K$5,"mmmm")),0),MATCH($B10,Working_Data!$D$1:$AD$1,0))} -> 183.7 | L10: {=INDEX(Working_Data!$D$2:$AD$2000,MATCH(1,(Working_Data!$A$2:$A$2000=$A10)*(Working_Data!$B$2:$B$2000=YEAR(L$5))*(Working_Data!$C$2:$C$2000=TEXT(L$5,"mmmm")),0),MATCH($B10,Working_Data!$D$1:$AD$1,0))} -> 182.1 | ... AH10: {=INDEX(Working_Data!$D$2:$AD$2000,MATCH(1,(Working_Data!$A$2:$A$2000=$A10)*(Working_Data!$B$2:$B$2000=YEAR(AH$5))*(Working_Data!$C$2:$C$2000=TEXT(AH$5,"mmmm")),0),MATCH($B10,Working_Data!$D$1:$AD$1,0))} -> 170 | AI10: - | AJ10: - | AK10: - | AL10: - | AM10: - | AN10: - | AO10: -
A11: Rural+Urban | B11: Fruits | C11: =_xlfn.XLOOKUP(B11,CPI_Category_Mapping[Category],CPI_Category_Mapping[New Food Category]) -> Food | D11: =CORREL(F11:AH11,'Crude Oil Price'!$B$5:$B$33) -> 0.47239562 | E11: {=INDEX(Working_Data!$D$2:$AD$2000,MATCH(1,(Working_Data!$A$2:$A$2000=$A11)*(Working_Data!$B$2:$B$2000=YEAR(E$5))*(Working_Data!$C$2:$C$2000=TEXT(E$5,"mmmm")),0),MATCH($B11,Working_Data!$D$1:$AD$1,0))} -> 147.7 | F11: {=INDEX(Working_Data!$D$2:$AD$2000,MATCH(1,(Working_Data!$A$2:$A$2000=$A11)*(Working_Data!$B$2:$B$2000=YEAR(F$5))*(Working_Data!$C$2:$C$2000=TEXT(F$5,"mmmm")),0),MATCH($B11,Working_Data!$D$1:$AD$1,0))} -> 149.6 | G11: {=INDEX(Working_Data!$D$2:$AD$2000,MATCH(1,(Working_Data!$A$2:$A$2000=$A11)*(Working_Data!$B$2:$B$2000=YEAR(G$5))*(Working_Data!$C$2:$C$2000=TEXT(G$5,"mmmm")),0),MATCH($B11,Working_Data!$D$1:$AD$1,0))} -> 150.7 | H11: {=INDEX(Working_Data!$D$2:$AD$2000,MATCH(1,(Working_Data!$A$2:$A$2000=$A11)*(Working_Data!$B$2:$B$2000=YEAR(H$5))*(Working_Data!$C$2:$C$2000=TEXT(H$5,"mmmm")),0),MATCH($B11,Working_Data!$D$1:$AD$1,0))} -> 153.7 | I11: {=INDEX(Working_Data!$D$2:$AD$2000,MATCH(1,(Working_Data!$A$2:$A$2000=$A11)*(Working_Data!$B$2:$B$2000=YEAR(I$5))*(Working_Data!$C$2:$C$2000=TEXT(I$5,"mmmm")),0),MATCH($B11,Working_Data!$D$1:$AD$1,0))} -> 164.4 | J11: {=INDEX(Working_Data!$D$2:$AD$2000,MATCH(1,(Working_Data!$A$2:$A$2000=$A11)*(Working_Data!$B$2:$B$2000=YEAR(J$5))*(Working_Data!$C$2:$C$2000=TEXT(J$5,"mmmm")),0),MATCH($B11,Working_Data!$D$1:$AD$1,0))} -> 167.1 | K11: {=INDEX(Working_Data!$D$2:$AD$2000,MATCH(1,(Working_Data!$A$2:$A$2000=$A11)*(Working_Data!$B$2:$B$2000=YEAR(K$5))*(Working_Data!$C$2:$C$2000=TEXT(K$5,"mmmm")),0),MATCH($B11,Working_Data!$D$1:$AD$1,0))} -> 164.6 | L11: {=INDEX(Working_Data!$D$2:$AD$2000,MATCH(1,(Working_Data!$A$2:$A$2000=$A11)*(Working_Data!$B$2:$B$2000=YEAR(L$5))*(Working_Data!$C$2:$C$2000=TEXT(L$5,"mmmm")),0),MATCH($B11,Working_Data!$D$1:$AD$1,0))} -> 163.9 | ... AH11: {=INDEX(Working_Data!$D$2:$AD$2000,MATCH(1,(Working_Data!$A$2:$A$2000=$A11)*(Working_Data!$B$2:$B$2000=YEAR(AH$5))*(Working_Data!$C$2:$C$2000=TEXT(AH$5,"mmmm")),0),MATCH($B11,Working_Data!$D$1:$AD$1,0))} -> 172.2 | AI11: - | AJ11: - | AK11: - | AL11: - | AM11: - | AN11: - | AO11: -
A12: Rural+Urban | B12: Vegetables | C12: =_xlfn.XLOOKUP(B12,CPI_Category_Mapping[Category],CPI_Category_Mapping[New Food Category]) -> Food | D12: =CORREL(F12:AH12,'Crude Oil Price'!$B$5:$B$33) -> 0.34646081 | E12: {=INDEX(Working_Data!$D$2:$AD$2000,MATCH(1,(Working_Data!$A$2:$A$2000=$A12)*(Working_Data!$B$2:$B$2000=YEAR(E$5))*(Working_Data!$C$2:$C$2000=TEXT(E$5,"mmmm")),0),MATCH($B12,Working_Data!$D$1:$AD$1,0))} -> 230.5 | F12: {=INDEX(Working_Data!$D$2:$AD$2000,MATCH(1,(Working_Data!$A$2:$A$2000=$A12)*(Working_Data!$B$2:$B$2000=YEAR(F$5))*(Working_Data!$C$2:$C$2000=TEXT(F$5,"mmmm")),0),MATCH($B12,Working_Data!$D$1:$AD$1,0))} -> 194.2 | G12: {=INDEX(Working_Data!$D$2:$AD$2000,MATCH(1,(Working_Data!$A$2:$A$2000=$A12)*(Working_Data!$B$2:$B$2000=YEAR(G$5))*(Working_Data!$C$2:$C$2000=TEXT(G$5,"mmmm")),0),MATCH($B12,Working_Data!$D$1:$AD$1,0))} -> 160 | H12: {=INDEX(Working_Data!$D$2:$AD$2000,MATCH(1,(Working_Data!$A$2:$A$2000=$A12)*(Working_Data!$B$2:$B$2000=YEAR(H$5))*(Working_Data!$C$2:$C$2000=TEXT(H$5,"mmmm")),0),MATCH($B12,Working_Data!$D$1:$AD$1,0))} -> 149.5 | I12: {=INDEX(Working_Data!$D$2:$AD$2000,MATCH(1,(Working_Data!$A$2:$A$2000=$A12)*(Working_Data!$B$2:$B$2000=YEAR(I$5))*(Working_Data!$C$2:$C$2000=TEXT(I$5,"mmmm")),0),MATCH($B12,Working_Data!$D$1:$AD$1,0))} -> 144.1 | J12: {=INDEX(Working_Data!$D$2:$AD$2000,MATCH(1,(Working_Data!$A$2:$A$2000=$A12)*(Working_Data!$B$2:$B$2000=YEAR(J$5))*(Working_Data!$C$2:$C$2000=TEXT(J$5,"mmmm")),0),MATCH($B12,Working_Data!$D$1:$AD$1,0))} -> 147.9 | K12: {=INDEX(Working_Data!$D$2:$AD$2000,MATCH(1,(Working_Data!$A$2:$A$2000=$A12)*(Working_Data!$B$2:$B$2000=YEAR(K$5))*(Working_Data!$C$2:$C$2000=TEXT(K$5,"mmmm")),0),MATCH($B12,Working_Data!$D$1:$AD$1,0))} -> 155.4 | L12: {=INDEX(Working_Data!$D$2:$AD$2000,MATCH(1,(Working_Data!$A$2:$A$2000=$A12)*(Working_Data!$B$2:$B$2000=YEAR(L$5))*(Working_Data!$C$2:$C$2000=TEXT(L$5,"mmmm")),0),MATCH($B12,Working_Data!$D$1:$AD$1,0))} -> 164.2 | ... AH12: {=INDEX(Working_Data!$D$2:$AD$2000,MATCH(1,(Working_Data!$A$2:$A$2000=$A12)*(Working_Data!$B$2:$B$2000=YEAR(AH$5))*(Working_Data!$C$2:$C$2000=TEXT(AH$5,"mmmm")),0),MATCH($B12,Working_Data!$D$1:$AD$1,0))} -> 161 | AI12: - | AJ12: - | AK12: - | AL12: - | AM12: - | AN12: - | AO12: -
A13: Rural+Urban | B13: Pulses and products | C13: =_xlfn.XLOOKUP(B13,CPI_Category_Mapping[Category],CPI_Category_Mapping[New Food Category]) -> Food | D13: =CORREL(F13:AH13,'Crude Oil Price'!$B$5:$B$33) -> 0.17606973 | E13: {=INDEX(Working_Data!$D$2:$AD$2000,MATCH(1,(Working_Data!$A$2:$A$2000=$A13)*(Working_Data!$B$2:$B$2000=YEAR(E$5))*(Working_Data!$C$2:$C$2000=TEXT(E$5,"mmmm")),0),MATCH($B13,Working_Data!$D$1:$AD$1,0))} -> 160.2 | F13: {=INDEX(Working_Data!$D$2:$AD$2000,MATCH(1,(Working_Data!$A$2:$A$2000=$A13)*(Working_Data!$B$2:$B$2000=YEAR(F$5))*(Working_Data!$C$2:$C$2000=TEXT(F$5,"mmmm")),0),MATCH($B13,Working_Data!$D$1:$AD$1,0))} -> 160.4 | G13: {=INDEX(Working_Data!$D$2:$AD$2000,MATCH(1,(Working_Data!$A$2:$A$2000=$A13)*(Working_Data!$B$2:$B$2000=YEAR(G$5))*(Working_Data!$C$2:$C$2000=TEXT(G$5,"mmmm")),0),MATCH($B13,Working_Data!$D$1:$AD$1,0))} -> 158.8 | H13: {=INDEX(Working_Data!$D$2:$AD$2000,MATCH(1,(Working_Data!$A$2:$A$2000=$A13)*(Working_Data!$B$2:$B$2000=YEAR(H$5))*(Working_Data!$C$2:$C$2000=TEXT(H$5,"mmmm")),0),MATCH($B13,Working_Data!$D$1:$AD$1,0))} -> 159.8 | I13: {=INDEX(Working_Data!$D$2:$AD$2000,MATCH(1,(Working_Data!$A$2:$A$2000=$A13)*(Working_Data!$B$2:$B$2000=YEAR(I$5))*(Working_Data!$C$2:$C$2000=TEXT(I$5,"mmmm")),0),MATCH($B13,Working_Data!$D$1:$AD$1,0))} -> 161.7 | J13: {=INDEX(Working_Data!$D$2:$AD$2000,MATCH(1,(Working_Data!$A$2:$A$2000=$A13)*(Working_Data!$B$2:$B$2000=YEAR(J$5))*(Working_Data!$C$2:$C$2000=TEXT(J$5,"mmmm")),0),MATCH($B13,Working_Data!$D$1:$AD$1,0))} -> 165.4 | K13: {=INDEX(Working_Data!$D$2:$AD$2000,MATCH(1,(Working_Data!$A$2:$A$2000=$A13)*(Working_Data!$B$2:$B$2000=YEAR(K$5))*(Working_Data!$C$2:$C$2000=TEXT(K$5,"mmmm")),0),MATCH($B13,Working_Data!$D$1:$AD$1,0))} -> 166 | L13: {=INDEX(Working_Data!$D$2:$AD$2000,MATCH(1,(Working_Data!$A$2:$A$2000=$A13)*(Working_Data!$B$2:$B$2000=YEAR(L$5))*(Working_Data!$C$2:$C$2000=TEXT(L$5,"mmmm")),0),MATCH($B13,Working_Data!$D$1:$AD$1,0))} -> 164 | ... AH13: {=INDEX(Working_Data!$D$2:$AD$2000,MATCH(1,(Working_Data!$A$2:$A$2000=$A13)*(Working_Data!$B$2:$B$2000=YEAR(AH$5))*(Working_Data!$C$2:$C$2000=TEXT(AH$5,"mmmm")),0),MATCH($B13,Working_Data!$D$1:$AD$1,0))} -> 175.6 | AI13: - | AJ13: - | AK13: - | AL13: - | AM13: - | AN13: - | AO13: -
A14: Rural+Urban | B14: Sugar and Confectionery | C14: =_xlfn.XLOOKUP(B14,CPI_Category_Mapping[Category],CPI_Category_Mapping[New Food Category]) -> Food | D14: =CORREL(F14:AH14,'Crude Oil Price'!$B$5:$B$33) -> 0.50195772 | E14: {=INDEX(Working_Data!$D$2:$AD$2000,MATCH(1,(Working_Data!$A$2:$A$2000=$A14)*(Working_Data!$B$2:$B$2000=YEAR(E$5))*(Working_Data!$C$2:$C$2000=TEXT(E$5,"mmmm")),0),MATCH($B14,Working_Data!$D$1:$AD$1,0))} -> 115.3 | F14: {=INDEX(Working_Data!$D$2:$AD$2000,MATCH(1,(Working_Data!$A$2:$A$2000=$A14)*(Working_Data!$B$2:$B$2000=YEAR(F$5))*(Working_Data!$C$2:$C$2000=TEXT(F$5,"mmmm")),0),MATCH($B14,Working_Data!$D$1:$AD$1,0))} -> 114.6 | G14: {=INDEX(Working_Data!$D$2:$AD$2000,MATCH(1,(Working_Data!$A$2:$A$2000=$A14)*(Working_Data!$B$2:$B$2000=YEAR(G$5))*(Working_Data!$C$2:$C$2000=TEXT(G$5,"mmmm")),0),MATCH($B14,Working_Data!$D$1:$AD$1,0))} -> 112.8 | H14: {=INDEX(Working_Data!$D$2:$AD$2000,MATCH(1,(Working_Data!$A$2:$A$2000=$A14)*(Working_Data!$B$2:$B$2000=YEAR(H$5))*(Working_Data!$C$2:$C$2000=TEXT(H$5,"mmmm")),0),MATCH($B14,Working_Data!$D$1:$AD$1,0))} -> 112.6 | I14: {=INDEX(Working_Data!$D$2:$AD$2000,MATCH(1,(Working_Data!$A$2:$A$2000=$A14)*(Working_Data!$B$2:$B$2000=YEAR(I$5))*(Working_Data!$C$2:$C$2000=TEXT(I$5,"mmmm")),0),MATCH($B14,Working_Data!$D$1:$AD$1,0))} -> 113.1 | J14: {=INDEX(Working_Data!$D$2:$AD$2000,MATCH(1,(Working_Data!$A$2:$A$2000=$A14)*(Working_Data!$B$2:$B$2000=YEAR(J$5))*(Working_Data!$C$2:$C$2000=TEXT(J$5,"mmmm")),0),MATCH($B14,Working_Data!$D$1:$AD$1,0))} -> 114.8 | K14: {=INDEX(Working_Data!$D$2:$AD$2000,MATCH(1,(Working_Data!$A$2:$A$2000=$A14)*(Working_Data!$B$2:$B$2000=YEAR(K$5))*(Working_Data!$C$2:$C$2000=TEXT(K$5,"mmmm")),0),MATCH($B14,Working_Data!$D$1:$AD$1,0))} -> 115.1 | L14: {=INDEX(Working_Data!$D$2:$AD$2000,MATCH(1,(Working_Data!$A$2:$A$2000=$A14)*(Working_Data!$B$2:$B$2000=YEAR(L$5))*(Working_Data!$C$2:$C$2000=TEXT(L$5,"mmmm")),0),MATCH($B14,Working_Data!$D$1:$AD$1,0))} -> 114.5 | ... AH14: {=INDEX(Working_Data!$D$2:$AD$2000,MATCH(1,(Working_Data!$A$2:$A$2000=$A14)*(Working_Data!$B$2:$B$2000=YEAR(AH$5))*(Working_Data!$C$2:$C$2000=TEXT(AH$5,"mmmm")),0),MATCH($B14,Working_Data!$D$1:$AD$1,0))} -> 122.7 | AI14: - | AJ14: - | AK14: - | AL14: - | AM14: - | AN14: - | AO14: -
A15: Rural+Urban | B15: Spices | C15: =_xlfn.XLOOKUP(B15,CPI_Category_Mapping[Category],CPI_Category_Mapping[New Food Category]) -> Food | D15: =CORREL(F15:AH15,'Crude Oil Price'!$B$5:$B$33) -> 0.33675352 | E15: {=INDEX(Working_Data!$D$2:$AD$2000,MATCH(1,(Working_Data!$A$2:$A$2000=$A15)*(Working_Data!$B$2:$B$2000=YEAR(E$5))*(Working_Data!$C$2:$C$2000=TEXT(E$5,"mmmm")),0),MATCH($B15,Working_Data!$D$1:$AD$1,0))} -> 163 | F15: {=INDEX(Working_Data!$D$2:$AD$2000,MATCH(1,(Working_Data!$A$2:$A$2000=$A15)*(Working_Data!$B$2:$B$2000=YEAR(F$5))*(Working_Data!$C$2:$C$2000=TEXT(F$5,"mmmm")),0),MATCH($B15,Working_Data!$D$1:$AD$1,0))} -> 164 | G15: {=INDEX(Working_Data!$D$2:$AD$2000,MATCH(1,(Working_Data!$A$2:$A$2000=$A15)*(Working_Data!$B$2:$B$2000=YEAR(G$5))*(Working_Data!$C$2:$C$2000=TEXT(G$5,"mmmm")),0),MATCH($B15,Working_Data!$D$1:$AD$1,0))} -> 164.2 | H15: {=INDEX(Working_Data!$D$2:$AD$2000,MATCH(1,(Working_Data!$A$2:$A$2000=$A15)*(Working_Data!$B$2:$B$2000=YEAR(H$5))*(Working_Data!$C$2:$C$2000=TEXT(H$5,"mmmm")),0),MATCH($B15,Working_Data!$D$1:$AD$1,0))} -> 163.5 | I15: {=INDEX(Working_Data!$D$2:$AD$2000,MATCH(1,(Working_Data!$A$2:$A$2000=$A15)*(Working_Data!$B$2:$B$2000=YEAR(I$5))*(Working_Data!$C$2:$C$2000=TEXT(I$5,"mmmm")),0),MATCH($B15,Working_Data!$D$1:$AD$1,0))} -> 163.9 | J15: {=INDEX(Working_Data!$D$2:$AD$2000,MATCH(1,(Working_Data!$A$2:$A$2000=$A15)*(Working_Data!$B$2:$B$2000=YEAR(J$5))*(Working_Data!$C$2:$C$2000=TEXT(J$5,"mmmm")),0),MATCH($B15,Working_Data!$D$1:$AD$1,0))} -> 168.2 | K15: {=INDEX(Working_Data!$D$2:$AD$2000,MATCH(1,(Working_Data!$A$2:$A$2000=$A15)*(Working_Data!$B$2:$B$2000=YEAR(K$5))*(Working_Data!$C$2:$C$2000=TEXT(K$5,"mmmm")),0),MATCH($B15,Working_Data!$D$1:$AD$1,0))} -> 168.5 | L15: {=INDEX(Working_Data!$D$2:$AD$2000,MATCH(1,(Working_Data!$A$2:$A$2000=$A15)*(Working_Data!$B$2:$B$2000=YEAR(L$5))*(Working_Data!$C$2:$C$2000=TEXT(L$5,"mmmm")),0),MATCH($B15,Working_Data!$D$1:$AD$1,0))} -> 168.3 | ... AH15: {=INDEX(Working_Data!$D$2:$AD$2000,MATCH(1,(Working_Data!$A$2:$A$2000=$A15)*(Working_Data!$B$2:$B$2000=YEAR(AH$5))*(Working_Data!$C$2:$C$2000=TEXT(AH$5,"mmmm")),0),MATCH($B15,Working_Data!$D$1:$AD$1,0))} -> 218 | AI15: - | AJ15: - | AK15: - | AL15: - | AM15: - | AN15: - | AO15: -
A16: Rural+Urban | B16: Non-alcoholic beverages | C16: =_xlfn.XLOOKUP(B16,CPI_Category_Mapping[Category],CPI_Category_Mapping[New Food Category]) -> Food | D16: =CORREL(F16:AH16,'Crude Oil Price'!$B$5:$B$33) -> 0.55440615 | E16: {=INDEX(Working_Data!$D$2:$AD$2000,MATCH(1,(Working_Data!$A$2:$A$2000=$A16)*(Working_Data!$B$2:$B$2000=YEAR(E$5))*(Working_Data!$C$2:$C$2000=TEXT(E$5,"mmmm")),0),MATCH($B16,Working_Data!$D$1:$AD$1,0))} -> 149.2 | F16: {=INDEX(Working_Data!$D$2:$AD$2000,MATCH(1,(Working_Data!$A$2:$A$2000=$A16)*(Working_Data!$B$2:$B$2000=YEAR(F$5))*(Working_Data!$C$2:$C$2000=TEXT(F$5,"mmmm")),0),MATCH($B16,Working_Data!$D$1:$AD$1,0))} -> 151.8 | G16: {=INDEX(Working_Data!$D$2:$AD$2000,MATCH(1,(Working_Data!$A$2:$A$2000=$A16)*(Working_Data!$B$2:$B$2000=YEAR(G$5))*(Working_Data!$C$2:$C$2000=TEXT(G$5,"mmmm")),0),MATCH($B16,Working_Data!$D$1:$AD$1,0))} -> 155.5 | H16: {=INDEX(Working_Data!$D$2:$AD$2000,MATCH(1,(Working_Data!$A$2:$A$2000=$A16)*(Working_Data!$B$2:$B$2000=YEAR(H$5))*(Working_Data!$C$2:$C$2000=TEXT(H$5,"mmmm")),0),MATCH($B16,Working_Data!$D$1:$AD$1,0))} -> 156.5 | I16: {=INDEX(Working_Data!$D$2:$AD$2000,MATCH(1,(Working_Data!$A$2:$A$2000=$A16)*(Working_Data!$B$2:$B$2000=YEAR(I$5))*(Working_Data!$C$2:$C$2000=TEXT(I$5,"mmmm")),0),MATCH($B16,Working_Data!$D$1:$AD$1,0))} -> 157.6 | J16: {=INDEX(Working_Data!$D$2:$AD$2000,MATCH(1,(Working_Data!$A$2:$A$2000=$A16)*(Working_Data!$B$2:$B$2000=YEAR(J$5))*(Working_Data!$C$2:$C$2000=TEXT(J$5,"mmmm")),0),MATCH($B16,Working_Data!$D$1:$AD$1,0))} -> 159.3 | K16: {=INDEX(Working_Data!$D$2:$AD$2000,MATCH(1,(Working_Data!$A$2:$A$2000=$A16)*(Working_Data!$B$2:$B$2000=YEAR(K$5))*(Working_Data!$C$2:$C$2000=TEXT(K$5,"mmmm")),0),MATCH($B16,Working_Data!$D$1:$AD$1,0))} -> 160 | L16: {=INDEX(Working_Data!$D$2:$AD$2000,MATCH(1,(Working_Data!$A$2:$A$2000=$A16)*(Working_Data!$B$2:$B$2000=YEAR(L$5))*(Working_Data!$C$2:$C$2000=TEXT(L$5,"mmmm")),0),MATCH($B16,Working_Data!$D$1:$AD$1,0))} -> 160.9 | ... AH16: {=INDEX(Working_Data!$D$2:$AD$2000,MATCH(1,(Working_Data!$A$2:$A$2000=$A16)*(Working_Data!$B$2:$B$2000=YEAR(AH$5))*(Working_Data!$C$2:$C$2000=TEXT(AH$5,"mmmm")),0),MATCH($B16,Working_Data!$D$1:$AD$1,0))} -> 173.4 | AI16: - | AJ16: - | AK16: - | AL16: - | AM16: - | AN16: - | AO16: -
A17: Rural+Urban | B17: Prepared meals, snacks, sweets etc. | C17: =_xlfn.XLOOKUP(B17,CPI_Category_Mapping[Category],CPI_Category_Mapping[New Food Category]) -> Luxury | D17: =CORREL(F17:AH17,'Crude Oil Price'!$B$5:$B$33) -> 0.4833618 | E17: {=INDEX(Working_Data!$D$2:$AD$2000,MATCH(1,(Working_Data!$A$2:$A$2000=$A17)*(Working_Data!$B$2:$B$2000=YEAR(E$5))*(Working_Data!$C$2:$C$2000=TEXT(E$5,"mmmm")),0),MATCH($B17,Working_Data!$D$1:$AD$1,0))} -> 164.8 | F17: {=INDEX(Working_Data!$D$2:$AD$2000,MATCH(1,(Working_Data!$A$2:$A$2000=$A17)*(Working_Data!$B$2:$B$2000=YEAR(F$5))*(Working_Data!$C$2:$C$2000=TEXT(F$5,"mmmm")),0),MATCH($B17,Working_Data!$D$1:$AD$1,0))} -> 165.6 | G17: {=INDEX(Working_Data!$D$2:$AD$2000,MATCH(1,(Working_Data!$A$2:$A$2000=$A17)*(Working_Data!$B$2:$B$2000=YEAR(G$5))*(Working_Data!$C$2:$C$2000=TEXT(G$5,"mmmm")),0),MATCH($B17,Working_Data!$D$1:$AD$1,0))} -> 167.5 | H17: {=INDEX(Working_Data!$D$2:$AD$2000,MATCH(1,(Working_Data!$A$2:$A$2000=$A17)*(Working_Data!$B$2:$B$2000=YEAR(H$5))*(Working_Data!$C$2:$C$2000=TEXT(H$5,"mmmm")),0),MATCH($B17,Working_Data!$D$1:$AD$1,0))} -> 168.2 | I17: {=INDEX(Working_Data!$D$2:$AD$2000,MATCH(1,(Working_Data!$A$2:$A$2000=$A17)*(Working_Data!$B$2:$B$2000=YEAR(I$5))*(Working_Data!$C$2:$C$2000=TEXT(I$5,"mmmm")),0),MATCH($B17,Working_Data!$D$1:$AD$1,0))} -> 168.9 | J17: {=INDEX(Working_Data!$D$2:$AD$2000,MATCH(1,(Working_Data!$A$2:$A$2000=$A17)*(Working_Data!$B$2:$B$2000=YEAR(J$5))*(Working_Data!$C$2:$C$2000=TEXT(J$5,"mmmm")),0),MATCH($B17,Working_Data!$D$1:$AD$1,0))} -> 170.4 | K17: {=INDEX(Working_Data!$D$2:$AD$2000,MATCH(1,(Working_Data!$A$2:$A$2000=$A17)*(Working_Data!$B$2:$B$2000=YEAR(K$5))*(Working_Data!$C$2:$C$2000=TEXT(K$5,"mmmm")),0),MATCH($B17,Working_Data!$D$1:$AD$1,0))} -> 172.4 | L17: {=INDEX(Working_Data!$D$2:$AD$2000,MATCH(1,(Working_Data!$A$2:$A$2000=$A17)*(Working_Data!$B$2:$B$2000=YEAR(L$5))*(Working_Data!$C$2:$C$2000=TEXT(L$5,"mmmm")),0),MATCH($B17,Working_Data!$D$1:$AD$1,0))} -> 172.2 | ... AH17: {=INDEX(Working_Data!$D$2:$AD$2000,MATCH(1,(Working_Data!$A$2:$A$2000=$A17)*(Working_Data!$B$2:$B$2000=YEAR(AH$5))*(Working_Data!$C$2:$C$2000=TEXT(AH$5,"mmmm")),0),MATCH($B17,Working_Data!$D$1:$AD$1,0))} -> 194.2 | AI17: - | AJ17: - | AK17: - | AL17: - | AM17: - | AN17: - | AO17: -
... A31: Rural+Urban | B31: Miscellaneous | C31: =_xlfn.XLOOKUP(B31,CPI_Category_Mapping[Category],CPI_Category_Mapping[New Food Category]) -> Other expenses | D31: =CORREL(F31:AH31,'Crude Oil Price'!$B$5:$B$33) -> 0.53388417 | E31: {=INDEX(Working_Data!$D$2:$AD$2000,MATCH(1,(Working_Data!$A$2:$A$2000=$A31)*(Working_Data!$B$2:$B$2000=YEAR(E$5))*(Working_Data!$C$2:$C$2000=TEXT(E$5,"mmmm")),0),MATCH($B31,Working_Data!$D$1:$AD$1,0))} -> 151.2 | F31: {=INDEX(Working_Data!$D$2:$AD$2000,MATCH(1,(Working_Data!$A$2:$A$2000=$A31)*(Working_Data!$B$2:$B$2000=YEAR(F$5))*(Working_Data!$C$2:$C$2000=TEXT(F$5,"mmmm")),0),MATCH($B31,Working_Data!$D$1:$AD$1,0))} -> 151.9 | G31: {=INDEX(Working_Data!$D$2:$AD$2000,MATCH(1,(Working_Data!$A$2:$A$2000=$A31)*(Working_Data!$B$2:$B$2000=YEAR(G$5))*(Working_Data!$C$2:$C$2000=TEXT(G$5,"mmmm")),0),MATCH($B31,Working_Data!$D$1:$AD$1,0))} -> 153.4 | H31: {=INDEX(Working_Data!$D$2:$AD$2000,MATCH(1,(Working_Data!$A$2:$A$2000=$A31)*(Working_Data!$B$2:$B$2000=YEAR(H$5))*(Working_Data!$C$2:$C$2000=TEXT(H$5,"mmmm")),0),MATCH($B31,Working_Data!$D$1:$AD$1,0))} -> 153.8 | I31: {=INDEX(Working_Data!$D$2:$AD$2000,MATCH(1,(Working_Data!$A$2:$A$2000=$A31)*(Working_Data!$B$2:$B$2000=YEAR(I$5))*(Working_Data!$C$2:$C$2000=TEXT(I$5,"mmmm")),0),MATCH($B31,Working_Data!$D$1:$AD$1,0))} -> 154.4 | J31: {=INDEX(Working_Data!$D$2:$AD$2000,MATCH(1,(Working_Data!$A$2:$A$2000=$A31)*(Working_Data!$B$2:$B$2000=YEAR(J$5))*(Working_Data!$C$2:$C$2000=TEXT(J$5,"mmmm")),0),MATCH($B31,Working_Data!$D$1:$AD$1,0))} -> 156.8 | K31: {=INDEX(Working_Data!$D$2:$AD$2000,MATCH(1,(Working_Data!$A$2:$A$2000=$A31)*(Working_Data!$B$2:$B$2000=YEAR(K$5))*(Working_Data!$C$2:$C$2000=TEXT(K$5,"mmmm")),0),MATCH($B31,Working_Data!$D$1:$AD$1,0))} -> 157.6 | L31: {=INDEX(Working_Data!$D$2:$AD$2000,MATCH(1,(Working_Data!$A$2:$A$2000=$A31)*(Working_Data!$B$2:$B$2000=YEAR(L$5))*(Working_Data!$C$2:$C$2000=TEXT(L$5,"mmmm")),0),MATCH($B31,Working_Data!$D$1:$AD$1,0))} -> 159 | ... AH31: {=INDEX(Working_Data!$D$2:$AD$2000,MATCH(1,(Working_Data!$A$2:$A$2000=$A31)*(Working_Data!$B$2:$B$2000=YEAR(AH$5))*(Working_Data!$C$2:$C$2000=TEXT(AH$5,"mmmm")),0),MATCH($B31,Working_Data!$D$1:$AD$1,0))} -> 175.7 | AI31: - | AJ31: - | AK31: - | AL31: - | AM31: - | AN31: - | AO31: -
A34: Summary
A35: Category | B35: New Category | C35: Correlation
A36: =_xlfn.XLOOKUP(MAX(D6:D31),D6:D31,B6:B31) -> Oils and fats | B36: =_xlfn.XLOOKUP(MAX(D6:D31),D6:D31,C6:C31) -> Food | C36: =MAX(D6:D31) -> 0.80946651
A39: Insight: The analysis examines the relationship between monthly crude oil prices and CPI category price indices from January 2021 to May 2023. Among the categories analysed, Oils and fats shows the strongest positive correlation with imported crude oil prices, with a correlation coefficient of 80.9%. This indicates a strong statistical association between the two series during the study period. However, correlation does not establish a causal relationship.

Sheet Crude Oil Price
A1: Source | B1: https://ppac.gov.in/prices/international-prices-of-crude-oil
A3: Month-Year | B3: Crude Oil Price ($/bbl) | C3: Oil Price MoM % | AA3: Month | AB3: Year | AC3: Imported Crude Oil Price ($/bbl)
A4: 44166 | B4: 49.84 | C4: - | AA4: January | AB4: 2021
A5: 44197 | B5: 54.79 | C5: =(B5-B4)/B4 -> 0.099317817 | AA5: February | AB5: 2021
A6: 44228 | B6: 61.22 | C6: =(B6-B5)/B5 -> 0.11735718 | AA6: March | AB6: 2021
A7: 44256 | B7: 64.73 | C7: =(B7-B6)/B6 -> 0.057334205 | AA7: April | AB7: 2021
A8: 44287 | B8: 63.4 | C8: =(B8-B7)/B7 -> -0.020546887 | AA8: May | AB8: 2021
A9: 44317 | B9: 66.95 | C9: =(B9-B8)/B8 -> 0.055993691 | AA9: June | AB9: 2021
A10: 44348 | B10: 71.98 | C10: =(B10-B9)/B9 -> 0.075130695 | AA10: July | AB10: 2021
A11: 44378 | B11: 73.54 | C11: =(B11-B10)/B10 -> 0.021672687 | AA11: August | AB11: 2021
A12: 44409 | B12: 69.8 | C12: =(B12-B11)/B11 -> -0.050856677 | AA12: September | AB12: 2021
A13: 44440 | B13: 73.13 | C13: =(B13-B12)/B12 -> 0.047707736 | AA13: October | AB13: 2021
A14: 44470 | B14: 82.11 | C14: =(B14-B13)/B13 -> 0.12279502 | AA14: November | AB14: 2021
A15: 44501 | B15: 80.64 | C15: =(B15-B14)/B14 -> -0.017902813 | AA15: December | AB15: 2021
A16: 44531 | B16: 73.3 | C16: =(B16-B15)/B15 -> -0.091021825 | AA16: January | AB16: 2022
... A33: 45047 | B33: 74.98 | C33: =(B33-B32)/B32 -> -0.1048233 | AA33: June | AB33: 2023
AA34: July | AB34: 2023
AA35: August | AB35: 2023
AA36: September | AB36: 2023
AA37: October | AB37: 2023
AA38: November | AB38: 2023
AA39: December | AB39: 2023

Sheet Notes
B1: Password | C1: IndiaCPI
B4: Missing values | C4: Missing observations were imputed using a 3-observation moving-average approach. The missing observation was excluded, and the three nearest available monthly observations from the same sector and CPI category were averaged."
C5: which formula is used to impute the values
C6: moving average formula used to fill the cell than paste them as values
D7: April | E7: ma | F7: ma
B8: 2020 | C8: February | D8: 145.1
B9: 2020 | C9: March | D9: 148.7
B10: 2020 | C10: April | E10: =AVERAGE(D8:D9,D12) -> 147.8
B11: 2020 | C11: May | E11: =AVERAGE(D9:D12,D13) -> 149.15
B12: 2020 | C12: June | D12: 149.6
